Workbook

Sheet Read Me
A1: Purpose | B1: One hierarchy that every MDP geographic label points to. Fix a place once on Hierarchy and every label that maps to it follows.
A3: HIERARCHY LEVELS
A4: Global | B4: Root. Also holds non-regional buckets (International, Domestic, Rest of World, Other) and multi-region composites
A5: Region | B5: AMER (Americas) · EMEA (Europe, Middle East, and Africa) · APAC (Asia-Pacific)
A6: Sub-region | B6: AMER: North America (NORAM), Latin America (LATAM) · EMEA: Europe, Middle East, Africa · APAC: South Asia, East Asia, Southeast Asia (ASEAN), Oceania (ANZ)
A7: Country | B7: All 242 inhabited ISO 3166 countries/territories plus Kosovo, with ISO3. Groupings column shows memberships (Western Europe, EU, Nordics, GCC, Greater China…)
A8: State/Province | B8: US, Canada, Mexico, Brazil, UK, Germany, France, UAE, Saudi Arabia, South Africa, Nigeria, India, China, Japan, Indonesia, Malaysia, Australia, New Zealand. US regions (incl. Census divisions) and cities also sit under their country
A9: EMEA sub-regions | B9: Europe · Middle East · Africa (components: North Africa, Sub-Saharan Africa and its West/East/Central/Southern Africa). MENA = Middle East + North Africa, kept as a grouping
A10: Components | B10: Sit inside one sub-region: e.g. Western Europe, CEE, Nordics, DACH under Europe; Middle East, North Africa, GCC under MENA; Greater China, Northeast Asia under East Asia; Caribbean, Central/South America under LATAM
A11: Tree View | B11: Indented view of Global > Region > Sub-region > Country > State/Province (and business regions) > City, in the same order as Hierarchy
A12: Business groupings | B12: NOLA, SOLA, CAC, NAFTA/USMCA, Mercosur, Pacific Alliance, CEEMEA, Northern/Central/Southeast Europe, Scandinavia, Maghreb, West/East/Central/Southern Africa, Mekong; market groupings BRIC, BRICS, G7, OECD, Frontier
A13: Cities | B13: ~200 major business cities and metro areas (Greater Toronto Area, Bay Area, Dallas–Fort Worth…) placed under state/province where known
A15: MAPPING RULES
A16: 1. Smallest container | B16: Map each label to the smallest node that fully contains what it describes (China + Hong Kong → Greater China)
A17: 2. Scope | B17: Exact = same geography · Partial = subset, e.g. 'Europe excl. UK' · Residual = 'Other X' · Combined = spans several nodes under one parent
A18: 3. International | B18: When a filing gives only broad non-US reporting (Foreign, Non-US, Outside the U.S.), use International
A19: 4. Cross-region | B19: Labels spanning regions go to a Multi-region node, never to one of the regions they span
A20: 5. Not a place | B20: Segments, facilities, tax categories and scraper artifacts go on Excluded
A22: HOW TO MAINTAIN
A23: New label | B23: Paste it into New Label Check. If Auto-matched, add it to Label Map with that node. If UNMAPPED, add a Label Map row and pick a node from the dropdown in column D
A24: New place | B24: Add one row on Hierarchy only when no existing node fits
A25: Reclassify | B25: Change Region/Sub-region on the node's Hierarchy row; all mapped labels update
A26: Blue text | B26: Inputs you edit. Black text is formula-driven
A28: COUNTS
A29: Hierarchy nodes | B29: =COUNTA(Hierarchy!A2:A1295) -> 1294
A30: Labels mapped | B30: =COUNTA('Label Map'!A2:A2019) -> 2018
A31: Labels pre-seeded for future scrapes | B31: =COUNTIF('Label Map'!M2:M2019,"Pre-seeded") -> 1341
A32: Labels changed vs previous | B32: =COUNTIF('Label Map'!M2:M2019,"Changed") -> 240
A33: Labels excluded | B33: =COUNTA(Excluded!A2:A19) -> 18
A34: Key conflicts (should be 0) | B34: =COUNTIF('Label Map'!O2:O2019,"CONFLICT") -> 0
A35: Node not found (should be 0) | B35: =COUNTIF('Label Map'!F2:F2019,"NODE NOT FOUND") -> 0
A36: Open decisions | B36: See Decisions sheet
A38: SOURCES
A39: UN M49 | B39: UN Statistics Division M49 standard (region, sub-region, intermediate region, LDC/LLDC/SIDS) via the datasets/country-codes open dataset: github.com/datasets/country-codes
A40: World Bank | B40: World Bank Country and Lending Groups, FY27 (thresholds on 2025 GNI per capita, Atlas method): datahelpdesk.worldbank.org/knowledgebase/articles/906519
A41: States/provinces | B41: ISO 3166-2 subdivisions (English names used; local spellings pre-seeded as aliases)

Sheet Hierarchy
A1: Standard Node | B1: Level | C1: Global | D1: Region | E1: Sub-region | F1: Country | G1: ISO3 | H1: State/Province | I1: City | J1: Parent Node | K1: Groupings | L1: UN M49 Region | M1: UN M49 Sub-region | N1: UN M49 Intermediate Region | O1: World Bank Region (FY27) | P1: World Bank Income Group (FY27) | Q1: Definition / Notes | R1: Labels Mapped
A2: Global | B2: Global | C2: Global | D2: Global | Q2: Root of the hierarchy — worldwide / consolidated total | R2: =COUNTIF('Label Map'!$D$2:$D$2000,A2) -> 3
A3: AMER (Americas) | B3: Region | C3: Global | D3: AMER | J3: Global | Q3: North America (NORAM) + Latin America (LATAM) | R3: =COUNTIF('Label Map'!$D$2:$D$2000,A3) -> 22
A4: NAFTA / USMCA | B4: Sub-region group | C4: Global | D4: AMER | J4: AMER (Americas) | Q4: Members: United States, Canada, Mexico — spans NORAM and LATAM | R4: =COUNTIF('Label Map'!$D$2:$D$2000,A4) -> 4
A5: North America (NORAM) | B5: Sub-region | C5: Global | D5: AMER | E5: North America (NORAM) | J5: AMER (Americas) | R5: =COUNTIF('Label Map'!$D$2:$D$2000,A5) -> 15
A6: United States | B6: Country | C6: Global | D6: AMER | E6: North America (NORAM) | F6: United States | G6: USA | J6: North America (NORAM) | K6: NAFTA / USMCA, G7, OECD | L6: Americas | M6: Northern America | O6: North America | P6: High income | R6: =COUNTIF('Label Map'!$D$2:$D$2000,A6) -> 42
A7: US Carolinas | B7: Sub-national region | C7: Global | D7: AMER | E7: North America (NORAM) | F7: United States | G7: USA | J7: United States | Q7: North and South Carolina | R7: =COUNTIF('Label Map'!$D$2:$D$2000,A7) -> 1
A8: US Central | B8: Sub-national region | C8: Global | D8: AMER | E8: North America (NORAM) | F8: United States | G8: USA | J8: United States | R8: =COUNTIF('Label Map'!$D$2:$D$2000,A8) -> 3
A9: US East | B9: Sub-national region | C9: Global | D9: AMER | E9: North America (NORAM) | F9: United States | G9: USA | J9: United States | R9: =COUNTIF('Label Map'!$D$2:$D$2000,A9) -> 3
A10: US East North Central | B10: Sub-national region | C10: Global | D10: AMER | E10: North America (NORAM) | F10: United States | G10: USA | J10: United States | Q10: Census division | R10: =COUNTIF('Label Map'!$D$2:$D$2000,A10) -> 2
A11: US East South Central | B11: Sub-national region | C11: Global | D11: AMER | E11: North America (NORAM) | F11: United States | G11: USA | J11: United States | Q11: Census division | R11: =COUNTIF('Label Map'!$D$2:$D$2000,A11) -> 2
A12: US Great Lakes | B12: Sub-national region | C12: Global | D12: AMER | E12: North America (NORAM) | F12: United States | G12: USA | J12: United States | R12: =COUNTIF('Label Map'!$D$2:$D$2000,A12) -> 2
A13: US Gulf Coast | B13: Sub-national region | C13: Global | D13: AMER | E13: North America (NORAM) | F13: United States | G13: USA | J13: United States | R13: =COUNTIF('Label Map'!$D$2:$D$2000,A13) -> 2
A14: US Mid-Atlantic | B14: Sub-national region | C14: Global | D14: AMER | E14: North America (NORAM) | F14: United States | G14: USA | J14: United States | R14: =COUNTIF('Label Map'!$D$2:$D$2000,A14) -> 3
A15: US Mid-South | B15: Sub-national region | C15: Global | D15: AMER | E15: North America (NORAM) | F15: United States | G15: USA | J15: United States | R15: =COUNTIF('Label Map'!$D$2:$D$2000,A15) -> 1
A16: US Midwest | B16: Sub-national region | C16: Global | D16: AMER | E16: North America (NORAM) | F16: United States | G16: USA | J16: United States | R16: =COUNTIF('Label Map'!$D$2:$D$2000,A16) -> 4
A17: US Mountain | B17: Sub-national region | C17: Global | D17: AMER | E17: North America (NORAM) | F17: United States | G17: USA | J17: United States | R17: =COUNTIF('Label Map'!$D$2:$D$2000,A17) -> 4
A18: US New England | B18: Sub-national region | C18: Global | D18: AMER | E18: North America (NORAM) | F18: United States | G18: USA | J18: United States | Q18: Census division | R18: =COUNTIF('Label Map'!$D$2:$D$2000,A18) -> 2
A19: US North | B19: Sub-national region | C19: Global | D19: AMER | E19: North America (NORAM) | F19: United States | G19: USA | J19: United States | R19: =COUNTIF('Label Map'!$D$2:$D$2000,A19) -> 2
A20: US Northeast | B20: Sub-national region | C20: Global | D20: AMER | E20: North America (NORAM) | F20: United States | G20: USA | J20: United States | R20: =COUNTIF('Label Map'!$D$2:$D$2000,A20) -> 3
A21: US Northeast Corridor | B21: Sub-national region | C21: Global | D21: AMER | E21: North America (NORAM) | F21: United States | G21: USA | J21: United States | Q21: Boston–Washington | R21: =COUNTIF('Label Map'!$D$2:$D$2000,A21) -> 1
A22: US Northwest | B22: Sub-national region | C22: Global | D22: AMER | E22: North America (NORAM) | F22: United States | G22: USA | J22: United States | R22: =COUNTIF('Label Map'!$D$2:$D$2000,A22) -> 2
A23: US Pacific | B23: Sub-national region | C23: Global | D23: AMER | E23: North America (NORAM) | F23: United States | G23: USA | J23: United States | Q23: Census division (not Asia Pacific) | R23: =COUNTIF('Label Map'!$D$2:$D$2000,A23) -> 1
A24: US Pacific Northwest | B24: Sub-national region | C24: Global | D24: AMER | E24: North America (NORAM) | F24: United States | G24: USA | J24: United States | R24: =COUNTIF('Label Map'!$D$2:$D$2000,A24) -> 2
A25: US Rust Belt | B25: Sub-national region | C25: Global | D25: AMER | E25: North America (NORAM) | F25: United States | G25: USA | J25: United States | R25: =COUNTIF('Label Map'!$D$2:$D$2000,A25) -> 1
A26: US South | B26: Sub-national region | C26: Global | D26: AMER | E26: North America (NORAM) | F26: United States | G26: USA | J26: United States | R26: =COUNTIF('Label Map'!$D$2:$D$2000,A26) -> 3
A27: US South Atlantic | B27: Sub-national region | C27: Global | D27: AMER | E27: North America (NORAM) | F27: United States | G27: USA | J27: United States | Q27: Census division | R27: =COUNTIF('Label Map'!$D$2:$D$2000,A27) -> 2
A28: US South Central | B28: Sub-national region | C28: Global | D28: AMER | E28: North America (NORAM) | F28: United States | G28: USA | J28: United States | Q28: Assumed US region — confirm | R28: =COUNTIF('Label Map'!$D$2:$D$2000,A28) -> 2
A29: US Southeast | B29: Sub-national region | C29: Global | D29: AMER | E29: North America (NORAM) | F29: United States | G29: USA | J29: United States | R29: =COUNTIF('Label Map'!$D$2:$D$2000,A29) -> 3
A30: US Southwest | B30: Sub-national region | C30: Global | D30: AMER | E30: North America (NORAM) | F30: United States | G30: USA | J30: United States | R30: =COUNTIF('Label Map'!$D$2:$D$2000,A30) -> 2
A31: US Sun Belt | B31: Sub-national region | C31: Global | D31: AMER | E31: North America (NORAM) | F31: United States | G31: USA | J31: United States | R31: =COUNTIF('Label Map'!$D$2:$D$2000,A31) -> 1
A32: US Tri-State Area | B32: Sub-national region | C32: Global | D32: AMER | E32: North America (NORAM) | F32: United States | G32: USA | J32: United States | Q32: New York, New Jersey, Connecticut | R32: =COUNTIF('Label Map'!$D$2:$D$2000,A32) -> 2
A33: US Upper Midwest | B33: Sub-national region | C33: Global | D33: AMER | E33: North America (NORAM) | F33: United States | G33: USA | J33: United States | R33: =COUNTIF('Label Map'!$D$2:$D$2000,A33) -> 1
A34: US Washington Metro (DMV) | B34: Sub-national region | C34: Global | D34: AMER | E34: North America (NORAM) | F34: United States | G34: USA | J34: United States | Q34: DC, Maryland, Virginia | R34: =COUNTIF('Label Map'!$D$2:$D$2000,A34) -> 2
A35: US West | B35: Sub-national region | C35: Global | D35: AMER | E35: North America (NORAM) | F35: United States | G35: USA | J35: United States | R35: =COUNTIF('Label Map'!$D$2:$D$2000,A35) -> 3
A36: US West Coast | B36: Sub-national region | C36: Global | D36: AMER | E36: North America (NORAM) | F36: United States | G36: USA | J36: United States | R36: =COUNTIF('Label Map'!$D$2:$D$2000,A36) -> 2
A37: US West North Central | B37: Sub-national region | C37: Global | D37: AMER | E37: North America (NORAM) | F37: United States | G37: USA | J37: United States | Q37: Census division | R37: =COUNTIF('Label Map'!$D$2:$D$2000,A37) -> 2
A38: US West South Central | B38: Sub-national region | C38: Global | D38: AMER | E38: North America (NORAM) | F38: United States | G38: USA | J38: United States | Q38: Census division | R38: =COUNTIF('Label Map'!$D$2:$D$2000,A38) -> 2
A39: Alabama | B39: State/Province | C39: Global | D39: AMER | E39: North America (NORAM) | F39: United States | G39: USA | H39: Alabama | J39: United States | R39: =COUNTIF('Label Map'!$D$2:$D$2000,A39) -> 2
A40: Alaska | B40: State/Province | C40: Global | D40: AMER | E40: North America (NORAM) | F40: United States | G40: USA | H40: Alaska | J40: United States | R40: =COUNTIF('Label Map'!$D$2:$D$2000,A40) -> 1
A41: American Samoa | B41: State/Province | C41: Global | D41: AMER | E41: North America (NORAM) | F41: United States | G41: USA | H41: American Samoa | J41: United States | Q41: US territory | R41: =COUNTIF('Label Map'!$D$2:$D$2000,A41) -> 1
A42: Arizona | B42: State/Province | C42: Global | D42: AMER | E42: North America (NORAM) | F42: United States | G42: USA | H42: Arizona | J42: United States | R42: =COUNTIF('Label Map'!$D$2:$D$2000,A42) -> 2
A43: Phoenix | B43: City | C43: Global | D43: AMER | E43: North America (NORAM) | F43: United States | G43: USA | H43: Arizona | I43: Phoenix | J43: Arizona | R43: =COUNTIF('Label Map'!$D$2:$D$2000,A43) -> 1
A44: Scottsdale | B44: City | C44: Global | D44: AMER | E44: North America (NORAM) | F44: United States | G44: USA | H44: Arizona | I44: Scottsdale | J44: Arizona | R44: =COUNTIF('Label Map'!$D$2:$D$2000,A44) -> 0
A45: Tucson | B45: City | C45: Global | D45: AMER | E45: North America (NORAM) | F45: United States | G45: USA | H45: Arizona | I45: Tucson | J45: Arizona | R45: =COUNTIF('Label Map'!$D$2:$D$2000,A45) -> 0
A46: Arkansas | B46: State/Province | C46: Global | D46: AMER | E46: North America (NORAM) | F46: United States | G46: USA | H46: Arkansas | J46: United States | R46: =COUNTIF('Label Map'!$D$2:$D$2000,A46) -> 2
A47: Bentonville | B47: City | C47: Global | D47: AMER | E47: North America (NORAM) | F47: United States | G47: USA | H47: Arkansas | I47: Bentonville | J47: Arkansas | R47: =COUNTIF('Label Map'!$D$2:$D$2000,A47) -> 0
A48: California | B48: State/Province | C48: Global | D48: AMER | E48: North America (NORAM) | F48: United States | G48: USA | H48: California | J48: United States | R48: =COUNTIF('Label Map'!$D$2:$D$2000,A48) -> 4
A49: Greater Los Angeles | B49: City | C49: Global | D49: AMER | E49: North America (NORAM) | F49: United States | G49: USA | H49: California | I49: Greater Los Angeles | J49: California | R49: =COUNTIF('Label Map'!$D$2:$D$2000,A49) -> 0
A50: Inland Empire | B50: City | C50: Global | D50: AMER | E50: North America (NORAM) | F50: United States | G50: USA | H50: California | I50: Inland Empire | J50: California | R50: =COUNTIF('Label Map'!$D$2:$D$2000,A50) -> 0
A51: Irwindale | B51: City | C51: Global | D51: AMER | E51: North America (NORAM) | F51: United States | G51: USA | H51: California | I51: Irwindale | J51: California | R51: =COUNTIF('Label Map'!$D$2:$D$2000,A51) -> 1
A52: Los Angeles | B52: City | C52: Global | D52: AMER | E52: North America (NORAM) | F52: United States | G52: USA | H52: California | I52: Los Angeles | J52: California | R52: =COUNTIF('Label Map'!$D$2:$D$2000,A52) -> 1
A53: Oceanside | B53: City | C53: Global | D53: AMER | E53: North America (NORAM) | F53: United States | G53: USA | H53: California | I53: Oceanside | J53: California | Q53: Assumed Oceanside, CA — confirm | R53: =COUNTIF('Label Map'!$D$2:$D$2000,A53) -> 1
A54: Sacramento | B54: City | C54: Global | D54: AMER | E54: North America (NORAM) | F54: United States | G54: USA | H54: California | I54: Sacramento | J54: California | R54: =COUNTIF('Label Map'!$D$2:$D$2000,A54) -> 0
A55: Sacramento Area | B55: City | C55: Global | D55: AMER | E55: North America (NORAM) | F55: United States | G55: USA | H55: California | I55: Sacramento Area | J55: California | Q55: Metro area | R55: =COUNTIF('Label Map'!$D$2:$D$2000,A55) -> 1
A56: San Bernardino | B56: City | C56: Global | D56: AMER | E56: North America (NORAM) | F56: United States | G56: USA | H56: California | I56: San Bernardino | J56: California | R56: =COUNTIF('Label Map'!$D$2:$D$2000,A56) -> 1
A57: San Diego | B57: City | C57: Global | D57: AMER | E57: North America (NORAM) | F57: United States | G57: USA | H57: California | I57: San Diego | J57: California | R57: =COUNTIF('Label Map'!$D$2:$D$2000,A57) -> 0
A58: San Francisco | B58: City | C58: Global | D58: AMER | E58: North America (NORAM) | F58: United States | G58: USA | H58: California | I58: San Francisco | J58: California | R58: =COUNTIF('Label Map'!$D$2:$D$2000,A58) -> 1
A59: San Francisco Bay Area | B59: City | C59: Global | D59: AMER | E59: North America (NORAM) | F59: United States | G59: USA | H59: California | I59: San Francisco Bay Area | J59: California | R59: =COUNTIF('Label Map'!$D$2:$D$2000,A59) -> 1
A60: San Jose | B60: City | C60: Global | D60: AMER | E60: North America (NORAM) | F60: United States | G60: USA | H60: California | I60: San Jose | J60: California | R60: =COUNTIF('Label Map'!$D$2:$D$2000,A60) -> 0
A61: Santa Ana | B61: City | C61: Global | D61: AMER | E61: North America (NORAM) | F61: United States | G61: USA | H61: California | I61: Santa Ana | J61: California | R61: =COUNTIF('Label Map'!$D$2:$D$2000,A61) -> 1
A62: Santa Clara | B62: City | C62: Global | D62: AMER | E62: North America (NORAM) | F62: United States | G62: USA | H62: California | I62: Santa Clara | J62: California | R62: =COUNTIF('Label Map'!$D$2:$D$2000,A62) -> 1
A63: Silicon Valley | B63: City | C63: Global | D63: AMER | E63: North America (NORAM) | F63: United States | G63: USA | H63: California | I63: Silicon Valley | J63: California | R63: =COUNTIF('Label Map'!$D$2:$D$2000,A63) -> 0
A64: Colorado | B64: State/Province | C64: Global | D64: AMER | E64: North America (NORAM) | F64: United States | G64: USA | H64: Colorado | J64: United States | R64: =COUNTIF('Label Map'!$D$2:$D$2000,A64) -> 2
A65: Colorado Springs | B65: City | C65: Global | D65: AMER | E65: North America (NORAM) | F65: United States | G65: USA | H65: Colorado | I65: Colorado Springs | J65: Colorado | R65: =COUNTIF('Label Map'!$D$2:$D$2000,A65) -> 1
A66: Denver | B66: City | C66: Global | D66: AMER | E66: North America (NORAM) | F66: United States | G66: USA | H66: Colorado | I66: Denver | J66: Colorado | R66: =COUNTIF('Label Map'!$D$2:$D$2000,A66) -> 0
A67: Connecticut | B67: State/Province | C67: Global | D67: AMER | E67: North America (NORAM) | F67: United States | G67: USA | H67: Connecticut | J67: United States | R67: =COUNTIF('Label Map'!$D$2:$D$2000,A67) -> 1
A68: Delaware | B68: State/Province | C68: Global | D68: AMER | E68: North America (NORAM) | F68: United States | G68: USA | H68: Delaware | J68: United States | R68: =COUNTIF('Label Map'!$D$2:$D$2000,A68) -> 2
A69: District of Columbia | B69: State/Province | C69: Global | D69: AMER | E69: North America (NORAM) | F69: United States | G69: USA | H69: District of Columbia | J69: United States | Q69: Federal district; treated at state level | R69: =COUNTIF('Label Map'!$D$2:$D$2000,A69) -> 2
A70: Florida | B70: State/Province | C70: Global | D70: AMER | E70: North America (NORAM) | F70: United States | G70: USA | H70: Florida | J70: United States | R70: =COUNTIF('Label Map'!$D$2:$D$2000,A70) -> 3
A71: Hollywood | B71: City | C71: Global | D71: AMER | E71: North America (NORAM) | F71: United States | G71: USA | H71: Florida | I71: Hollywood | J71: Florida | Q71: Assumed Hollywood, FL (Hard Rock Casino context in filings) | R71: =COUNTIF('Label Map'!$D$2:$D$2000,A71) -> 2
A72: Jacksonville | B72: City | C72: Global | D72: AMER | E72: North America (NORAM) | F72: United States | G72: USA | H72: Florida | I72: Jacksonville | J72: Florida | R72: =COUNTIF('Label Map'!$D$2:$D$2000,A72) -> 0
A73: Miami | B73: City | C73: Global | D73: AMER | E73: North America (NORAM) | F73: United States | G73: USA | H73: Florida | I73: Miami | J73: Florida | R73: =COUNTIF('Label Map'!$D$2:$D$2000,A73) -> 0
A74: Orlando | B74: City | C74: Global | D74: AMER | E74: North America (NORAM) | F74: United States | G74: USA | H74: Florida | I74: Orlando | J74: Florida | R74: =COUNTIF('Label Map'!$D$2:$D$2000,A74) -> 0
A75: Tampa | B75: City | C75: Global | D75: AMER | E75: North America (NORAM) | F75: United States | G75: USA | H75: Florida | I75: Tampa | J75: Florida | R75: =COUNTIF('Label Map'!$D$2:$D$2000,A75) -> 2
A76: Georgia | B76: State/Province | C76: Global | D76: AMER | E76: North America (NORAM) | F76: United States | G76: USA | H76: Georgia | J76: United States | Q76: US state. The country is 'Georgia (Country)' — see Decisions | R76: =COUNTIF('Label Map'!$D$2:$D$2000,A76) -> 2
A77: Atlanta | B77: City | C77: Global | D77: AMER | E77: North America (NORAM) | F77: United States | G77: USA | H77: Georgia | I77: Atlanta | J77: Georgia | R77: =COUNTIF('Label Map'!$D$2:$D$2000,A77) -> 1
A78: Savannah | B78: City | C78: Global | D78: AMER | E78: North America (NORAM) | F78: United States | G78: USA | H78: Georgia | I78: Savannah | J78: Georgia | R78: =COUNTIF('Label Map'!$D$2:$D$2000,A78) -> 0
A79: Guam | B79: State/Province | C79: Global | D79: AMER | E79: North America (NORAM) | F79: United States | G79: USA | H79: Guam | J79: United States | Q79: US territory — reported inside US segments by US filers | R79: =COUNTIF('Label Map'!$D$2:$D$2000,A79) -> 1
A80: Hawaii | B80: State/Province | C80: Global | D80: AMER | E80: North America (NORAM) | F80: United States | G80: USA | H80: Hawaii | J80: United States | R80: =COUNTIF('Label Map'!$D$2:$D$2000,A80) -> 1
A81: Honolulu | B81: City | C81: Global | D81: AMER | E81: North America (NORAM) | F81: United States | G81: USA | H81: Hawaii | I81: Honolulu | J81: Hawaii | R81: =COUNTIF('Label Map'!$D$2:$D$2000,A81) -> 0
A82: Idaho | B82: State/Province | C82: Global | D82: AMER | E82: North America (NORAM) | F82: United States | G82: USA | H82: Idaho | J82: United States | R82: =COUNTIF('Label Map'!$D$2:$D$2000,A82) -> 2
A83: Illinois | B83: State/Province | C83: Global | D83: AMER | E83: North America (NORAM) | F83: United States | G83: USA | H83: Illinois | J83: United States | R83: =COUNTIF('Label Map'!$D$2:$D$2000,A83) -> 2
A84: Chicago | B84: City | C84: Global | D84: AMER | E84: North America (NORAM) | F84: United States | G84: USA | H84: Illinois | I84: Chicago | J84: Illinois | R84: =COUNTIF('Label Map'!$D$2:$D$2000,A84) -> 1
A85: Chicagoland | B85: City | C85: Global | D85: AMER | E85: North America (NORAM) | F85: United States | G85: USA | H85: Illinois | I85: Chicagoland | J85: Illinois | R85: =COUNTIF('Label Map'!$D$2:$D$2000,A85) -> 0
A86: Indiana | B86: State/Province | C86: Global | D86: AMER | E86: North America (NORAM) | F86: United States | G86: USA | H86: Indiana | J86: United States | R86: =COUNTIF('Label Map'!$D$2:$D$2000,A86) -> 1
A87: Indianapolis | B87: City | C87: Global | D87: AMER | E87: North America (NORAM) | F87: United States | G87: USA | H87: Indiana | I87: Indianapolis | J87: Indiana | R87: =COUNTIF('Label Map'!$D$2:$D$2000,A87) -> 0
A88: Iowa | B88: State/Province | C88: Global | D88: AMER | E88: North America (NORAM) | F88: United States | G88: USA | H88: Iowa | J88: United States | R88: =COUNTIF('Label Map'!$D$2:$D$2000,A88) -> 2
A89: Kansas | B89: State/Province | C89: Global | D89: AMER | E89: North America (NORAM) | F89: United States | G89: USA | H89: Kansas | J89: United States | R89: =COUNTIF('Label Map'!$D$2:$D$2000,A89) -> 1
A90: Kentucky | B90: State/Province | C90: Global | D90: AMER | E90: North America (NORAM) | F90: United States | G90: USA | H90: Kentucky | J90: United States | R90: =COUNTIF('Label Map'!$D$2:$D$2000,A90) -> 2
A91: Louisville | B91: City | C91: Global | D91: AMER | E91: North America (NORAM) | F91: United States | G91: USA | H91: Kentucky | I91: Louisville | J91: Kentucky | R91: =COUNTIF('Label Map'!$D$2:$D$2000,A91) -> 0
A92: Louisiana | B92: State/Province | C92: Global | D92: AMER | E92: North America (NORAM) | F92: United States | G92: USA | H92: Louisiana | J92: United States | R92: =COUNTIF('Label Map'!$D$2:$D$2000,A92) -> 2
A93: New Orleans | B93: City | C93: Global | D93: AMER | E93: North America (NORAM) | F93: United States | G93: USA | H93: Louisiana | I93: New Orleans | J93: Louisiana | R93: =COUNTIF('Label Map'!$D$2:$D$2000,A93) -> 0
A94: Maine | B94: State/Province | C94: Global | D94: AMER | E94: North America (NORAM) | F94: United States | G94: USA | H94: Maine | J94: United States | R94: =COUNTIF('Label Map'!$D$2:$D$2000,A94) -> 1
A95: Maryland | B95: State/Province | C95: Global | D95: AMER | E95: North America (NORAM) | F95: United States | G95: USA | H95: Maryland | J95: United States | R95: =COUNTIF('Label Map'!$D$2:$D$2000,A95) -> 2
A96: Baltimore | B96: City | C96: Global | D96: AMER | E96: North America (NORAM) | F96: United States | G96: USA | H96: Maryland | I96: Baltimore | J96: Maryland | R96: =COUNTIF('Label Map'!$D$2:$D$2000,A96) -> 0
A97: Massachusetts | B97: State/Province | C97: Global | D97: AMER | E97: North America (NORAM) | F97: United States | G97: USA | H97: Massachusetts | J97: United States | R97: =COUNTIF('Label Map'!$D$2:$D$2000,A97) -> 2
A98: Boston | B98: City | C98: Global | D98: AMER | E98: North America (NORAM) | F98: United States | G98: USA | H98: Massachusetts | I98: Boston | J98: Massachusetts | R98: =COUNTIF('Label Map'!$D$2:$D$2000,A98) -> 1
A99: Greater Boston | B99: City | C99: Global | D99: AMER | E99: North America (NORAM) | F99: United States | G99: USA | H99: Massachusetts | I99: Greater Boston | J99: Massachusetts | R99: =COUNTIF('Label Map'!$D$2:$D$2000,A99) -> 0
A100: Michigan | B100: State/Province | C100: Global | D100: AMER | E100: North America (NORAM) | F100: United States | G100: USA | H100: Michigan | J100: United States | R100: =COUNTIF('Label Map'!$D$2:$D$2000,A100) -> 2
...

Sheet Tree View
A1: Global > Region > Sub-region > Country > State/Province (business regions in italics) > City. Names are live links to Hierarchy. Groupings (Nordics, GCC, NOLA…) and non-regional buckets are on Hierarchy only.
A3: Global | B3: Region | C3: Sub-region | D3: Country | E3: State/Province / Region | F3: City | G3: ISO3
A4: =Hierarchy!A2 -> Global
B5: =Hierarchy!A3 -> AMER (Americas)
C6: =Hierarchy!A5 -> North America (NORAM)
D7: =Hierarchy!A6 -> United States | G7: =Hierarchy!G6 -> USA
E8: =Hierarchy!A7 -> US Carolinas
E9: =Hierarchy!A8 -> US Central
E10: =Hierarchy!A9 -> US East
E11: =Hierarchy!A10 -> US East North Central
E12: =Hierarchy!A11 -> US East South Central
E13: =Hierarchy!A12 -> US Great Lakes
E14: =Hierarchy!A13 -> US Gulf Coast
E15: =Hierarchy!A14 -> US Mid-Atlantic
E16: =Hierarchy!A15 -> US Mid-South
E17: =Hierarchy!A16 -> US Midwest
E18: =Hierarchy!A17 -> US Mountain
E19: =Hierarchy!A18 -> US New England
... E43: =Hierarchy!A42 -> Arizona
F44: =Hierarchy!A43 -> Phoenix
F45: =Hierarchy!A44 -> Scottsdale
F46: =Hierarchy!A45 -> Tucson
E47: =Hierarchy!A46 -> Arkansas
F48: =Hierarchy!A47 -> Bentonville
E49: =Hierarchy!A48 -> California
F50: =Hierarchy!A49 -> Greater Los Angeles
F51: =Hierarchy!A50 -> Inland Empire
F52: =Hierarchy!A51 -> Irwindale
F53: =Hierarchy!A52 -> Los Angeles
F54: =Hierarchy!A53 -> Oceanside
F55: =Hierarchy!A54 -> Sacramento
F56: =Hierarchy!A55 -> Sacramento Area
F57: =Hierarchy!A56 -> San Bernardino
F58: =Hierarchy!A57 -> San Diego
F59: =Hierarchy!A58 -> San Francisco
F60: =Hierarchy!A59 -> San Francisco Bay Area
F61: =Hierarchy!A60 -> San Jose
... F64: =Hierarchy!A63 -> Silicon Valley
E65: =Hierarchy!A64 -> Colorado
F66: =Hierarchy!A65 -> Colorado Springs
F67: =Hierarchy!A66 -> Denver
E68: =Hierarchy!A67 -> Connecticut
E69: =Hierarchy!A68 -> Delaware
E70: =Hierarchy!A69 -> District of Columbia
E71: =Hierarchy!A70 -> Florida
F72: =Hierarchy!A71 -> Hollywood
F73: =Hierarchy!A72 -> Jacksonville
F74: =Hierarchy!A73 -> Miami
F75: =Hierarchy!A74 -> Orlando
F76: =Hierarchy!A75 -> Tampa
E77: =Hierarchy!A76 -> Georgia
F78: =Hierarchy!A77 -> Atlanta
F79: =Hierarchy!A78 -> Savannah
E80: =Hierarchy!A79 -> Guam
E81: =Hierarchy!A80 -> Hawaii
F82: =Hierarchy!A81 -> Honolulu
E83: =Hierarchy!A82 -> Idaho
E84: =Hierarchy!A83 -> Illinois
F85: =Hierarchy!A84 -> Chicago
F86: =Hierarchy!A85 -> Chicagoland
E87: =Hierarchy!A86 -> Indiana
F88: =Hierarchy!A87 -> Indianapolis
E89: =Hierarchy!A88 -> Iowa
E90: =Hierarchy!A89 -> Kansas
E91: =Hierarchy!A90 -> Kentucky
F92: =Hierarchy!A91 -> Louisville
E93: =Hierarchy!A92 -> Louisiana
F94: =Hierarchy!A93 -> New Orleans
E95: =Hierarchy!A94 -> Maine
E96: =Hierarchy!A95 -> Maryland
F97: =Hierarchy!A96 -> Baltimore
E98: =Hierarchy!A97 -> Massachusetts
F99: =Hierarchy!A98 -> Boston
F100: =Hierarchy!A99 -> Greater Boston
E101: =Hierarchy!A100 -> Michigan
F102: =Hierarchy!A101 -> Detroit
E103: =Hierarchy!A102 -> Minnesota
F104: =Hierarchy!A103 -> Minneapolis
E105: =Hierarchy!A104 -> Mississippi
E106: =Hierarchy!A105 -> Missouri
F107: =Hierarchy!A106 -> Kansas City
F108: =Hierarchy!A107 -> St. Louis
E109: =Hierarchy!A108 -> Montana
E110: =Hierarchy!A109 -> Nebraska
E111: =Hierarchy!A110 -> Nevada
F112: =Hierarchy!A111 -> Las Vegas
F113: =Hierarchy!A112 -> Reno
E114: =Hierarchy!A113 -> New Hampshire
E115: =Hierarchy!A114 -> New Jersey
E116: =Hierarchy!A115 -> New Mexico
F117: =Hierarchy!A116 -> Albuquerque
E118: =Hierarchy!A117 -> New York
F119: =Hierarchy!A118 -> Buffalo
F120: =Hierarchy!A119 -> Greater New York
F121: =Hierarchy!A120 -> Long Island
F122: =Hierarchy!A121 -> New York City
E123: =Hierarchy!A122 -> North Carolina
F124: =Hierarchy!A123 -> Charlotte
F125: =Hierarchy!A124 -> Raleigh
E126: =Hierarchy!A125 -> North Dakota
...

Sheet Label Map
A1: MDP Label (raw) | B1: Source Sheet | C1: Previous MDP Name | D1: Standard Node | E1: Scope | F1: Level | G1: Region | H1: Sub-region | I1: Country | J1: ISO3 | K1: State/Province | L1: City | M1: Change vs Previous | N1: Match Key | O1: Key Conflict | P1: Note
A2: Aargau | B2: Pre-seeded | D2: Aargau | E2: Exact | F2: =IF($D2="","",IFERROR(IF(INDEX(Hierarchy!$B$2:$B$1295,MATCH($D2,Hierarchy!$A$2:$A$1295,0))="","",INDEX(Hierarchy!$B$2:$B$1295,MATCH($D2,Hierarchy!$A$2:$A$1295,0))),"NODE NOT FOUND")) -> State/Province | G2: =IF($D2="","",IFERROR(IF(INDEX(Hierarchy!$D$2:$D$1295,MATCH($D2,Hierarchy!$A$2:$A$1295,0))="","",INDEX(Hierarchy!$D$2:$D$1295,MATCH($D2,Hierarchy!$A$2:$A$1295,0))),"NODE NOT FOUND")) -> EMEA | H2: =IF($D2="","",IFERROR(IF(INDEX(Hierarchy!$E$2:$E$1295,MATCH($D2,Hierarchy!$A$2:$A$1295,0))="","",INDEX(Hierarchy!$E$2:$E$1295,MATCH($D2,Hierarchy!$A$2:$A$1295,0))),"NODE NOT FOUND")) -> Europe | I2: =IF($D2="","",IFERROR(IF(INDEX(Hierarchy!$F$2:$F$1295,MATCH($D2,Hierarchy!$A$2:$A$1295,0))="","",INDEX(Hierarchy!$F$2:$F$1295,MATCH($D2,Hierarchy!$A$2:$A$1295,0))),"NODE NOT FOUND")) -> Switzerland | J2: =IF($D2="","",IFERROR(IF(INDEX(Hierarchy!$G$2:$G$1295,MATCH($D2,Hierarchy!$A$2:$A$1295,0))="","",INDEX(Hierarchy!$G$2:$G$1295,MATCH($D2,Hierarchy!$A$2:$A$1295,0))),"NODE NOT FOUND")) -> CHE | K2: =IF($D2="","",IFERROR(IF(INDEX(Hierarchy!$H$2:$H$1295,MATCH($D2,Hierarchy!$A$2:$A$1295,0))="","",INDEX(Hierarchy!$H$2:$H$1295,MATCH($D2,Hierarchy!$A$2:$A$1295,0))),"NODE NOT FOUND")) -> Aargau | L2: =IF($D2="","",IFERROR(IF(INDEX(Hierarchy!$I$2:$I$1295,MATCH($D2,Hierarchy!$A$2:$A$1295,0))="","",INDEX(Hierarchy!$I$2:$I$1295,MATCH($D2,Hierarchy!$A$2:$A$1295,0))),"NODE NOT FOUND")) | M2: =IF(B2="Pre-seeded","Pre-seeded",IF(B2="Review 2026-09-16","Added from review",IF(C2="","New",IF(C2=D2,"","Changed")))) -> Pre-seeded | N2: =TRIM(SUBSTITUTE(SUBSTITUTE(SUBSTITUTE(" "&TRIM(SUBSTITUTE(SUBSTITUTE(SUBSTITUTE(SUBSTITUTE(SUBSTITUTE(SUBSTITUTE(SUBSTITUTE(SUBSTITUTE(SUBSTITUTE(SUBSTITUTE(SUBSTITUTE(SUBSTITUTE(SUBSTITUTE(SUBSTITUTE(SUBSTITUTE(UPPER(TRIM(A2)),"[MEMBER]",""),"{MEMBER}",""),"[MEMBER}",""),"MEMBER]",""),"(A)",""),"""",""),"“",""),"”",""),".",""),":",""),",",""),"–"," "),"-"," "),"/"," "),"&"," AND "))&" "," THE "," ")," TOTAL "," ")," OPERATIONS "," ")) -> AARGAU | O2: =IF(COUNTIFS($N$2:$N$2000,N2,$D$2:$D$2000,"<>"&D2)>0,"CONFLICT","")
A3: Abia | B3: Pre-seeded | D3: Abia | E3: Exact | F3: =IF($D3="","",IFERROR(IF(INDEX(Hierarchy!$B$2:$B$1295,MATCH($D3,Hierarchy!$A$2:$A$1295,0))="","",INDEX(Hierarchy!$B$2:$B$1295,MATCH($D3,Hierarchy!$A$2:$A$1295,0))),"NODE NOT FOUND")) -> State/Province | G3: =IF($D3="","",IFERROR(IF(INDEX(Hierarchy!$D$2:$D$1295,MATCH($D3,Hierarchy!$A$2:$A$1295,0))="","",INDEX(Hierarchy!$D$2:$D$1295,MATCH($D3,Hierarchy!$A$2:$A$1295,0))),"NODE NOT FOUND")) -> EMEA | H3: =IF($D3="","",IFERROR(IF(INDEX(Hierarchy!$E$2:$E$1295,MATCH($D3,Hierarchy!$A$2:$A$1295,0))="","",INDEX(Hierarchy!$E$2:$E$1295,MATCH($D3,Hierarchy!$A$2:$A$1295,0))),"NODE NOT FOUND")) -> Africa | I3: =IF($D3="","",IFERROR(IF(INDEX(Hierarchy!$F$2:$F$1295,MATCH($D3,Hierarchy!$A$2:$A$1295,0))="","",INDEX(Hierarchy!$F$2:$F$1295,MATCH($D3,Hierarchy!$A$2:$A$1295,0))),"NODE NOT FOUND")) -> Nigeria | J3: =IF($D3="","",IFERROR(IF(INDEX(Hierarchy!$G$2:$G$1295,MATCH($D3,Hierarchy!$A$2:$A$1295,0))="","",INDEX(Hierarchy!$G$2:$G$1295,MATCH($D3,Hierarchy!$A$2:$A$1295,0))),"NODE NOT FOUND")) -> NGA | K3: =IF($D3="","",IFERROR(IF(INDEX(Hierarchy!$H$2:$H$1295,MATCH($D3,Hierarchy!$A$2:$A$1295,0))="","",INDEX(Hierarchy!$H$2:$H$1295,MATCH($D3,Hierarchy!$A$2:$A$1295,0))),"NODE NOT FOUND")) -> Abia | L3: =IF($D3="","",IFERROR(IF(INDEX(Hierarchy!$I$2:$I$1295,MATCH($D3,Hierarchy!$A$2:$A$1295,0))="","",INDEX(Hierarchy!$I$2:$I$1295,MATCH($D3,Hierarchy!$A$2:$A$1295,0))),"NODE NOT FOUND")) | M3: =IF(B3="Pre-seeded","Pre-seeded",IF(B3="Review 2026-09-16","Added from review",IF(C3="","New",IF(C3=D3,"","Changed")))) -> Pre-seeded | N3: =TRIM(SUBSTITUTE(SUBSTITUTE(SUBSTITUTE(" "&TRIM(SUBSTITUTE(SUBSTITUTE(SUBSTITUTE(SUBSTITUTE(SUBSTITUTE(SUBSTITUTE(SUBSTITUTE(SUBSTITUTE(SUBSTITUTE(SUBSTITUTE(SUBSTITUTE(SUBSTITUTE(SUBSTITUTE(SUBSTITUTE(SUBSTITUTE(UPPER(TRIM(A3)),"[MEMBER]",""),"{MEMBER}",""),"[MEMBER}",""),"MEMBER]",""),"(A)",""),"""",""),"“",""),"”",""),".",""),":",""),",",""),"–"," "),"-"," "),"/"," "),"&"," AND "))&" "," THE "," ")," TOTAL "," ")," OPERATIONS "," ")) -> ABIA | O3: =IF(COUNTIFS($N$2:$N$2000,N3,$D$2:$D$2000,"<>"&D3)>0,"CONFLICT","")
A4: Abroad | B4: Pre-seeded | D4: International | E4: Exact | F4: =IF($D4="","",IFERROR(IF(INDEX(Hierarchy!$B$2:$B$1295,MATCH($D4,Hierarchy!$A$2:$A$1295,0))="","",INDEX(Hierarchy!$B$2:$B$1295,MATCH($D4,Hierarchy!$A$2:$A$1295,0))),"NODE NOT FOUND")) -> Bucket | G4: =IF($D4="","",IFERROR(IF(INDEX(Hierarchy!$D$2:$D$1295,MATCH($D4,Hierarchy!$A$2:$A$1295,0))="","",INDEX(Hierarchy!$D$2:$D$1295,MATCH($D4,Hierarchy!$A$2:$A$1295,0))),"NODE NOT FOUND")) -> Non-regional | H4: =IF($D4="","",IFERROR(IF(INDEX(Hierarchy!$E$2:$E$1295,MATCH($D4,Hierarchy!$A$2:$A$1295,0))="","",INDEX(Hierarchy!$E$2:$E$1295,MATCH($D4,Hierarchy!$A$2:$A$1295,0))),"NODE NOT FOUND")) | I4: =IF($D4="","",IFERROR(IF(INDEX(Hierarchy!$F$2:$F$1295,MATCH($D4,Hierarchy!$A$2:$A$1295,0))="","",INDEX(Hierarchy!$F$2:$F$1295,MATCH($D4,Hierarchy!$A$2:$A$1295,0))),"NODE NOT FOUND")) | J4: =IF($D4="","",IFERROR(IF(INDEX(Hierarchy!$G$2:$G$1295,MATCH($D4,Hierarchy!$A$2:$A$1295,0))="","",INDEX(Hierarchy!$G$2:$G$1295,MATCH($D4,Hierarchy!$A$2:$A$1295,0))),"NODE NOT FOUND")) | K4: =IF($D4="","",IFERROR(IF(INDEX(Hierarchy!$H$2:$H$1295,MATCH($D4,Hierarchy!$A$2:$A$1295,0))="","",INDEX(Hierarchy!$H$2:$H$1295,MATCH($D4,Hierarchy!$A$2:$A$1295,0))),"NODE NOT FOUND")) | L4: =IF($D4="","",IFERROR(IF(INDEX(Hierarchy!$I$2:$I$1295,MATCH($D4,Hierarchy!$A$2:$A$1295,0))="","",INDEX(Hierarchy!$I$2:$I$1295,MATCH($D4,Hierarchy!$A$2:$A$1295,0))),"NODE NOT FOUND")) | M4: =IF(B4="Pre-seeded","Pre-seeded",IF(B4="Review 2026-09-16","Added from review",IF(C4="","New",IF(C4=D4,"","Changed")))) -> Pre-seeded | N4: =TRIM(SUBSTITUTE(SUBSTITUTE(SUBSTITUTE(" "&TRIM(SUBSTITUTE(SUBSTITUTE(SUBSTITUTE(SUBSTITUTE(SUBSTITUTE(SUBSTITUTE(SUBSTITUTE(SUBSTITUTE(SUBSTITUTE(SUBSTITUTE(SUBSTITUTE(SUBSTITUTE(SUBSTITUTE(SUBSTITUTE(SUBSTITUTE(UPPER(TRIM(A4)),"[MEMBER]",""),"{MEMBER}",""),"[MEMBER}",""),"MEMBER]",""),"(A)",""),"""",""),"“",""),"”",""),".",""),":",""),",",""),"–"," "),"-"," "),"/"," "),"&"," AND "))&" "," THE "," ")," TOTAL "," ")," OPERATIONS "," ")) -> ABROAD | O4: =IF(COUNTIFS($N$2:$N$2000,N4,$D$2:$D$2000,"<>"&D4)>0,"CONFLICT","")
A5: Abruzzo | B5: Pre-seeded | D5: Abruzzo | E5: Exact | F5: =IF($D5="","",IFERROR(IF(INDEX(Hierarchy!$B$2:$B$1295,MATCH($D5,Hierarchy!$A$2:$A$1295,0))="","",INDEX(Hierarchy!$B$2:$B$1295,MATCH($D5,Hierarchy!$A$2:$A$1295,0))),"NODE NOT FOUND")) -> State/Province | G5: =IF($D5="","",IFERROR(IF(INDEX(Hierarchy!$D$2:$D$1295,MATCH($D5,Hierarchy!$A$2:$A$1295,0))="","",INDEX(Hierarchy!$D$2:$D$1295,MATCH($D5,Hierarchy!$A$2:$A$1295,0))),"NODE NOT FOUND")) -> EMEA | H5: =IF($D5="","",IFERROR(IF(INDEX(Hierarchy!$E$2:$E$1295,MATCH($D5,Hierarchy!$A$2:$A$1295,0))="","",INDEX(Hierarchy!$E$2:$E$1295,MATCH($D5,Hierarchy!$A$2:$A$1295,0))),"NODE NOT FOUND")) -> Europe | I5: =IF($D5="","",IFERROR(IF(INDEX(Hierarchy!$F$2:$F$1295,MATCH($D5,Hierarchy!$A$2:$A$1295,0))="","",INDEX(Hierarchy!$F$2:$F$1295,MATCH($D5,Hierarchy!$A$2:$A$1295,0))),"NODE NOT FOUND")) -> Italy | J5: =IF($D5="","",IFERROR(IF(INDEX(Hierarchy!$G$2:$G$1295,MATCH($D5,Hierarchy!$A$2:$A$1295,0))="","",INDEX(Hierarchy!$G$2:$G$1295,MATCH($D5,Hierarchy!$A$2:$A$1295,0))),"NODE NOT FOUND")) -> ITA | K5: =IF($D5="","",IFERROR(IF(INDEX(Hierarchy!$H$2:$H$1295,MATCH($D5,Hierarchy!$A$2:$A$1295,0))="","",INDEX(Hierarchy!$H$2:$H$1295,MATCH($D5,Hierarchy!$A$2:$A$1295,0))),"NODE NOT FOUND")) -> Abruzzo | L5: =IF($D5="","",IFERROR(IF(INDEX(Hierarchy!$I$2:$I$1295,MATCH($D5,Hierarchy!$A$2:$A$1295,0))="","",INDEX(Hierarchy!$I$2:$I$1295,MATCH($D5,Hierarchy!$A$2:$A$1295,0))),"NODE NOT FOUND")) | M5: =IF(B5="Pre-seeded","Pre-seeded",IF(B5="Review 2026-09-16","Added from review",IF(C5="","New",IF(C5=D5,"","Changed")))) -> Pre-seeded | N5: =TRIM(SUBSTITUTE(SUBSTITUTE(SUBSTITUTE(" "&TRIM(SUBSTITUTE(SUBSTITUTE(SUBSTITUTE(SUBSTITUTE(SUBSTITUTE(SUBSTITUTE(SUBSTITUTE(SUBSTITUTE(SUBSTITUTE(SUBSTITUTE(SUBSTITUTE(SUBSTITUTE(SUBSTITUTE(SUBSTITUTE(SUBSTITUTE(UPPER(TRIM(A5)),"[MEMBER]",""),"{MEMBER}",""),"[MEMBER}",""),"MEMBER]",""),"(A)",""),"""",""),"“",""),"”",""),".",""),":",""),",",""),"–"," "),"-"," "),"/"," "),"&"," AND "))&" "," THE "," ")," TOTAL "," ")," OPERATIONS "," ")) -> ABRUZZO | O5: =IF(COUNTIFS($N$2:$N$2000,N5,$D$2:$D$2000,"<>"&D5)>0,"CONFLICT","")
A6: Abu Dhabi | B6: Mapping | C6: Abu Dhabi | D6: Abu Dhabi | E6: Exact | F6: =IF($D6="","",IFERROR(IF(INDEX(Hierarchy!$B$2:$B$1295,MATCH($D6,Hierarchy!$A$2:$A$1295,0))="","",INDEX(Hierarchy!$B$2:$B$1295,MATCH($D6,Hierarchy!$A$2:$A$1295,0))),"NODE NOT FOUND")) -> State/Province | G6: =IF($D6="","",IFERROR(IF(INDEX(Hierarchy!$D$2:$D$1295,MATCH($D6,Hierarchy!$A$2:$A$1295,0))="","",INDEX(Hierarchy!$D$2:$D$1295,MATCH($D6,Hierarchy!$A$2:$A$1295,0))),"NODE NOT FOUND")) -> EMEA | H6: =IF($D6="","",IFERROR(IF(INDEX(Hierarchy!$E$2:$E$1295,MATCH($D6,Hierarchy!$A$2:$A$1295,0))="","",INDEX(Hierarchy!$E$2:$E$1295,MATCH($D6,Hierarchy!$A$2:$A$1295,0))),"NODE NOT FOUND")) -> Middle East | I6: =IF($D6="","",IFERROR(IF(INDEX(Hierarchy!$F$2:$F$1295,MATCH($D6,Hierarchy!$A$2:$A$1295,0))="","",INDEX(Hierarchy!$F$2:$F$1295,MATCH($D6,Hierarchy!$A$2:$A$1295,0))),"NODE NOT FOUND")) -> United Arab Emirates | J6: =IF($D6="","",IFERROR(IF(INDEX(Hierarchy!$G$2:$G$1295,MATCH($D6,Hierarchy!$A$2:$A$1295,0))="","",INDEX(Hierarchy!$G$2:$G$1295,MATCH($D6,Hierarchy!$A$2:$A$1295,0))),"NODE NOT FOUND")) -> ARE | K6: =IF($D6="","",IFERROR(IF(INDEX(Hierarchy!$H$2:$H$1295,MATCH($D6,Hierarchy!$A$2:$A$1295,0))="","",INDEX(Hierarchy!$H$2:$H$1295,MATCH($D6,Hierarchy!$A$2:$A$1295,0))),"NODE NOT FOUND")) -> Abu Dhabi | L6: =IF($D6="","",IFERROR(IF(INDEX(Hierarchy!$I$2:$I$1295,MATCH($D6,Hierarchy!$A$2:$A$1295,0))="","",INDEX(Hierarchy!$I$2:$I$1295,MATCH($D6,Hierarchy!$A$2:$A$1295,0))),"NODE NOT FOUND")) | M6: =IF(B6="Pre-seeded","Pre-seeded",IF(B6="Review 2026-09-16","Added from review",IF(C6="","New",IF(C6=D6,"","Changed")))) | N6: =TRIM(SUBSTITUTE(SUBSTITUTE(SUBSTITUTE(" "&TRIM(SUBSTITUTE(SUBSTITUTE(SUBSTITUTE(SUBSTITUTE(SUBSTITUTE(SUBSTITUTE(SUBSTITUTE(SUBSTITUTE(SUBSTITUTE(SUBSTITUTE(SUBSTITUTE(SUBSTITUTE(SUBSTITUTE(SUBSTITUTE(SUBSTITUTE(UPPER(TRIM(A6)),"[MEMBER]",""),"{MEMBER}",""),"[MEMBER}",""),"MEMBER]",""),"(A)",""),"""",""),"“",""),"”",""),".",""),":",""),",",""),"–"," "),"-"," "),"/"," "),"&"," AND "))&" "," THE "," ")," TOTAL "," ")," OPERATIONS "," ")) -> ABU DHABI | O6: =IF(COUNTIFS($N$2:$N$2000,N6,$D$2:$D$2000,"<>"&D6)>0,"CONFLICT","")
A7: Abuja | B7: Pre-seeded | D7: Federal Capital Territory (Abuja) | E7: Exact | F7: =IF($D7="","",IFERROR(IF(INDEX(Hierarchy!$B$2:$B$1295,MATCH($D7,Hierarchy!$A$2:$A$1295,0))="","",INDEX(Hierarchy!$B$2:$B$1295,MATCH($D7,Hierarchy!$A$2:$A$1295,0))),"NODE NOT FOUND")) -> State/Province | G7: =IF($D7="","",IFERROR(IF(INDEX(Hierarchy!$D$2:$D$1295,MATCH($D7,Hierarchy!$A$2:$A$1295,0))="","",INDEX(Hierarchy!$D$2:$D$1295,MATCH($D7,Hierarchy!$A$2:$A$1295,0))),"NODE NOT FOUND")) -> EMEA | H7: =IF($D7="","",IFERROR(IF(INDEX(Hierarchy!$E$2:$E$1295,MATCH($D7,Hierarchy!$A$2:$A$1295,0))="","",INDEX(Hierarchy!$E$2:$E$1295,MATCH($D7,Hierarchy!$A$2:$A$1295,0))),"NODE NOT FOUND")) -> Africa | I7: =IF($D7="","",IFERROR(IF(INDEX(Hierarchy!$F$2:$F$1295,MATCH($D7,Hierarchy!$A$2:$A$1295,0))="","",INDEX(Hierarchy!$F$2:$F$1295,MATCH($D7,Hierarchy!$A$2:$A$1295,0))),"NODE NOT FOUND")) -> Nigeria | J7: =IF($D7="","",IFERROR(IF(INDEX(Hierarchy!$G$2:$G$1295,MATCH($D7,Hierarchy!$A$2:$A$1295,0))="","",INDEX(Hierarchy!$G$2:$G$1295,MATCH($D7,Hierarchy!$A$2:$A$1295,0))),"NODE NOT FOUND")) -> NGA | K7: =IF($D7="","",IFERROR(IF(INDEX(Hierarchy!$H$2:$H$1295,MATCH($D7,Hierarchy!$A$2:$A$1295,0))="","",INDEX(Hierarchy!$H$2:$H$1295,MATCH($D7,Hierarchy!$A$2:$A$1295,0))),"NODE NOT FOUND")) -> Federal Capital Territory (Abuja) | L7: =IF($D7="","",IFERROR(IF(INDEX(Hierarchy!$I$2:$I$1295,MATCH($D7,Hierarchy!$A$2:$A$1295,0))="","",INDEX(Hierarchy!$I$2:$I$1295,MATCH($D7,Hierarchy!$A$2:$A$1295,0))),"NODE NOT FOUND")) | M7: =IF(B7="Pre-seeded","Pre-seeded",IF(B7="Review 2026-09-16","Added from review",IF(C7="","New",IF(C7=D7,"","Changed")))) -> Pre-seeded | N7: =TRIM(SUBSTITUTE(SUBSTITUTE(SUBSTITUTE(" "&TRIM(SUBSTITUTE(SUBSTITUTE(SUBSTITUTE(SUBSTITUTE(SUBSTITUTE(SUBSTITUTE(SUBSTITUTE(SUBSTITUTE(SUBSTITUTE(SUBSTITUTE(SUBSTITUTE(SUBSTITUTE(SUBSTITUTE(SUBSTITUTE(SUBSTITUTE(UPPER(TRIM(A7)),"[MEMBER]",""),"{MEMBER}",""),"[MEMBER}",""),"MEMBER]",""),"(A)",""),"""",""),"“",""),"”",""),".",""),":",""),",",""),"–"," "),"-"," "),"/"," "),"&"," AND "))&" "," THE "," ")," TOTAL "," ")," OPERATIONS "," ")) -> ABUJA | O7: =IF(COUNTIFS($N$2:$N$2000,N7,$D$2:$D$2000,"<>"&D7)>0,"CONFLICT","")
A8: Aceh | B8: Pre-seeded | D8: Aceh | E8: Exact | F8: =IF($D8="","",IFERROR(IF(INDEX(Hierarchy!$B$2:$B$1295,MATCH($D8,Hierarchy!$A$2:$A$1295,0))="","",INDEX(Hierarchy!$B$2:$B$1295,MATCH($D8,Hierarchy!$A$2:$A$1295,0))),"NODE NOT FOUND")) -> State/Province | G8: =IF($D8="","",IFERROR(IF(INDEX(Hierarchy!$D$2:$D$1295,MATCH($D8,Hierarchy!$A$2:$A$1295,0))="","",INDEX(Hierarchy!$D$2:$D$1295,MATCH($D8,Hierarchy!$A$2:$A$1295,0))),"NODE NOT FOUND")) -> APAC | H8: =IF($D8="","",IFERROR(IF(INDEX(Hierarchy!$E$2:$E$1295,MATCH($D8,Hierarchy!$A$2:$A$1295,0))="","",INDEX(Hierarchy!$E$2:$E$1295,MATCH($D8,Hierarchy!$A$2:$A$1295,0))),"NODE NOT FOUND")) -> Southeast Asia (ASEAN) | I8: =IF($D8="","",IFERROR(IF(INDEX(Hierarchy!$F$2:$F$1295,MATCH($D8,Hierarchy!$A$2:$A$1295,0))="","",INDEX(Hierarchy!$F$2:$F$1295,MATCH($D8,Hierarchy!$A$2:$A$1295,0))),"NODE NOT FOUND")) -> Indonesia | J8: =IF($D8="","",IFERROR(IF(INDEX(Hierarchy!$G$2:$G$1295,MATCH($D8,Hierarchy!$A$2:$A$1295,0))="","",INDEX(Hierarchy!$G$2:$G$1295,MATCH($D8,Hierarchy!$A$2:$A$1295,0))),"NODE NOT FOUND")) -> IDN | K8: =IF($D8="","",IFERROR(IF(INDEX(Hierarchy!$H$2:$H$1295,MATCH($D8,Hierarchy!$A$2:$A$1295,0))="","",INDEX(Hierarchy!$H$2:$H$1295,MATCH($D8,Hierarchy!$A$2:$A$1295,0))),"NODE NOT FOUND")) -> Aceh | L8: =IF($D8="","",IFERROR(IF(INDEX(Hierarchy!$I$2:$I$1295,MATCH($D8,Hierarchy!$A$2:$A$1295,0))="","",INDEX(Hierarchy!$I$2:$I$1295,MATCH($D8,Hierarchy!$A$2:$A$1295,0))),"NODE NOT FOUND")) | M8: =IF(B8="Pre-seeded","Pre-seeded",IF(B8="Review 2026-09-16","Added from review",IF(C8="","New",IF(C8=D8,"","Changed")))) -> Pre-seeded | N8: =TRIM(SUBSTITUTE(SUBSTITUTE(SUBSTITUTE(" "&TRIM(SUBSTITUTE(SUBSTITUTE(SUBSTITUTE(SUBSTITUTE(SUBSTITUTE(SUBSTITUTE(SUBSTITUTE(SUBSTITUTE(SUBSTITUTE(SUBSTITUTE(SUBSTITUTE(SUBSTITUTE(SUBSTITUTE(SUBSTITUTE(SUBSTITUTE(UPPER(TRIM(A8)),"[MEMBER]",""),"{MEMBER}",""),"[MEMBER}",""),"MEMBER]",""),"(A)",""),"""",""),"“",""),"”",""),".",""),":",""),",",""),"–"," "),"-"," "),"/"," "),"&"," AND "))&" "," THE "," ")," TOTAL "," ")," OPERATIONS "," ")) -> ACEH | O8: =IF(COUNTIFS($N$2:$N$2000,N8,$D$2:$D$2000,"<>"&D8)>0,"CONFLICT","")
A9: Acre | B9: Pre-seeded | D9: Acre | E9: Exact | F9: =IF($D9="","",IFERROR(IF(INDEX(Hierarchy!$B$2:$B$1295,MATCH($D9,Hierarchy!$A$2:$A$1295,0))="","",INDEX(Hierarchy!$B$2:$B$1295,MATCH($D9,Hierarchy!$A$2:$A$1295,0))),"NODE NOT FOUND")) -> State/Province | G9: =IF($D9="","",IFERROR(IF(INDEX(Hierarchy!$D$2:$D$1295,MATCH($D9,Hierarchy!$A$2:$A$1295,0))="","",INDEX(Hierarchy!$D$2:$D$1295,MATCH($D9,Hierarchy!$A$2:$A$1295,0))),"NODE NOT FOUND")) -> AMER | H9: =IF($D9="","",IFERROR(IF(INDEX(Hierarchy!$E$2:$E$1295,MATCH($D9,Hierarchy!$A$2:$A$1295,0))="","",INDEX(Hierarchy!$E$2:$E$1295,MATCH($D9,Hierarchy!$A$2:$A$1295,0))),"NODE NOT FOUND")) -> Latin America (LATAM) | I9: =IF($D9="","",IFERROR(IF(INDEX(Hierarchy!$F$2:$F$1295,MATCH($D9,Hierarchy!$A$2:$A$1295,0))="","",INDEX(Hierarchy!$F$2:$F$1295,MATCH($D9,Hierarchy!$A$2:$A$1295,0))),"NODE NOT FOUND")) -> Brazil | J9: =IF($D9="","",IFERROR(IF(INDEX(Hierarchy!$G$2:$G$1295,MATCH($D9,Hierarchy!$A$2:$A$1295,0))="","",INDEX(Hierarchy!$G$2:$G$1295,MATCH($D9,Hierarchy!$A$2:$A$1295,0))),"NODE NOT FOUND")) -> BRA | K9: =IF($D9="","",IFERROR(IF(INDEX(Hierarchy!$H$2:$H$1295,MATCH($D9,Hierarchy!$A$2:$A$1295,0))="","",INDEX(Hierarchy!$H$2:$H$1295,MATCH($D9,Hierarchy!$A$2:$A$1295,0))),"NODE NOT FOUND")) -> Acre | L9: =IF($D9="","",IFERROR(IF(INDEX(Hierarchy!$I$2:$I$1295,MATCH($D9,Hierarchy!$A$2:$A$1295,0))="","",INDEX(Hierarchy!$I$2:$I$1295,MATCH($D9,Hierarchy!$A$2:$A$1295,0))),"NODE NOT FOUND")) | M9: =IF(B9="Pre-seeded","Pre-seeded",IF(B9="Review 2026-09-16","Added from review",IF(C9="","New",IF(C9=D9,"","Changed")))) -> Pre-seeded | N9: =TRIM(SUBSTITUTE(SUBSTITUTE(SUBSTITUTE(" "&TRIM(SUBSTITUTE(SUBSTITUTE(SUBSTITUTE(SUBSTITUTE(SUBSTITUTE(SUBSTITUTE(SUBSTITUTE(SUBSTITUTE(SUBSTITUTE(SUBSTITUTE(SUBSTITUTE(SUBSTITUTE(SUBSTITUTE(SUBSTITUTE(SUBSTITUTE(UPPER(TRIM(A9)),"[MEMBER]",""),"{MEMBER}",""),"[MEMBER}",""),"MEMBER]",""),"(A)",""),"""",""),"“",""),"”",""),".",""),":",""),",",""),"–"," "),"-"," "),"/"," "),"&"," AND "))&" "," THE "," ")," TOTAL "," ")," OPERATIONS "," ")) -> ACRE | O9: =IF(COUNTIFS($N$2:$N$2000,N9,$D$2:$D$2000,"<>"&D9)>0,"CONFLICT","")
A10: Adamawa | B10: Pre-seeded | D10: Adamawa | E10: Exact | F10: =IF($D10="","",IFERROR(IF(INDEX(Hierarchy!$B$2:$B$1295,MATCH($D10,Hierarchy!$A$2:$A$1295,0))="","",INDEX(Hierarchy!$B$2:$B$1295,MATCH($D10,Hierarchy!$A$2:$A$1295,0))),"NODE NOT FOUND")) -> State/Province | G10: =IF($D10="","",IFERROR(IF(INDEX(Hierarchy!$D$2:$D$1295,MATCH($D10,Hierarchy!$A$2:$A$1295,0))="","",INDEX(Hierarchy!$D$2:$D$1295,MATCH($D10,Hierarchy!$A$2:$A$1295,0))),"NODE NOT FOUND")) -> EMEA | H10: =IF($D10="","",IFERROR(IF(INDEX(Hierarchy!$E$2:$E$1295,MATCH($D10,Hierarchy!$A$2:$A$1295,0))="","",INDEX(Hierarchy!$E$2:$E$1295,MATCH($D10,Hierarchy!$A$2:$A$1295,0))),"NODE NOT FOUND")) -> Africa | I10: =IF($D10="","",IFERROR(IF(INDEX(Hierarchy!$F$2:$F$1295,MATCH($D10,Hierarchy!$A$2:$A$1295,0))="","",INDEX(Hierarchy!$F$2:$F$1295,MATCH($D10,Hierarchy!$A$2:$A$1295,0))),"NODE NOT FOUND")) -> Nigeria | J10: =IF($D10="","",IFERROR(IF(INDEX(Hierarchy!$G$2:$G$1295,MATCH($D10,Hierarchy!$A$2:$A$1295,0))="","",INDEX(Hierarchy!$G$2:$G$1295,MATCH($D10,Hierarchy!$A$2:$A$1295,0))),"NODE NOT FOUND")) -> NGA | K10: =IF($D10="","",IFERROR(IF(INDEX(Hierarchy!$H$2:$H$1295,MATCH($D10,Hierarchy!$A$2:$A$1295,0))="","",INDEX(Hierarchy!$H$2:$H$1295,MATCH($D10,Hierarchy!$A$2:$A$1295,0))),"NODE NOT FOUND")) -> Adamawa | L10: =IF($D10="","",IFERROR(IF(INDEX(Hierarchy!$I$2:$I$1295,MATCH($D10,Hierarchy!$A$2:$A$1295,0))="","",INDEX(Hierarchy!$I$2:$I$1295,MATCH($D10,Hierarchy!$A$2:$A$1295,0))),"NODE NOT FOUND")) | M10: =IF(B10="Pre-seeded","Pre-seeded",IF(B10="Review 2026-09-16","Added from review",IF(C10="","New",IF(C10=D10,"","Changed")))) -> Pre-seeded | N10: =TRIM(SUBSTITUTE(SUBSTITUTE(SUBSTITUTE(" "&TRIM(SUBSTITUTE(SUBSTITUTE(SUBSTITUTE(SUBSTITUTE(SUBSTITUTE(SUBSTITUTE(SUBSTITUTE(SUBSTITUTE(SUBSTITUTE(SUBSTITUTE(SUBSTITUTE(SUBSTITUTE(SUBSTITUTE(SUBSTITUTE(SUBSTITUTE(UPPER(TRIM(A10)),"[MEMBER]",""),"{MEMBER}",""),"[MEMBER}",""),"MEMBER]",""),"(A)",""),"""",""),"“",""),"”",""),".",""),":",""),",",""),"–"," "),"-"," "),"/"," "),"&"," AND "))&" "," THE "," ")," TOTAL "," ")," OPERATIONS "," ")) -> ADAMAWA | O10: =IF(COUNTIFS($N$2:$N$2000,N10,$D$2:$D$2000,"<>"&D10)>0,"CONFLICT","")
A11: Afghanistan | B11: Pre-seeded | D11: Afghanistan | E11: Exact | F11: =IF($D11="","",IFERROR(IF(INDEX(Hierarchy!$B$2:$B$1295,MATCH($D11,Hierarchy!$A$2:$A$1295,0))="","",INDEX(Hierarchy!$B$2:$B$1295,MATCH($D11,Hierarchy!$A$2:$A$1295,0))),"NODE NOT FOUND")) -> Country | G11: =IF($D11="","",IFERROR(IF(INDEX(Hierarchy!$D$2:$D$1295,MATCH($D11,Hierarchy!$A$2:$A$1295,0))="","",INDEX(Hierarchy!$D$2:$D$1295,MATCH($D11,Hierarchy!$A$2:$A$1295,0))),"NODE NOT FOUND")) -> APAC | H11: =IF($D11="","",IFERROR(IF(INDEX(Hierarchy!$E$2:$E$1295,MATCH($D11,Hierarchy!$A$2:$A$1295,0))="","",INDEX(Hierarchy!$E$2:$E$1295,MATCH($D11,Hierarchy!$A$2:$A$1295,0))),"NODE NOT FOUND")) -> South Asia | I11: =IF($D11="","",IFERROR(IF(INDEX(Hierarchy!$F$2:$F$1295,MATCH($D11,Hierarchy!$A$2:$A$1295,0))="","",INDEX(Hierarchy!$F$2:$F$1295,MATCH($D11,Hierarchy!$A$2:$A$1295,0))),"NODE NOT FOUND")) -> Afghanistan | J11: =IF($D11="","",IFERROR(IF(INDEX(Hierarchy!$G$2:$G$1295,MATCH($D11,Hierarchy!$A$2:$A$1295,0))="","",INDEX(Hierarchy!$G$2:$G$1295,MATCH($D11,Hierarchy!$A$2:$A$1295,0))),"NODE NOT FOUND")) -> AFG | K11: =IF($D11="","",IFERROR(IF(INDEX(Hierarchy!$H$2:$H$1295,MATCH($D11,Hierarchy!$A$2:$A$1295,0))="","",INDEX(Hierarchy!$H$2:$H$1295,MATCH($D11,Hierarchy!$A$2:$A$1295,0))),"NODE NOT FOUND")) | L11: =IF($D11="","",IFERROR(IF(INDEX(Hierarchy!$I$2:$I$1295,MATCH($D11,Hierarchy!$A$2:$A$1295,0))="","",INDEX(Hierarchy!$I$2:$I$1295,MATCH($D11,Hierarchy!$A$2:$A$1295,0))),"NODE NOT FOUND")) | M11: =IF(B11="Pre-seeded","Pre-seeded",IF(B11="Review 2026-09-16","Added from review",IF(C11="","New",IF(C11=D11,"","Changed")))) -> Pre-seeded | N11: =TRIM(SUBSTITUTE(SUBSTITUTE(SUBSTITUTE(" "&TRIM(SUBSTITUTE(SUBSTITUTE(SUBSTITUTE(SUBSTITUTE(SUBSTITUTE(SUBSTITUTE(SUBSTITUTE(SUBSTITUTE(SUBSTITUTE(SUBSTITUTE(SUBSTITUTE(SUBSTITUTE(SUBSTITUTE(SUBSTITUTE(SUBSTITUTE(UPPER(TRIM(A11)),"[MEMBER]",""),"{MEMBER}",""),"[MEMBER}",""),"MEMBER]",""),"(A)",""),"""",""),"“",""),"”",""),".",""),":",""),",",""),"–"," "),"-"," "),"/"," "),"&"," AND "))&" "," THE "," ")," TOTAL "," ")," OPERATIONS "," ")) -> AFGHANISTAN | O11: =IF(COUNTIFS($N$2:$N$2000,N11,$D$2:$D$2000,"<>"&D11)>0,"CONFLICT","")
A12: Africa | B12: Mapping | C12: Africa | D12: Africa | E12: Exact | F12: =IF($D12="","",IFERROR(IF(INDEX(Hierarchy!$B$2:$B$1295,MATCH($D12,Hierarchy!$A$2:$A$1295,0))="","",INDEX(Hierarchy!$B$2:$B$1295,MATCH($D12,Hierarchy!$A$2:$A$1295,0))),"NODE NOT FOUND")) -> Sub-region | G12: =IF($D12="","",IFERROR(IF(INDEX(Hierarchy!$D$2:$D$1295,MATCH($D12,Hierarchy!$A$2:$A$1295,0))="","",INDEX(Hierarchy!$D$2:$D$1295,MATCH($D12,Hierarchy!$A$2:$A$1295,0))),"NODE NOT FOUND")) -> EMEA | H12: =IF($D12="","",IFERROR(IF(INDEX(Hierarchy!$E$2:$E$1295,MATCH($D12,Hierarchy!$A$2:$A$1295,0))="","",INDEX(Hierarchy!$E$2:$E$1295,MATCH($D12,Hierarchy!$A$2:$A$1295,0))),"NODE NOT FOUND")) -> Africa | I12: =IF($D12="","",IFERROR(IF(INDEX(Hierarchy!$F$2:$F$1295,MATCH($D12,Hierarchy!$A$2:$A$1295,0))="","",INDEX(Hierarchy!$F$2:$F$1295,MATCH($D12,Hierarchy!$A$2:$A$1295,0))),"NODE NOT FOUND")) | J12: =IF($D12="","",IFERROR(IF(INDEX(Hierarchy!$G$2:$G$1295,MATCH($D12,Hierarchy!$A$2:$A$1295,0))="","",INDEX(Hierarchy!$G$2:$G$1295,MATCH($D12,Hierarchy!$A$2:$A$1295,0))),"NODE NOT FOUND")) | K12: =IF($D12="","",IFERROR(IF(INDEX(Hierarchy!$H$2:$H$1295,MATCH($D12,Hierarchy!$A$2:$A$1295,0))="","",INDEX(Hierarchy!$H$2:$H$1295,MATCH($D12,Hierarchy!$A$2:$A$1295,0))),"NODE NOT FOUND")) | L12: =IF($D12="","",IFERROR(IF(INDEX(Hierarchy!$I$2:$I$1295,MATCH($D12,Hierarchy!$A$2:$A$1295,0))="","",INDEX(Hierarchy!$I$2:$I$1295,MATCH($D12,Hierarchy!$A$2:$A$1295,0))),"NODE NOT FOUND")) | M12: =IF(B12="Pre-seeded","Pre-seeded",IF(B12="Review 2026-09-16","Added from review",IF(C12="","New",IF(C12=D12,"","Changed")))) | N12: =TRIM(SUBSTITUTE(SUBSTITUTE(SUBSTITUTE(" "&TRIM(SUBSTITUTE(SUBSTITUTE(SUBSTITUTE(SUBSTITUTE(SUBSTITUTE(SUBSTITUTE(SUBSTITUTE(SUBSTITUTE(SUBSTITUTE(SUBSTITUTE(SUBSTITUTE(SUBSTITUTE(SUBSTITUTE(SUBSTITUTE(SUBSTITUTE(UPPER(TRIM(A12)),"[MEMBER]",""),"{MEMBER}",""),"[MEMBER}",""),"MEMBER]",""),"(A)",""),"""",""),"“",""),"”",""),".",""),":",""),",",""),"–"," "),"-"," "),"/"," "),"&"," AND "))&" "," THE "," ")," TOTAL "," ")," OPERATIONS "," ")) -> AFRICA | O12: =IF(COUNTIFS($N$2:$N$2000,N12,$D$2:$D$2000,"<>"&D12)>0,"CONFLICT","")
A13: Africa/Eurasia | B13: final | C13: Africa | D13: Multi-region (Other) | E13: Combined | F13: =IF($D13="","",IFERROR(IF(INDEX(Hierarchy!$B$2:$B$1295,MATCH($D13,Hierarchy!$A$2:$A$1295,0))="","",INDEX(Hierarchy!$B$2:$B$1295,MATCH($D13,Hierarchy!$A$2:$A$1295,0))),"NODE NOT FOUND")) -> Multi-region | G13: =IF($D13="","",IFERROR(IF(INDEX(Hierarchy!$D$2:$D$1295,MATCH($D13,Hierarchy!$A$2:$A$1295,0))="","",INDEX(Hierarchy!$D$2:$D$1295,MATCH($D13,Hierarchy!$A$2:$A$1295,0))),"NODE NOT FOUND")) -> Multi-region | H13: =IF($D13="","",IFERROR(IF(INDEX(Hierarchy!$E$2:$E$1295,MATCH($D13,Hierarchy!$A$2:$A$1295,0))="","",INDEX(Hierarchy!$E$2:$E$1295,MATCH($D13,Hierarchy!$A$2:$A$1295,0))),"NODE NOT FOUND")) | I13: =IF($D13="","",IFERROR(IF(INDEX(Hierarchy!$F$2:$F$1295,MATCH($D13,Hierarchy!$A$2:$A$1295,0))="","",INDEX(Hierarchy!$F$2:$F$1295,MATCH($D13,Hierarchy!$A$2:$A$1295,0))),"NODE NOT FOUND")) | J13: =IF($D13="","",IFERROR(IF(INDEX(Hierarchy!$G$2:$G$1295,MATCH($D13,Hierarchy!$A$2:$A$1295,0))="","",INDEX(Hierarchy!$G$2:$G$1295,MATCH($D13,Hierarchy!$A$2:$A$1295,0))),"NODE NOT FOUND")) | K13: =IF($D13="","",IFERROR(IF(INDEX(Hierarchy!$H$2:$H$1295,MATCH($D13,Hierarchy!$A$2:$A$1295,0))="","",INDEX(Hierarchy!$H$2:$H$1295,MATCH($D13,Hierarchy!$A$2:$A$1295,0))),"NODE NOT FOUND")) | L13: =IF($D13="","",IFERROR(IF(INDEX(Hierarchy!$I$2:$I$1295,MATCH($D13,Hierarchy!$A$2:$A$1295,0))="","",INDEX(Hierarchy!$I$2:$I$1295,MATCH($D13,Hierarchy!$A$2:$A$1295,0))),"NODE NOT FOUND")) | M13: =IF(B13="Pre-seeded","Pre-seeded",IF(B13="Review 2026-09-16","Added from review",IF(C13="","New",IF(C13=D13,"","Changed")))) -> Changed | N13: =TRIM(SUBSTITUTE(SUBSTITUTE(SUBSTITUTE(" "&TRIM(SUBSTITUTE(SUBSTITUTE(SUBSTITUTE(SUBSTITUTE(SUBSTITUTE(SUBSTITUTE(SUBSTITUTE(SUBSTITUTE(SUBSTITUTE(SUBSTITUTE(SUBSTITUTE(SUBSTITUTE(SUBSTITUTE(SUBSTITUTE(SUBSTITUTE(UPPER(TRIM(A13)),"[MEMBER]",""),"{MEMBER}",""),"[MEMBER}",""),"MEMBER]",""),"(A)",""),"""",""),"“",""),"”",""),".",""),":",""),",",""),"–"," "),"-"," "),"/"," "),"&"," AND "))&" "," THE "," ")," TOTAL "," ")," OPERATIONS "," ")) -> AFRICA EURASIA | O13: =IF(COUNTIFS($N$2:$N$2000,N13,$D$2:$D$2000,"<>"&D13)>0,"CONFLICT","") | P13: Spans EMEA and APAC
A14: Aguascalientes | B14: Pre-seeded | D14: Aguascalientes | E14: Exact | F14: =IF($D14="","",IFERROR(IF(INDEX(Hierarchy!$B$2:$B$1295,MATCH($D14,Hierarchy!$A$2:$A$1295,0))="","",INDEX(Hierarchy!$B$2:$B$1295,MATCH($D14,Hierarchy!$A$2:$A$1295,0))),"NODE NOT FOUND")) -> State/Province | G14: =IF($D14="","",IFERROR(IF(INDEX(Hierarchy!$D$2:$D$1295,MATCH($D14,Hierarchy!$A$2:$A$1295,0))="","",INDEX(Hierarchy!$D$2:$D$1295,MATCH($D14,Hierarchy!$A$2:$A$1295,0))),"NODE NOT FOUND")) -> AMER | H14: =IF($D14="","",IFERROR(IF(INDEX(Hierarchy!$E$2:$E$1295,MATCH($D14,Hierarchy!$A$2:$A$1295,0))="","",INDEX(Hierarchy!$E$2:$E$1295,MATCH($D14,Hierarchy!$A$2:$A$1295,0))),"NODE NOT FOUND")) -> Latin America (LATAM) | I14: =IF($D14="","",IFERROR(IF(INDEX(Hierarchy!$F$2:$F$1295,MATCH($D14,Hierarchy!$A$2:$A$1295,0))="","",INDEX(Hierarchy!$F$2:$F$1295,MATCH($D14,Hierarchy!$A$2:$A$1295,0))),"NODE NOT FOUND")) -> Mexico | J14: =IF($D14="","",IFERROR(IF(INDEX(Hierarchy!$G$2:$G$1295,MATCH($D14,Hierarchy!$A$2:$A$1295,0))="","",INDEX(Hierarchy!$G$2:$G$1295,MATCH($D14,Hierarchy!$A$2:$A$1295,0))),"NODE NOT FOUND")) -> MEX | K14: =IF($D14="","",IFERROR(IF(INDEX(Hierarchy!$H$2:$H$1295,MATCH($D14,Hierarchy!$A$2:$A$1295,0))="","",INDEX(Hierarchy!$H$2:$H$1295,MATCH($D14,Hierarchy!$A$2:$A$1295,0))),"NODE NOT FOUND")) -> Aguascalientes | L14: =IF($D14="","",IFERROR(IF(INDEX(Hierarchy!$I$2:$I$1295,MATCH($D14,Hierarchy!$A$2:$A$1295,0))="","",INDEX(Hierarchy!$I$2:$I$1295,MATCH($D14,Hierarchy!$A$2:$A$1295,0))),"NODE NOT FOUND")) | M14: =IF(B14="Pre-seeded","Pre-seeded",IF(B14="Review 2026-09-16","Added from review",IF(C14="","New",IF(C14=D14,"","Changed")))) -> Pre-seeded | N14: =TRIM(SUBSTITUTE(SUBSTITUTE(SUBSTITUTE(" "&TRIM(SUBSTITUTE(SUBSTITUTE(SUBSTITUTE(SUBSTITUTE(SUBSTITUTE(SUBSTITUTE(SUBSTITUTE(SUBSTITUTE(SUBSTITUTE(SUBSTITUTE(SUBSTITUTE(SUBSTITUTE(SUBSTITUTE(SUBSTITUTE(SUBSTITUTE(UPPER(TRIM(A14)),"[MEMBER]",""),"{MEMBER}",""),"[MEMBER}",""),"MEMBER]",""),"(A)",""),"""",""),"“",""),"”",""),".",""),":",""),",",""),"–"," "),"-"," "),"/"," "),"&"," AND "))&" "," THE "," ")," TOTAL "," ")," OPERATIONS "," ")) -> AGUASCALIENTES | O14: =IF(COUNTIFS($N$2:$N$2000,N14,$D$2:$D$2000,"<>"&D14)>0,"CONFLICT","")
A15: Aichi | B15: Pre-seeded | D15: Aichi | E15: Exact | F15: =IF($D15="","",IFERROR(IF(INDEX(Hierarchy!$B$2:$B$1295,MATCH($D15,Hierarchy!$A$2:$A$1295,0))="","",INDEX(Hierarchy!$B$2:$B$1295,MATCH($D15,Hierarchy!$A$2:$A$1295,0))),"NODE NOT FOUND")) -> State/Province | G15: =IF($D15="","",IFERROR(IF(INDEX(Hierarchy!$D$2:$D$1295,MATCH($D15,Hierarchy!$A$2:$A$1295,0))="","",INDEX(Hierarchy!$D$2:$D$1295,MATCH($D15,Hierarchy!$A$2:$A$1295,0))),"NODE NOT FOUND")) -> APAC | H15: =IF($D15="","",IFERROR(IF(INDEX(Hierarchy!$E$2:$E$1295,MATCH($D15,Hierarchy!$A$2:$A$1295,0))="","",INDEX(Hierarchy!$E$2:$E$1295,MATCH($D15,Hierarchy!$A$2:$A$1295,0))),"NODE NOT FOUND")) -> East Asia | I15: =IF($D15="","",IFERROR(IF(INDEX(Hierarchy!$F$2:$F$1295,MATCH($D15,Hierarchy!$A$2:$A$1295,0))="","",INDEX(Hierarchy!$F$2:$F$1295,MATCH($D15,Hierarchy!$A$2:$A$1295,0))),"NODE NOT FOUND")) -> Japan | J15: =IF($D15="","",IFERROR(IF(INDEX(Hierarchy!$G$2:$G$1295,MATCH($D15,Hierarchy!$A$2:$A$1295,0))="","",INDEX(Hierarchy!$G$2:$G$1295,MATCH($D15,Hierarchy!$A$2:$A$1295,0))),"NODE NOT FOUND")) -> JPN | K15: =IF($D15="","",IFERROR(IF(INDEX(Hierarchy!$H$2:$H$1295,MATCH($D15,Hierarchy!$A$2:$A$1295,0))="","",INDEX(Hierarchy!$H$2:$H$1295,MATCH($D15,Hierarchy!$A$2:$A$1295,0))),"NODE NOT FOUND")) -> Aichi | L15: =IF($D15="","",IFERROR(IF(INDEX(Hierarchy!$I$2:$I$1295,MATCH($D15,Hierarchy!$A$2:$A$1295,0))="","",INDEX(Hierarchy!$I$2:$I$1295,MATCH($D15,Hierarchy!$A$2:$A$1295,0))),"NODE NOT FOUND")) | M15: =IF(B15="Pre-seeded","Pre-seeded",IF(B15="Review 2026-09-16","Added from review",IF(C15="","New",IF(C15=D15,"","Changed")))) -> Pre-seeded | N15: =TRIM(SUBSTITUTE(SUBSTITUTE(SUBSTITUTE(" "&TRIM(SUBSTITUTE(SUBSTITUTE(SUBSTITUTE(SUBSTITUTE(SUBSTITUTE(SUBSTITUTE(SUBSTITUTE(SUBSTITUTE(SUBSTITUTE(SUBSTITUTE(SUBSTITUTE(SUBSTITUTE(SUBSTITUTE(SUBSTITUTE(SUBSTITUTE(UPPER(TRIM(A15)),"[MEMBER]",""),"{MEMBER}",""),"[MEMBER}",""),"MEMBER]",""),"(A)",""),"""",""),"“",""),"”",""),".",""),":",""),",",""),"–"," "),"-"," "),"/"," "),"&"," AND "))&" "," THE "," ")," TOTAL "," ")," OPERATIONS "," ")) -> AICHI | O15: =IF(COUNTIFS($N$2:$N$2000,N15,$D$2:$D$2000,"<>"&D15)>0,"CONFLICT","")
A16: Ajman | B16: Pre-seeded | D16: Ajman | E16: Exact | F16: =IF($D16="","",IFERROR(IF(INDEX(Hierarchy!$B$2:$B$1295,MATCH($D16,Hierarchy!$A$2:$A$1295,0))="","",INDEX(Hierarchy!$B$2:$B$1295,MATCH($D16,Hierarchy!$A$2:$A$1295,0))),"NODE NOT FOUND")) -> State/Province | G16: =IF($D16="","",IFERROR(IF(INDEX(Hierarchy!$D$2:$D$1295,MATCH($D16,Hierarchy!$A$2:$A$1295,0))="","",INDEX(Hierarchy!$D$2:$D$1295,MATCH($D16,Hierarchy!$A$2:$A$1295,0))),"NODE NOT FOUND")) -> EMEA | H16: =IF($D16="","",IFERROR(IF(INDEX(Hierarchy!$E$2:$E$1295,MATCH($D16,Hierarchy!$A$2:$A$1295,0))="","",INDEX(Hierarchy!$E$2:$E$1295,MATCH($D16,Hierarchy!$A$2:$A$1295,0))),"NODE NOT FOUND")) -> Middle East | I16: =IF($D16="","",IFERROR(IF(INDEX(Hierarchy!$F$2:$F$1295,MATCH($D16,Hierarchy!$A$2:$A$1295,0))="","",INDEX(Hierarchy!$F$2:$F$1295,MATCH($D16,Hierarchy!$A$2:$A$1295,0))),"NODE NOT FOUND")) -> United Arab Emirates | J16: =IF($D16="","",IFERROR(IF(INDEX(Hierarchy!$G$2:$G$1295,MATCH($D16,Hierarchy!$A$2:$A$1295,0))="","",INDEX(Hierarchy!$G$2:$G$1295,MATCH($D16,Hierarchy!$A$2:$A$1295,0))),"NODE NOT FOUND")) -> ARE | K16: =IF($D16="","",IFERROR(IF(INDEX(Hierarchy!$H$2:$H$1295,MATCH($D16,Hierarchy!$A$2:$A$1295,0))="","",INDEX(Hierarchy!$H$2:$H$1295,MATCH($D16,Hierarchy!$A$2:$A$1295,0))),"NODE NOT FOUND")) -> Ajman | L16: =IF($D16="","",IFERROR(IF(INDEX(Hierarchy!$I$2:$I$1295,MATCH($D16,Hierarchy!$A$2:$A$1295,0))="","",INDEX(Hierarchy!$I$2:$I$1295,MATCH($D16,Hierarchy!$A$2:$A$1295,0))),"NODE NOT FOUND")) | M16: =IF(B16="Pre-seeded","Pre-seeded",IF(B16="Review 2026-09-16","Added from review",IF(C16="","New",IF(C16=D16,"","Changed")))) -> Pre-seeded | N16: =TRIM(SUBSTITUTE(SUBSTITUTE(SUBSTITUTE(" "&TRIM(SUBSTITUTE(SUBSTITUTE(SUBSTITUTE(SUBSTITUTE(SUBSTITUTE(SUBSTITUTE(SUBSTITUTE(SUBSTITUTE(SUBSTITUTE(SUBSTITUTE(SUBSTITUTE(SUBSTITUTE(SUBSTITUTE(SUBSTITUTE(SUBSTITUTE(UPPER(TRIM(A16)),"[MEMBER]",""),"{MEMBER}",""),"[MEMBER}",""),"MEMBER]",""),"(A)",""),"""",""),"“",""),"”",""),".",""),":",""),",",""),"–"," "),"-"," "),"/"," "),"&"," AND "))&" "," THE "," ")," TOTAL "," ")," OPERATIONS "," ")) -> AJMAN | O16: =IF(COUNTIFS($N$2:$N$2000,N16,$D$2:$D$2000,"<>"&D16)>0,"CONFLICT","")
A17: Akita | B17: Pre-seeded | D17: Akita | E17: Exact | F17: =IF($D17="","",IFERROR(IF(INDEX(Hierarchy!$B$2:$B$1295,MATCH($D17,Hierarchy!$A$2:$A$1295,0))="","",INDEX(Hierarchy!$B$2:$B$1295,MATCH($D17,Hierarchy!$A$2:$A$1295,0))),"NODE NOT FOUND")) -> State/Province | G17: =IF($D17="","",IFERROR(IF(INDEX(Hierarchy!$D$2:$D$1295,MATCH($D17,Hierarchy!$A$2:$A$1295,0))="","",INDEX(Hierarchy!$D$2:$D$1295,MATCH($D17,Hierarchy!$A$2:$A$1295,0))),"NODE NOT FOUND")) -> APAC | H17: =IF($D17="","",IFERROR(IF(INDEX(Hierarchy!$E$2:$E$1295,MATCH($D17,Hierarchy!$A$2:$A$1295,0))="","",INDEX(Hierarchy!$E$2:$E$1295,MATCH($D17,Hierarchy!$A$2:$A$1295,0))),"NODE NOT FOUND")) -> East Asia | I17: =IF($D17="","",IFERROR(IF(INDEX(Hierarchy!$F$2:$F$1295,MATCH($D17,Hierarchy!$A$2:$A$1295,0))="","",INDEX(Hierarchy!$F$2:$F$1295,MATCH($D17,Hierarchy!$A$2:$A$1295,0))),"NODE NOT FOUND")) -> Japan | J17: =IF($D17="","",IFERROR(IF(INDEX(Hierarchy!$G$2:$G$1295,MATCH($D17,Hierarchy!$A$2:$A$1295,0))="","",INDEX(Hierarchy!$G$2:$G$1295,MATCH($D17,Hierarchy!$A$2:$A$1295,0))),"NODE NOT FOUND")) -> JPN | K17: =IF($D17="","",IFERROR(IF(INDEX(Hierarchy!$H$2:$H$1295,MATCH($D17,Hierarchy!$A$2:$A$1295,0))="","",INDEX(Hierarchy!$H$2:$H$1295,MATCH($D17,Hierarchy!$A$2:$A$1295,0))),"NODE NOT FOUND")) -> Akita | L17: =IF($D17="","",IFERROR(IF(INDEX(Hierarchy!$I$2:$I$1295,MATCH($D17,Hierarchy!$A$2:$A$1295,0))="","",INDEX(Hierarchy!$I$2:$I$1295,MATCH($D17,Hierarchy!$A$2:$A$1295,0))),"NODE NOT FOUND")) | M17: =IF(B17="Pre-seeded","Pre-seeded",IF(B17="Review 2026-09-16","Added from review",IF(C17="","New",IF(C17=D17,"","Changed")))) -> Pre-seeded | N17: =TRIM(SUBSTITUTE(SUBSTITUTE(SUBSTITUTE(" "&TRIM(SUBSTITUTE(SUBSTITUTE(SUBSTITUTE(SUBSTITUTE(SUBSTITUTE(SUBSTITUTE(SUBSTITUTE(SUBSTITUTE(SUBSTITUTE(SUBSTITUTE(SUBSTITUTE(SUBSTITUTE(SUBSTITUTE(SUBSTITUTE(SUBSTITUTE(UPPER(TRIM(A17)),"[MEMBER]",""),"{MEMBER}",""),"[MEMBER}",""),"MEMBER]",""),"(A)",""),"""",""),"“",""),"”",""),".",""),":",""),",",""),"–"," "),"-"," "),"/"," "),"&"," AND "))&" "," THE "," ")," TOTAL "," ")," OPERATIONS "," ")) -> AKITA | O17: =IF(COUNTIFS($N$2:$N$2000,N17,$D$2:$D$2000,"<>"&D17)>0,"CONFLICT","")
A18: Akwa Ibom | B18: Pre-seeded | D18: Akwa Ibom | E18: Exact | F18: =IF($D18="","",IFERROR(IF(INDEX(Hierarchy!$B$2:$B$1295,MATCH($D18,Hierarchy!$A$2:$A$1295,0))="","",INDEX(Hierarchy!$B$2:$B$1295,MATCH($D18,Hierarchy!$A$2:$A$1295,0))),"NODE NOT FOUND")) -> State/Province | G18: =IF($D18="","",IFERROR(IF(INDEX(Hierarchy!$D$2:$D$1295,MATCH($D18,Hierarchy!$A$2:$A$1295,0))="","",INDEX(Hierarchy!$D$2:$D$1295,MATCH($D18,Hierarchy!$A$2:$A$1295,0))),"NODE NOT FOUND")) -> EMEA | H18: =IF($D18="","",IFERROR(IF(INDEX(Hierarchy!$E$2:$E$1295,MATCH($D18,Hierarchy!$A$2:$A$1295,0))="","",INDEX(Hierarchy!$E$2:$E$1295,MATCH($D18,Hierarchy!$A$2:$A$1295,0))),"NODE NOT FOUND")) -> Africa | I18: =IF($D18="","",IFERROR(IF(INDEX(Hierarchy!$F$2:$F$1295,MATCH($D18,Hierarchy!$A$2:$A$1295,0))="","",INDEX(Hierarchy!$F$2:$F$1295,MATCH($D18,Hierarchy!$A$2:$A$1295,0))),"NODE NOT FOUND")) -> Nigeria | J18: =IF($D18="","",IFERROR(IF(INDEX(Hierarchy!$G$2:$G$1295,MATCH($D18,Hierarchy!$A$2:$A$1295,0))="","",INDEX(Hierarchy!$G$2:$G$1295,MATCH($D18,Hierarchy!$A$2:$A$1295,0))),"NODE NOT FOUND")) -> NGA | K18: =IF($D18="","",IFERROR(IF(INDEX(Hierarchy!$H$2:$H$1295,MATCH($D18,Hierarchy!$A$2:$A$1295,0))="","",INDEX(Hierarchy!$H$2:$H$1295,MATCH($D18,Hierarchy!$A$2:$A$1295,0))),"NODE NOT FOUND")) -> Akwa Ibom | L18: =IF($D18="","",IFERROR(IF(INDEX(Hierarchy!$I$2:$I$1295,MATCH($D18,Hierarchy!$A$2:$A$1295,0))="","",INDEX(Hierarchy!$I$2:$I$1295,MATCH($D18,Hierarchy!$A$2:$A$1295,0))),"NODE NOT FOUND")) | M18: =IF(B18="Pre-seeded","Pre-seeded",IF(B18="Review 2026-09-16","Added from review",IF(C18="","New",IF(C18=D18,"","Changed")))) -> Pre-seeded | N18: =TRIM(SUBSTITUTE(SUBSTITUTE(SUBSTITUTE(" "&TRIM(SUBSTITUTE(SUBSTITUTE(SUBSTITUTE(SUBSTITUTE(SUBSTITUTE(SUBSTITUTE(SUBSTITUTE(SUBSTITUTE(SUBSTITUTE(SUBSTITUTE(SUBSTITUTE(SUBSTITUTE(SUBSTITUTE(SUBSTITUTE(SUBSTITUTE(UPPER(TRIM(A18)),"[MEMBER]",""),"{MEMBER}",""),"[MEMBER}",""),"MEMBER]",""),"(A)",""),"""",""),"“",""),"”",""),".",""),":",""),",",""),"–"," "),"-"," "),"/"," "),"&"," AND "))&" "," THE "," ")," TOTAL "," ")," OPERATIONS "," ")) -> AKWA IBOM | O18: =IF(COUNTIFS($N$2:$N$2000,N18,$D$2:$D$2000,"<>"&D18)>0,"CONFLICT","")
A19: Al Bahah Province | B19: Pre-seeded | D19: Al Bahah Province | E19: Exact | F19: =IF($D19="","",IFERROR(IF(INDEX(Hierarchy!$B$2:$B$1295,MATCH($D19,Hierarchy!$A$2:$A$1295,0))="","",INDEX(Hierarchy!$B$2:$B$1295,MATCH($D19,Hierarchy!$A$2:$A$1295,0))),"NODE NOT FOUND")) -> State/Province | G19: =IF($D19="","",IFERROR(IF(INDEX(Hierarchy!$D$2:$D$1295,MATCH($D19,Hierarchy!$A$2:$A$1295,0))="","",INDEX(Hierarchy!$D$2:$D$1295,MATCH($D19,Hierarchy!$A$2:$A$1295,0))),"NODE NOT FOUND")) -> EMEA | H19: =IF($D19="","",IFERROR(IF(INDEX(Hierarchy!$E$2:$E$1295,MATCH($D19,Hierarchy!$A$2:$A$1295,0))="","",INDEX(Hierarchy!$E$2:$E$1295,MATCH($D19,Hierarchy!$A$2:$A$1295,0))),"NODE NOT FOUND")) -> Middle East | I19: =IF($D19="","",IFERROR(IF(INDEX(Hierarchy!$F$2:$F$1295,MATCH($D19,Hierarchy!$A$2:$A$1295,0))="","",INDEX(Hierarchy!$F$2:$F$1295,MATCH($D19,Hierarchy!$A$2:$A$1295,0))),"NODE NOT FOUND")) -> Saudi Arabia | J19: =IF($D19="","",IFERROR(IF(INDEX(Hierarchy!$G$2:$G$1295,MATCH($D19,Hierarchy!$A$2:$A$1295,0))="","",INDEX(Hierarchy!$G$2:$G$1295,MATCH($D19,Hierarchy!$A$2:$A$1295,0))),"NODE NOT FOUND")) -> SAU | K19: =IF($D19="","",IFERROR(IF(INDEX(Hierarchy!$H$2:$H$1295,MATCH($D19,Hierarchy!$A$2:$A$1295,0))="","",INDEX(Hierarchy!$H$2:$H$1295,MATCH($D19,Hierarchy!$A$2:$A$1295,0))),"NODE NOT FOUND")) -> Al Bahah Province | L19: =IF($D19="","",IFERROR(IF(INDEX(Hierarchy!$I$2:$I$1295,MATCH($D19,Hierarchy!$A$2:$A$1295,0))="","",INDEX(Hierarchy!$I$2:$I$1295,MATCH($D19,Hierarchy!$A$2:$A$1295,0))),"NODE NOT FOUND")) | M19: =IF(B19="Pre-seeded","Pre-seeded",IF(B19="Review 2026-09-16","Added from review",IF(C19="","New",IF(C19=D19,"","Changed")))) -> Pre-seeded | N19: =TRIM(SUBSTITUTE(SUBSTITUTE(SUBSTITUTE(" "&TRIM(SUBSTITUTE(SUBSTITUTE(SUBSTITUTE(SUBSTITUTE(SUBSTITUTE(SUBSTITUTE(SUBSTITUTE(SUBSTITUTE(SUBSTITUTE(SUBSTITUTE(SUBSTITUTE(SUBSTITUTE(SUBSTITUTE(SUBSTITUTE(SUBSTITUTE(UPPER(TRIM(A19)),"[MEMBER]",""),"{MEMBER}",""),"[MEMBER}",""),"MEMBER]",""),"(A)",""),"""",""),"“",""),"”",""),".",""),":",""),",",""),"–"," "),"-"," "),"/"," "),"&"," AND "))&" "," THE "," ")," TOTAL "," ")," OPERATIONS "," ")) -> AL BAHAH PROVINCE | O19: =IF(COUNTIFS($N$2:$N$2000,N19,$D$2:$D$2000,"<>"&D19)>0,"CONFLICT","")
A20: Al Jawf Province | B20: Pre-seeded | D20: Al Jawf Province | E20: Exact | F20: =IF($D20="","",IFERROR(IF(INDEX(Hierarchy!$B$2:$B$1295,MATCH($D20,Hierarchy!$A$2:$A$1295,0))="","",INDEX(Hierarchy!$B$2:$B$1295,MATCH($D20,Hierarchy!$A$2:$A$1295,0))),"NODE NOT FOUND")) -> State/Province | G20: =IF($D20="","",IFERROR(IF(INDEX(Hierarchy!$D$2:$D$1295,MATCH($D20,Hierarchy!$A$2:$A$1295,0))="","",INDEX(Hierarchy!$D$2:$D$1295,MATCH($D20,Hierarchy!$A$2:$A$1295,0))),"NODE NOT FOUND")) -> EMEA | H20: =IF($D20="","",IFERROR(IF(INDEX(Hierarchy!$E$2:$E$1295,MATCH($D20,Hierarchy!$A$2:$A$1295,0))="","",INDEX(Hierarchy!$E$2:$E$1295,MATCH($D20,Hierarchy!$A$2:$A$1295,0))),"NODE NOT FOUND")) -> Middle East | I20: =IF($D20="","",IFERROR(IF(INDEX(Hierarchy!$F$2:$F$1295,MATCH($D20,Hierarchy!$A$2:$A$1295,0))="","",INDEX(Hierarchy!$F$2:$F$1295,MATCH($D20,Hierarchy!$A$2:$A$1295,0))),"NODE NOT FOUND")) -> Saudi Arabia | J20: =IF($D20="","",IFERROR(IF(INDEX(Hierarchy!$G$2:$G$1295,MATCH($D20,Hierarchy!$A$2:$A$1295,0))="","",INDEX(Hierarchy!$G$2:$G$1295,MATCH($D20,Hierarchy!$A$2:$A$1295,0))),"NODE NOT FOUND")) -> SAU | K20: =IF($D20="","",IFERROR(IF(INDEX(Hierarchy!$H$2:$H$1295,MATCH($D20,Hierarchy!$A$2:$A$1295,0))="","",INDEX(Hierarchy!$H$2:$H$1295,MATCH($D20,Hierarchy!$A$2:$A$1295,0))),"NODE NOT FOUND")) -> Al Jawf Province | L20: =IF($D20="","",IFERROR(IF(INDEX(Hierarchy!$I$2:$I$1295,MATCH($D20,Hierarchy!$A$2:$A$1295,0))="","",INDEX(Hierarchy!$I$2:$I$1295,MATCH($D20,Hierarchy!$A$2:$A$1295,0))),"NODE NOT FOUND")) | M20: =IF(B20="Pre-seeded","Pre-seeded",IF(B20="Review 2026-09-16","Added from review",IF(C20="","New",IF(C20=D20,"","Changed")))) -> Pre-seeded | N20: =TRIM(SUBSTITUTE(SUBSTITUTE(SUBSTITUTE(" "&TRIM(SUBSTITUTE(SUBSTITUTE(SUBSTITUTE(SUBSTITUTE(SUBSTITUTE(SUBSTITUTE(SUBSTITUTE(SUBSTITUTE(SUBSTITUTE(SUBSTITUTE(SUBSTITUTE(SUBSTITUTE(SUBSTITUTE(SUBSTITUTE(SUBSTITUTE(UPPER(TRIM(A20)),"[MEMBER]",""),"{MEMBER}",""),"[MEMBER}",""),"MEMBER]",""),"(A)",""),"""",""),"“",""),"”",""),".",""),":",""),",",""),"–"," "),"-"," "),"/"," "),"&"," AND "))&" "," THE "," ")," TOTAL "," ")," OPERATIONS "," ")) -> AL JAWF PROVINCE | O20: =IF(COUNTIFS($N$2:$N$2000,N20,$D$2:$D$2000,"<>"&D20)>0,"CONFLICT","")
A21: ALABAMA | B21: Mapping | C21: Alabama | D21: Alabama | E21: Exact | F21: =IF($D21="","",IFERROR(IF(INDEX(Hierarchy!$B$2:$B$1295,MATCH($D21,Hierarchy!$A$2:$A$1295,0))="","",INDEX(Hierarchy!$B$2:$B$1295,MATCH($D21,Hierarchy!$A$2:$A$1295,0))),"NODE NOT FOUND")) -> State/Province | G21: =IF($D21="","",IFERROR(IF(INDEX(Hierarchy!$D$2:$D$1295,MATCH($D21,Hierarchy!$A$2:$A$1295,0))="","",INDEX(Hierarchy!$D$2:$D$1295,MATCH($D21,Hierarchy!$A$2:$A$1295,0))),"NODE NOT FOUND")) -> AMER | H21: =IF($D21="","",IFERROR(IF(INDEX(Hierarchy!$E$2:$E$1295,MATCH($D21,Hierarchy!$A$2:$A$1295,0))="","",INDEX(Hierarchy!$E$2:$E$1295,MATCH($D21,Hierarchy!$A$2:$A$1295,0))),"NODE NOT FOUND")) -> North America (NORAM) | I21: =IF($D21="","",IFERROR(IF(INDEX(Hierarchy!$F$2:$F$1295,MATCH($D21,Hierarchy!$A$2:$A$1295,0))="","",INDEX(Hierarchy!$F$2:$F$1295,MATCH($D21,Hierarchy!$A$2:$A$1295,0))),"NODE NOT FOUND")) -> United States | J21: =IF($D21="","",IFERROR(IF(INDEX(Hierarchy!$G$2:$G$1295,MATCH($D21,Hierarchy!$A$2:$A$1295,0))="","",INDEX(Hierarchy!$G$2:$G$1295,MATCH($D21,Hierarchy!$A$2:$A$1295,0))),"NODE NOT FOUND")) -> USA | K21: =IF($D21="","",IFERROR(IF(INDEX(Hierarchy!$H$2:$H$1295,MATCH($D21,Hierarchy!$A$2:$A$1295,0))="","",INDEX(Hierarchy!$H$2:$H$1295,MATCH($D21,Hierarchy!$A$2:$A$1295,0))),"NODE NOT FOUND")) -> Alabama | L21: =IF($D21="","",IFERROR(IF(INDEX(Hierarchy!$I$2:$I$1295,MATCH($D21,Hierarchy!$A$2:$A$1295,0))="","",INDEX(Hierarchy!$I$2:$I$1295,MATCH($D21,Hierarchy!$A$2:$A$1295,0))),"NODE NOT FOUND")) | M21: =IF(B21="Pre-seeded","Pre-seeded",IF(B21="Review 2026-09-16","Added from review",IF(C21="","New",IF(C21=D21,"","Changed")))) | N21: =TRIM(SUBSTITUTE(SUBSTITUTE(SUBSTITUTE(" "&TRIM(SUBSTITUTE(SUBSTITUTE(SUBSTITUTE(SUBSTITUTE(SUBSTITUTE(SUBSTITUTE(SUBSTITUTE(SUBSTITUTE(SUBSTITUTE(SUBSTITUTE(SUBSTITUTE(SUBSTITUTE(SUBSTITUTE(SUBSTITUTE(SUBSTITUTE(UPPER(TRIM(A21)),"[MEMBER]",""),"{MEMBER}",""),"[MEMBER}",""),"MEMBER]",""),"(A)",""),"""",""),"“",""),"”",""),".",""),":",""),",",""),"–"," "),"-"," "),"/"," "),"&"," AND "))&" "," THE "," ")," TOTAL "," ")," OPERATIONS "," ")) -> ALABAMA | O21: =IF(COUNTIFS($N$2:$N$2000,N21,$D$2:$D$2000,"<>"&D21)>0,"CONFLICT","")
A22: Alabama | B22: Mapping | C22: Alabama | D22: Alabama | E22: Exact | F22: =IF($D22="","",IFERROR(IF(INDEX(Hierarchy!$B$2:$B$1295,MATCH($D22,Hierarchy!$A$2:$A$1295,0))="","",INDEX(Hierarchy!$B$2:$B$1295,MATCH($D22,Hierarchy!$A$2:$A$1295,0))),"NODE NOT FOUND")) -> State/Province | G22: =IF($D22="","",IFERROR(IF(INDEX(Hierarchy!$D$2:$D$1295,MATCH($D22,Hierarchy!$A$2:$A$1295,0))="","",INDEX(Hierarchy!$D$2:$D$1295,MATCH($D22,Hierarchy!$A$2:$A$1295,0))),"NODE NOT FOUND")) -> AMER | H22: =IF($D22="","",IFERROR(IF(INDEX(Hierarchy!$E$2:$E$1295,MATCH($D22,Hierarchy!$A$2:$A$1295,0))="","",INDEX(Hierarchy!$E$2:$E$1295,MATCH($D22,Hierarchy!$A$2:$A$1295,0))),"NODE NOT FOUND")) -> North America (NORAM) | I22: =IF($D22="","",IFERROR(IF(INDEX(Hierarchy!$F$2:$F$1295,MATCH($D22,Hierarchy!$A$2:$A$1295,0))="","",INDEX(Hierarchy!$F$2:$F$1295,MATCH($D22,Hierarchy!$A$2:$A$1295,0))),"NODE NOT FOUND")) -> United States | J22: =IF($D22="","",IFERROR(IF(INDEX(Hierarchy!$G$2:$G$1295,MATCH($D22,Hierarchy!$A$2:$A$1295,0))="","",INDEX(Hierarchy!$G$2:$G$1295,MATCH($D22,Hierarchy!$A$2:$A$1295,0))),"NODE NOT FOUND")) -> USA | K22: =IF($D22="","",IFERROR(IF(INDEX(Hierarchy!$H$2:$H$1295,MATCH($D22,Hierarchy!$A$2:$A$1295,0))="","",INDEX(Hierarchy!$H$2:$H$1295,MATCH($D22,Hierarchy!$A$2:$A$1295,0))),"NODE NOT FOUND")) -> Alabama | L22: =IF($D22="","",IFERROR(IF(INDEX(Hierarchy!$I$2:$I$1295,MATCH($D22,Hierarchy!$A$2:$A$1295,0))="","",INDEX(Hierarchy!$I$2:$I$1295,MATCH($D22,Hierarchy!$A$2:$A$1295,0))),"NODE NOT FOUND")) | M22: =IF(B22="Pre-seeded","Pre-seeded",IF(B22="Review 2026-09-16","Added from review",IF(C22="","New",IF(C22=D22,"","Changed")))) | N22: =TRIM(SUBSTITUTE(SUBSTITUTE(SUBSTITUTE(" "&TRIM(SUBSTITUTE(SUBSTITUTE(SUBSTITUTE(SUBSTITUTE(SUBSTITUTE(SUBSTITUTE(SUBSTITUTE(SUBSTITUTE(SUBSTITUTE(SUBSTITUTE(SUBSTITUTE(SUBSTITUTE(SUBSTITUTE(SUBSTITUTE(SUBSTITUTE(UPPER(TRIM(A22)),"[MEMBER]",""),"{MEMBER}",""),"[MEMBER}",""),"MEMBER]",""),"(A)",""),"""",""),"“",""),"”",""),".",""),":",""),",",""),"–"," "),"-"," "),"/"," "),"&"," AND "))&" "," THE "," ")," TOTAL "," ")," OPERATIONS "," ")) -> ALABAMA | O22: =IF(COUNTIFS($N$2:$N$2000,N22,$D$2:$D$2000,"<>"&D22)>0,"CONFLICT","")
A23: Alagoas | B23: Pre-seeded | D23: Alagoas | E23: Exact | F23: =IF($D23="","",IFERROR(IF(INDEX(Hierarchy!$B$2:$B$1295,MATCH($D23,Hierarchy!$A$2:$A$1295,0))="","",INDEX(Hierarchy!$B$2:$B$1295,MATCH($D23,Hierarchy!$A$2:$A$1295,0))),"NODE NOT FOUND")) -> State/Province | G23: =IF($D23="","",IFERROR(IF(INDEX(Hierarchy!$D$2:$D$1295,MATCH($D23,Hierarchy!$A$2:$A$1295,0))="","",INDEX(Hierarchy!$D$2:$D$1295,MATCH($D23,Hierarchy!$A$2:$A$1295,0))),"NODE NOT FOUND")) -> AMER | H23: =IF($D23="","",IFERROR(IF(INDEX(Hierarchy!$E$2:$E$1295,MATCH($D23,Hierarchy!$A$2:$A$1295,0))="","",INDEX(Hierarchy!$E$2:$E$1295,MATCH($D23,Hierarchy!$A$2:$A$1295,0))),"NODE NOT FOUND")) -> Latin America (LATAM) | I23: =IF($D23="","",IFERROR(IF(INDEX(Hierarchy!$F$2:$F$1295,MATCH($D23,Hierarchy!$A$2:$A$1295,0))="","",INDEX(Hierarchy!$F$2:$F$1295,MATCH($D23,Hierarchy!$A$2:$A$1295,0))),"NODE NOT FOUND")) -> Brazil | J23: =IF($D23="","",IFERROR(IF(INDEX(Hierarchy!$G$2:$G$1295,MATCH($D23,Hierarchy!$A$2:$A$1295,0))="","",INDEX(Hierarchy!$G$2:$G$1295,MATCH($D23,Hierarchy!$A$2:$A$1295,0))),"NODE NOT FOUND")) -> BRA | K23: =IF($D23="","",IFERROR(IF(INDEX(Hierarchy!$H$2:$H$1295,MATCH($D23,Hierarchy!$A$2:$A$1295,0))="","",INDEX(Hierarchy!$H$2:$H$1295,MATCH($D23,Hierarchy!$A$2:$A$1295,0))),"NODE NOT FOUND")) -> Alagoas | L23: =IF($D23="","",IFERROR(IF(INDEX(Hierarchy!$I$2:$I$1295,MATCH($D23,Hierarchy!$A$2:$A$1295,0))="","",INDEX(Hierarchy!$I$2:$I$1295,MATCH($D23,Hierarchy!$A$2:$A$1295,0))),"NODE NOT FOUND")) | M23: =IF(B23="Pre-seeded","Pre-seeded",IF(B23="Review 2026-09-16","Added from review",IF(C23="","New",IF(C23=D23,"","Changed")))) -> Pre-seeded | N23: =TRIM(SUBSTITUTE(SUBSTITUTE(SUBSTITUTE(" "&TRIM(SUBSTITUTE(SUBSTITUTE(SUBSTITUTE(SUBSTITUTE(SUBSTITUTE(SUBSTITUTE(SUBSTITUTE(SUBSTITUTE(SUBSTITUTE(SUBSTITUTE(SUBSTITUTE(SUBSTITUTE(SUBSTITUTE(SUBSTITUTE(SUBSTITUTE(UPPER(TRIM(A23)),"[MEMBER]",""),"{MEMBER}",""),"[MEMBER}",""),"MEMBER]",""),"(A)",""),"""",""),"“",""),"”",""),".",""),":",""),",",""),"–"," "),"-"," "),"/"," "),"&"," AND "))&" "," THE "," ")," TOTAL "," ")," OPERATIONS "," ")) -> ALAGOAS | O23: =IF(COUNTIFS($N$2:$N$2000,N23,$D$2:$D$2000,"<>"&D23)>0,"CONFLICT","")
A24: Aland Islands | B24: Pre-seeded | D24: Åland Islands | E24: Exact | F24: =IF($D24="","",IFERROR(IF(INDEX(Hierarchy!$B$2:$B$1295,MATCH($D24,Hierarchy!$A$2:$A$1295,0))="","",INDEX(Hierarchy!$B$2:$B$1295,MATCH($D24,Hierarchy!$A$2:$A$1295,0))),"NODE NOT FOUND")) -> Country | G24: =IF($D24="","",IFERROR(IF(INDEX(Hierarchy!$D$2:$D$1295,MATCH($D24,Hierarchy!$A$2:$A$1295,0))="","",INDEX(Hierarchy!$D$2:$D$1295,MATCH($D24,Hierarchy!$A$2:$A$1295,0))),"NODE NOT FOUND")) -> EMEA | H24: =IF($D24="","",IFERROR(IF(INDEX(Hierarchy!$E$2:$E$1295,MATCH($D24,Hierarchy!$A$2:$A$1295,0))="","",INDEX(Hierarchy!$E$2:$E$1295,MATCH($D24,Hierarchy!$A$2:$A$1295,0))),"NODE NOT FOUND")) -> Europe | I24: =IF($D24="","",IFERROR(IF(INDEX(Hierarchy!$F$2:$F$1295,MATCH($D24,Hierarchy!$A$2:$A$1295,0))="","",INDEX(Hierarchy!$F$2:$F$1295,MATCH($D24,Hierarchy!$A$2:$A$1295,0))),"NODE NOT FOUND")) -> Åland Islands | J24: =IF($D24="","",IFERROR(IF(INDEX(Hierarchy!$G$2:$G$1295,MATCH($D24,Hierarchy!$A$2:$A$1295,0))="","",INDEX(Hierarchy!$G$2:$G$1295,MATCH($D24,Hierarchy!$A$2:$A$1295,0))),"NODE NOT FOUND")) -> ALA | K24: =IF($D24="","",IFERROR(IF(INDEX(Hierarchy!$H$2:$H$1295,MATCH($D24,Hierarchy!$A$2:$A$1295,0))="","",INDEX(Hierarchy!$H$2:$H$1295,MATCH($D24,Hierarchy!$A$2:$A$1295,0))),"NODE NOT FOUND")) | L24: =IF($D24="","",IFERROR(IF(INDEX(Hierarchy!$I$2:$I$1295,MATCH($D24,Hierarchy!$A$2:$A$1295,0))="","",INDEX(Hierarchy!$I$2:$I$1295,MATCH($D24,Hierarchy!$A$2:$A$1295,0))),"NODE NOT FOUND")) | M24: =IF(B24="Pre-seeded","Pre-seeded",IF(B24="Review 2026-09-16","Added from review",IF(C24="","New",IF(C24=D24,"","Changed")))) -> Pre-seeded | N24: =TRIM(SUBSTITUTE(SUBSTITUTE(SUBSTITUTE(" "&TRIM(SUBSTITUTE(SUBSTITUTE(SUBSTITUTE(SUBSTITUTE(SUBSTITUTE(SUBSTITUTE(SUBSTITUTE(SUBSTITUTE(SUBSTITUTE(SUBSTITUTE(SUBSTITUTE(SUBSTITUTE(SUBSTITUTE(SUBSTITUTE(SUBSTITUTE(UPPER(TRIM(A24)),"[MEMBER]",""),"{MEMBER}",""),"[MEMBER}",""),"MEMBER]",""),"(A)",""),"""",""),"“",""),"”",""),".",""),":",""),",",""),"–"," "),"-"," "),"/"," "),"&"," AND "))&" "," THE "," ")," TOTAL "," ")," OPERATIONS "," ")) -> ALAND ISLANDS | O24: =IF(COUNTIFS($N$2:$N$2000,N24,$D$2:$D$2000,"<>"&D24)>0,"CONFLICT","")
A25: Alaska | B25: Mapping | C25: Alaska | D25: Alaska | E25: Exact | F25: =IF($D25="","",IFERROR(IF(INDEX(Hierarchy!$B$2:$B$1295,MATCH($D25,Hierarchy!$A$2:$A$1295,0))="","",INDEX(Hierarchy!$B$2:$B$1295,MATCH($D25,Hierarchy!$A$2:$A$1295,0))),"NODE NOT FOUND")) -> State/Province | G25: =IF($D25="","",IFERROR(IF(INDEX(Hierarchy!$D$2:$D$1295,MATCH($D25,Hierarchy!$A$2:$A$1295,0))="","",INDEX(Hierarchy!$D$2:$D$1295,MATCH($D25,Hierarchy!$A$2:$A$1295,0))),"NODE NOT FOUND")) -> AMER | H25: =IF($D25="","",IFERROR(IF(INDEX(Hierarchy!$E$2:$E$1295,MATCH($D25,Hierarchy!$A$2:$A$1295,0))="","",INDEX(Hierarchy!$E$2:$E$1295,MATCH($D25,Hierarchy!$A$2:$A$1295,0))),"NODE NOT FOUND")) -> North America (NORAM) | I25: =IF($D25="","",IFERROR(IF(INDEX(Hierarchy!$F$2:$F$1295,MATCH($D25,Hierarchy!$A$2:$A$1295,0))="","",INDEX(Hierarchy!$F$2:$F$1295,MATCH($D25,Hierarchy!$A$2:$A$1295,0))),"NODE NOT FOUND")) -> United States | J25: =IF($D25="","",IFERROR(IF(INDEX(Hierarchy!$G$2:$G$1295,MATCH($D25,Hierarchy!$A$2:$A$1295,0))="","",INDEX(Hierarchy!$G$2:$G$1295,MATCH($D25,Hierarchy!$A$2:$A$1295,0))),"NODE NOT FOUND")) -> USA | K25: =IF($D25="","",IFERROR(IF(INDEX(Hierarchy!$H$2:$H$1295,MATCH($D25,Hierarchy!$A$2:$A$1295,0))="","",INDEX(Hierarchy!$H$2:$H$1295,MATCH($D25,Hierarchy!$A$2:$A$1295,0))),"NODE NOT FOUND")) -> Alaska | L25: =IF($D25="","",IFERROR(IF(INDEX(Hierarchy!$I$2:$I$1295,MATCH($D25,Hierarchy!$A$2:$A$1295,0))="","",INDEX(Hierarchy!$I$2:$I$1295,MATCH($D25,Hierarchy!$A$2:$A$1295,0))),"NODE NOT FOUND")) | M25: =IF(B25="Pre-seeded","Pre-seeded",IF(B25="Review 2026-09-16","Added from review",IF(C25="","New",IF(C25=D25,"","Changed")))) | N25: =TRIM(SUBSTITUTE(SUBSTITUTE(SUBSTITUTE(" "&TRIM(SUBSTITUTE(SUBSTITUTE(SUBSTITUTE(SUBSTITUTE(SUBSTITUTE(SUBSTITUTE(SUBSTITUTE(SUBSTITUTE(SUBSTITUTE(SUBSTITUTE(SUBSTITUTE(SUBSTITUTE(SUBSTITUTE(SUBSTITUTE(SUBSTITUTE(UPPER(TRIM(A25)),"[MEMBER]",""),"{MEMBER}",""),"[MEMBER}",""),"MEMBER]",""),"(A)",""),"""",""),"“",""),"”",""),".",""),":",""),",",""),"–"," "),"-"," "),"/"," "),"&"," AND "))&" "," THE "," ")," TOTAL "," ")," OPERATIONS "," ")) -> ALASKA | O25: =IF(COUNTIFS($N$2:$N$2000,N25,$D$2:$D$2000,"<>"&D25)>0,"CONFLICT","")
A26: Alaska and Hawaii | B26: final | C26: Alaska | D26: United States | E26: Partial | F26: =IF($D26="","",IFERROR(IF(INDEX(Hierarchy!$B$2:$B$1295,MATCH($D26,Hierarchy!$A$2:$A$1295,0))="","",INDEX(Hierarchy!$B$2:$B$1295,MATCH($D26,Hierarchy!$A$2:$A$1295,0))),"NODE NOT FOUND")) -> Country | G26: =IF($D26="","",IFERROR(IF(INDEX(Hierarchy!$D$2:$D$1295,MATCH($D26,Hierarchy!$A$2:$A$1295,0))="","",INDEX(Hierarchy!$D$2:$D$1295,MATCH($D26,Hierarchy!$A$2:$A$1295,0))),"NODE NOT FOUND")) -> AMER | H26: =IF($D26="","",IFERROR(IF(INDEX(Hierarchy!$E$2:$E$1295,MATCH($D26,Hierarchy!$A$2:$A$1295,0))="","",INDEX(Hierarchy!$E$2:$E$1295,MATCH($D26,Hierarchy!$A$2:$A$1295,0))),"NODE NOT FOUND")) -> North America (NORAM) | I26: =IF($D26="","",IFERROR(IF(INDEX(Hierarchy!$F$2:$F$1295,MATCH($D26,Hierarchy!$A$2:$A$1295,0))="","",INDEX(Hierarchy!$F$2:$F$1295,MATCH($D26,Hierarchy!$A$2:$A$1295,0))),"NODE NOT FOUND")) -> United States | J26: =IF($D26="","",IFERROR(IF(INDEX(Hierarchy!$G$2:$G$1295,MATCH($D26,Hierarchy!$A$2:$A$1295,0))="","",INDEX(Hierarchy!$G$2:$G$1295,MATCH($D26,Hierarchy!$A$2:$A$1295,0))),"NODE NOT FOUND")) -> USA | K26: =IF($D26="","",IFERROR(IF(INDEX(Hierarchy!$H$2:$H$1295,MATCH($D26,Hierarchy!$A$2:$A$1295,0))="","",INDEX(Hierarchy!$H$2:$H$1295,MATCH($D26,Hierarchy!$A$2:$A$1295,0))),"NODE NOT FOUND")) | L26: =IF($D26="","",IFERROR(IF(INDEX(Hierarchy!$I$2:$I$1295,MATCH($D26,Hierarchy!$A$2:$A$1295,0))="","",INDEX(Hierarchy!$I$2:$I$1295,MATCH($D26,Hierarchy!$A$2:$A$1295,0))),"NODE NOT FOUND")) | M26: =IF(B26="Pre-seeded","Pre-seeded",IF(B26="Review 2026-09-16","Added from review",IF(C26="","New",IF(C26=D26,"","Changed")))) -> Changed | N26: =TRIM(SUBSTITUTE(SUBSTITUTE(SUBSTITUTE(" "&TRIM(SUBSTITUTE(SUBSTITUTE(SUBSTITUTE(SUBSTITUTE(SUBSTITUTE(SUBSTITUTE(SUBSTITUTE(SUBSTITUTE(SUBSTITUTE(SUBSTITUTE(SUBSTITUTE(SUBSTITUTE(SUBSTITUTE(SUBSTITUTE(SUBSTITUTE(UPPER(TRIM(A26)),"[MEMBER]",""),"{MEMBER}",""),"[MEMBER}",""),"MEMBER]",""),"(A)",""),"""",""),"“",""),"”",""),".",""),":",""),",",""),"–"," "),"-"," "),"/"," "),"&"," AND "))&" "," THE "," ")," TOTAL "," ")," OPERATIONS "," ")) -> ALASKA AND HAWAII | O26: =IF(COUNTIFS($N$2:$N$2000,N26,$D$2:$D$2000,"<>"&D26)>0,"CONFLICT","") | P26: Two states
A27: Albania | B27: Pre-seeded | D27: Albania | E27: Exact | F27: =IF($D27="","",IFERROR(IF(INDEX(Hierarchy!$B$2:$B$1295,MATCH($D27,Hierarchy!$A$2:$A$1295,0))="","",INDEX(Hierarchy!$B$2:$B$1295,MATCH($D27,Hierarchy!$A$2:$A$1295,0))),"NODE NOT FOUND")) -> Country | G27: =IF($D27="","",IFERROR(IF(INDEX(Hierarchy!$D$2:$D$1295,MATCH($D27,Hierarchy!$A$2:$A$1295,0))="","",INDEX(Hierarchy!$D$2:$D$1295,MATCH($D27,Hierarchy!$A$2:$A$1295,0))),"NODE NOT FOUND")) -> EMEA | H27: =IF($D27="","",IFERROR(IF(INDEX(Hierarchy!$E$2:$E$1295,MATCH($D27,Hierarchy!$A$2:$A$1295,0))="","",INDEX(Hierarchy!$E$2:$E$1295,MATCH($D27,Hierarchy!$A$2:$A$1295,0))),"NODE NOT FOUND")) -> Europe | I27: =IF($D27="","",IFERROR(IF(INDEX(Hierarchy!$F$2:$F$1295,MATCH($D27,Hierarchy!$A$2:$A$1295,0))="","",INDEX(Hierarchy!$F$2:$F$1295,MATCH($D27,Hierarchy!$A$2:$A$1295,0))),"NODE NOT FOUND")) -> Albania | J27: =IF($D27="","",IFERROR(IF(INDEX(Hierarchy!$G$2:$G$1295,MATCH($D27,Hierarchy!$A$2:$A$1295,0))="","",INDEX(Hierarchy!$G$2:$G$1295,MATCH($D27,Hierarchy!$A$2:$A$1295,0))),"NODE NOT FOUND")) -> ALB | K27: =IF($D27="","",IFERROR(IF(INDEX(Hierarchy!$H$2:$H$1295,MATCH($D27,Hierarchy!$A$2:$A$1295,0))="","",INDEX(Hierarchy!$H$2:$H$1295,MATCH($D27,Hierarchy!$A$2:$A$1295,0))),"NODE NOT FOUND")) | L27: =IF($D27="","",IFERROR(IF(INDEX(Hierarchy!$I$2:$I$1295,MATCH($D27,Hierarchy!$A$2:$A$1295,0))="","",INDEX(Hierarchy!$I$2:$I$1295,MATCH($D27,Hierarchy!$A$2:$A$1295,0))),"NODE NOT FOUND")) | M27: =IF(B27="Pre-seeded","Pre-seeded",IF(B27="Review 2026-09-16","Added from review",IF(C27="","New",IF(C27=D27,"","Changed")))) -> Pre-seeded | N27: =TRIM(SUBSTITUTE(SUBSTITUTE(SUBSTITUTE(" "&TRIM(SUBSTITUTE(SUBSTITUTE(SUBSTITUTE(SUBSTITUTE(SUBSTITUTE(SUBSTITUTE(SUBSTITUTE(SUBSTITUTE(SUBSTITUTE(SUBSTITUTE(SUBSTITUTE(SUBSTITUTE(SUBSTITUTE(SUBSTITUTE(SUBSTITUTE(UPPER(TRIM(A27)),"[MEMBER]",""),"{MEMBER}",""),"[MEMBER}",""),"MEMBER]",""),"(A)",""),"""",""),"“",""),"”",""),".",""),":",""),",",""),"–"," "),"-"," "),"/"," "),"&"," AND "))&" "," THE "," ")," TOTAL "," ")," OPERATIONS "," ")) -> ALBANIA | O27: =IF(COUNTIFS($N$2:$N$2000,N27,$D$2:$D$2000,"<>"&D27)>0,"CONFLICT","")
A28: Alberta | B28: Pre-seeded | D28: Alberta | E28: Exact | F28: =IF($D28="","",IFERROR(IF(INDEX(Hierarchy!$B$2:$B$1295,MATCH($D28,Hierarchy!$A$2:$A$1295,0))="","",INDEX(Hierarchy!$B$2:$B$1295,MATCH($D28,Hierarchy!$A$2:$A$1295,0))),"NODE NOT FOUND")) -> State/Province | G28: =IF($D28="","",IFERROR(IF(INDEX(Hierarchy!$D$2:$D$1295,MATCH($D28,Hierarchy!$A$2:$A$1295,0))="","",INDEX(Hierarchy!$D$2:$D$1295,MATCH($D28,Hierarchy!$A$2:$A$1295,0))),"NODE NOT FOUND")) -> AMER | H28: =IF($D28="","",IFERROR(IF(INDEX(Hierarchy!$E$2:$E$1295,MATCH($D28,Hierarchy!$A$2:$A$1295,0))="","",INDEX(Hierarchy!$E$2:$E$1295,MATCH($D28,Hierarchy!$A$2:$A$1295,0))),"NODE NOT FOUND")) -> North America (NORAM) | I28: =IF($D28="","",IFERROR(IF(INDEX(Hierarchy!$F$2:$F$1295,MATCH($D28,Hierarchy!$A$2:$A$1295,0))="","",INDEX(Hierarchy!$F$2:$F$1295,MATCH($D28,Hierarchy!$A$2:$A$1295,0))),"NODE NOT FOUND")) -> Canada | J28: =IF($D28="","",IFERROR(IF(INDEX(Hierarchy!$G$2:$G$1295,MATCH($D28,Hierarchy!$A$2:$A$1295,0))="","",INDEX(Hierarchy!$G$2:$G$1295,MATCH($D28,Hierarchy!$A$2:$A$1295,0))),"NODE NOT FOUND")) -> CAN | K28: =IF($D28="","",IFERROR(IF(INDEX(Hierarchy!$H$2:$H$1295,MATCH($D28,Hierarchy!$A$2:$A$1295,0))="","",INDEX(Hierarchy!$H$2:$H$1295,MATCH($D28,Hierarchy!$A$2:$A$1295,0))),"NODE NOT FOUND")) -> Alberta | L28: =IF($D28="","",IFERROR(IF(INDEX(Hierarchy!$I$2:$I$1295,MATCH($D28,Hierarchy!$A$2:$A$1295,0))="","",INDEX(Hierarchy!$I$2:$I$1295,MATCH($D28,Hierarchy!$A$2:$A$1295,0))),"NODE NOT FOUND")) | M28: =IF(B28="Pre-seeded","Pre-seeded",IF(B28="Review 2026-09-16","Added from review",IF(C28="","New",IF(C28=D28,"","Changed")))) -> Pre-seeded | N28: =TRIM(SUBSTITUTE(SUBSTITUTE(SUBSTITUTE(" "&TRIM(SUBSTITUTE(SUBSTITUTE(SUBSTITUTE(SUBSTITUTE(SUBSTITUTE(SUBSTITUTE(SUBSTITUTE(SUBSTITUTE(SUBSTITUTE(SUBSTITUTE(SUBSTITUTE(SUBSTITUTE(SUBSTITUTE(SUBSTITUTE(SUBSTITUTE(UPPER(TRIM(A28)),"[MEMBER]",""),"{MEMBER}",""),"[MEMBER}",""),"MEMBER]",""),"(A)",""),"""",""),"“",""),"”",""),".",""),":",""),",",""),"–"," "),"-"," "),"/"," "),"&"," AND "))&" "," THE "," ")," TOTAL "," ")," OPERATIONS "," ")) -> ALBERTA | O28: =IF(COUNTIFS($N$2:$N$2000,N28,$D$2:$D$2000,"<>"&D28)>0,"CONFLICT","")
A29: Algeria | B29: Pre-seeded | D29: Algeria | E29: Exact | F29: =IF($D29="","",IFERROR(IF(INDEX(Hierarchy!$B$2:$B$1295,MATCH($D29,Hierarchy!$A$2:$A$1295,0))="","",INDEX(Hierarchy!$B$2:$B$1295,MATCH($D29,Hierarchy!$A$2:$A$1295,0))),"NODE NOT FOUND")) -> Country | G29: =IF($D29="","",IFERROR(IF(INDEX(Hierarchy!$D$2:$D$1295,MATCH($D29,Hierarchy!$A$2:$A$1295,0))="","",INDEX(Hierarchy!$D$2:$D$1295,MATCH($D29,Hierarchy!$A$2:$A$1295,0))),"NODE NOT FOUND")) -> EMEA | H29: =IF($D29="","",IFERROR(IF(INDEX(Hierarchy!$E$2:$E$1295,MATCH($D29,Hierarchy!$A$2:$A$1295,0))="","",INDEX(Hierarchy!$E$2:$E$1295,MATCH($D29,Hierarchy!$A$2:$A$1295,0))),"NODE NOT FOUND")) -> Africa | I29: =IF($D29="","",IFERROR(IF(INDEX(Hierarchy!$F$2:$F$1295,MATCH($D29,Hierarchy!$A$2:$A$1295,0))="","",INDEX(Hierarchy!$F$2:$F$1295,MATCH($D29,Hierarchy!$A$2:$A$1295,0))),"NODE NOT FOUND")) -> Algeria | J29: =IF($D29="","",IFERROR(IF(INDEX(Hierarchy!$G$2:$G$1295,MATCH($D29,Hierarchy!$A$2:$A$1295,0))="","",INDEX(Hierarchy!$G$2:$G$1295,MATCH($D29,Hierarchy!$A$2:$A$1295,0))),"NODE NOT FOUND")) -> DZA | K29: =IF($D29="","",IFERROR(IF(INDEX(Hierarchy!$H$2:$H$1295,MATCH($D29,Hierarchy!$A$2:$A$1295,0))="","",INDEX(Hierarchy!$H$2:$H$1295,MATCH($D29,Hierarchy!$A$2:$A$1295,0))),"NODE NOT FOUND")) | L29: =IF($D29="","",IFERROR(IF(INDEX(Hierarchy!$I$2:$I$1295,MATCH($D29,Hierarchy!$A$2:$A$1295,0))="","",INDEX(Hierarchy!$I$2:$I$1295,MATCH($D29,Hierarchy!$A$2:$A$1295,0))),"NODE NOT FOUND")) | M29: =IF(B29="Pre-seeded","Pre-seeded",IF(B29="Review 2026-09-16","Added from review",IF(C29="","New",IF(C29=D29,"","Changed")))) -> Pre-seeded | N29: =TRIM(SUBSTITUTE(SUBSTITUTE(SUBSTITUTE(" "&TRIM(SUBSTITUTE(SUBSTITUTE(SUBSTITUTE(SUBSTITUTE(SUBSTITUTE(SUBSTITUTE(SUBSTITUTE(SUBSTITUTE(SUBSTITUTE(SUBSTITUTE(SUBSTITUTE(SUBSTITUTE(SUBSTITUTE(SUBSTITUTE(SUBSTITUTE(UPPER(TRIM(A29)),"[MEMBER]",""),"{MEMBER}",""),"[MEMBER}",""),"MEMBER]",""),"(A)",""),"""",""),"“",""),"”",""),".",""),":",""),",",""),"–"," "),"-"," "),"/"," "),"&"," AND "))&" "," THE "," ")," TOTAL "," ")," OPERATIONS "," ")) -> ALGERIA | O29: =IF(COUNTIFS($N$2:$N$2000,N29,$D$2:$D$2000,"<>"&D29)>0,"CONFLICT","")
A30: All foreign countries | B30: final | C30: Foreign | D30: International | E30: Exact | F30: =IF($D30="","",IFERROR(IF(INDEX(Hierarchy!$B$2:$B$1295,MATCH($D30,Hierarchy!$A$2:$A$1295,0))="","",INDEX(Hierarchy!$B$2:$B$1295,MATCH($D30,Hierarchy!$A$2:$A$1295,0))),"NODE NOT FOUND")) -> Bucket | G30: =IF($D30="","",IFERROR(IF(INDEX(Hierarchy!$D$2:$D$1295,MATCH($D30,Hierarchy!$A$2:$A$1295,0))="","",INDEX(Hierarchy!$D$2:$D$1295,MATCH($D30,Hierarchy!$A$2:$A$1295,0))),"NODE NOT FOUND")) -> Non-regional | H30: =IF($D30="","",IFERROR(IF(INDEX(Hierarchy!$E$2:$E$1295,MATCH($D30,Hierarchy!$A$2:$A$1295,0))="","",INDEX(Hierarchy!$E$2:$E$1295,MATCH($D30,Hierarchy!$A$2:$A$1295,0))),"NODE NOT FOUND")) | I30: =IF($D30="","",IFERROR(IF(INDEX(Hierarchy!$F$2:$F$1295,MATCH($D30,Hierarchy!$A$2:$A$1295,0))="","",INDEX(Hierarchy!$F$2:$F$1295,MATCH($D30,Hierarchy!$A$2:$A$1295,0))),"NODE NOT FOUND")) | J30: =IF($D30="","",IFERROR(IF(INDEX(Hierarchy!$G$2:$G$1295,MATCH($D30,Hierarchy!$A$2:$A$1295,0))="","",INDEX(Hierarchy!$G$2:$G$1295,MATCH($D30,Hierarchy!$A$2:$A$1295,0))),"NODE NOT FOUND")) | K30: =IF($D30="","",IFERROR(IF(INDEX(Hierarchy!$H$2:$H$1295,MATCH($D30,Hierarchy!$A$2:$A$1295,0))="","",INDEX(Hierarchy!$H$2:$H$1295,MATCH($D30,Hierarchy!$A$2:$A$1295,0))),"NODE NOT FOUND")) | L30: =IF($D30="","",IFERROR(IF(INDEX(Hierarchy!$I$2:$I$1295,MATCH($D30,Hierarchy!$A$2:$A$1295,0))="","",INDEX(Hierarchy!$I$2:$I$1295,MATCH($D30,Hierarchy!$A$2:$A$1295,0))),"NODE NOT FOUND")) | M30: =IF(B30="Pre-seeded","Pre-seeded",IF(B30="Review 2026-09-16","Added from review",IF(C30="","New",IF(C30=D30,"","Changed")))) -> Changed | N30: =TRIM(SUBSTITUTE(SUBSTITUTE(SUBSTITUTE(" "&TRIM(SUBSTITUTE(SUBSTITUTE(SUBSTITUTE(SUBSTITUTE(SUBSTITUTE(SUBSTITUTE(SUBSTITUTE(SUBSTITUTE(SUBSTITUTE(SUBSTITUTE(SUBSTITUTE(SUBSTITUTE(SUBSTITUTE(SUBSTITUTE(SUBSTITUTE(UPPER(TRIM(A30)),"[MEMBER]",""),"{MEMBER}",""),"[MEMBER}",""),"MEMBER]",""),"(A)",""),"""",""),"“",""),"”",""),".",""),":",""),",",""),"–"," "),"-"," "),"/"," "),"&"," AND "))&" "," THE "," ")," TOTAL "," ")," OPERATIONS "," ")) -> ALL FOREIGN COUNTRIES | O30: =IF(COUNTIFS($N$2:$N$2000,N30,$D$2:$D$2000,"<>"&D30)>0,"CONFLICT","") | P30: Foreign → International
A31: All international | B31: final | C31: International | D31: International | E31: Exact | F31: =IF($D31="","",IFERROR(IF(INDEX(Hierarchy!$B$2:$B$1295,MATCH($D31,Hierarchy!$A$2:$A$1295,0))="","",INDEX(Hierarchy!$B$2:$B$1295,MATCH($D31,Hierarchy!$A$2:$A$1295,0))),"NODE NOT FOUND")) -> Bucket | G31: =IF($D31="","",IFERROR(IF(INDEX(Hierarchy!$D$2:$D$1295,MATCH($D31,Hierarchy!$A$2:$A$1295,0))="","",INDEX(Hierarchy!$D$2:$D$1295,MATCH($D31,Hierarchy!$A$2:$A$1295,0))),"NODE NOT FOUND")) -> Non-regional | H31: =IF($D31="","",IFERROR(IF(INDEX(Hierarchy!$E$2:$E$1295,MATCH($D31,Hierarchy!$A$2:$A$1295,0))="","",INDEX(Hierarchy!$E$2:$E$1295,MATCH($D31,Hierarchy!$A$2:$A$1295,0))),"NODE NOT FOUND")) | I31: =IF($D31="","",IFERROR(IF(INDEX(Hierarchy!$F$2:$F$1295,MATCH($D31,Hierarchy!$A$2:$A$1295,0))="","",INDEX(Hierarchy!$F$2:$F$1295,MATCH($D31,Hierarchy!$A$2:$A$1295,0))),"NODE NOT FOUND")) | J31: =IF($D31="","",IFERROR(IF(INDEX(Hierarchy!$G$2:$G$1295,MATCH($D31,Hierarchy!$A$2:$A$1295,0))="","",INDEX(Hierarchy!$G$2:$G$1295,MATCH($D31,Hierarchy!$A$2:$A$1295,0))),"NODE NOT FOUND")) | K31: =IF($D31="","",IFERROR(IF(INDEX(Hierarchy!$H$2:$H$1295,MATCH($D31,Hierarchy!$A$2:$A$1295,0))="","",INDEX(Hierarchy!$H$2:$H$1295,MATCH($D31,Hierarchy!$A$2:$A$1295,0))),"NODE NOT FOUND")) | L31: =IF($D31="","",IFERROR(IF(INDEX(Hierarchy!$I$2:$I$1295,MATCH($D31,Hierarchy!$A$2:$A$1295,0))="","",INDEX(Hierarchy!$I$2:$I$1295,MATCH($D31,Hierarchy!$A$2:$A$1295,0))),"NODE NOT FOUND")) | M31: =IF(B31="Pre-seeded","Pre-seeded",IF(B31="Review 2026-09-16","Added from review",IF(C31="","New",IF(C31=D31,"","Changed")))) | N31: =TRIM(SUBSTITUTE(SUBSTITUTE(SUBSTITUTE(" "&TRIM(SUBSTITUTE(SUBSTITUTE(SUBSTITUTE(SUBSTITUTE(SUBSTITUTE(SUBSTITUTE(SUBSTITUTE(SUBSTITUTE(SUBSTITUTE(SUBSTITUTE(SUBSTITUTE(SUBSTITUTE(SUBSTITUTE(SUBSTITUTE(SUBSTITUTE(UPPER(TRIM(A31)),"[MEMBER]",""),"{MEMBER}",""),"[MEMBER}",""),"MEMBER]",""),"(A)",""),"""",""),"“",""),"”",""),".",""),":",""),",",""),"–"," "),"-"," "),"/"," "),"&"," AND "))&" "," THE "," ")," TOTAL "," ")," OPERATIONS "," ")) -> ALL INTERNATIONAL | O31: =IF(COUNTIFS($N$2:$N$2000,N31,$D$2:$D$2000,"<>"&D31)>0,"CONFLICT","")
A32: All other | B32: final | C32: Other | D32: Other | E32: Residual | F32: =IF($D32="","",IFERROR(IF(INDEX(Hierarchy!$B$2:$B$1295,MATCH($D32,Hierarchy!$A$2:$A$1295,0))="","",INDEX(Hierarchy!$B$2:$B$1295,MATCH($D32,Hierarchy!$A$2:$A$1295,0))),"NODE NOT FOUND")) -> Bucket | G32: =IF($D32="","",IFERROR(IF(INDEX(Hierarchy!$D$2:$D$1295,MATCH($D32,Hierarchy!$A$2:$A$1295,0))="","",INDEX(Hierarchy!$D$2:$D$1295,MATCH($D32,Hierarchy!$A$2:$A$1295,0))),"NODE NOT FOUND")) -> Non-regional | H32: =IF($D32="","",IFERROR(IF(INDEX(Hierarchy!$E$2:$E$1295,MATCH($D32,Hierarchy!$A$2:$A$1295,0))="","",INDEX(Hierarchy!$E$2:$E$1295,MATCH($D32,Hierarchy!$A$2:$A$1295,0))),"NODE NOT FOUND")) | I32: =IF($D32="","",IFERROR(IF(INDEX(Hierarchy!$F$2:$F$1295,MATCH($D32,Hierarchy!$A$2:$A$1295,0))="","",INDEX(Hierarchy!$F$2:$F$1295,MATCH($D32,Hierarchy!$A$2:$A$1295,0))),"NODE NOT FOUND")) | J32: =IF($D32="","",IFERROR(IF(INDEX(Hierarchy!$G$2:$G$1295,MATCH($D32,Hierarchy!$A$2:$A$1295,0))="","",INDEX(Hierarchy!$G$2:$G$1295,MATCH($D32,Hierarchy!$A$2:$A$1295,0))),"NODE NOT FOUND")) | K32: =IF($D32="","",IFERROR(IF(INDEX(Hierarchy!$H$2:$H$1295,MATCH($D32,Hierarchy!$A$2:$A$1295,0))="","",INDEX(Hierarchy!$H$2:$H$1295,MATCH($D32,Hierarchy!$A$2:$A$1295,0))),"NODE NOT FOUND")) | L32: =IF($D32="","",IFERROR(IF(INDEX(Hierarchy!$I$2:$I$1295,MATCH($D32,Hierarchy!$A$2:$A$1295,0))="","",INDEX(Hierarchy!$I$2:$I$1295,MATCH($D32,Hierarchy!$A$2:$A$1295,0))),"NODE NOT FOUND")) | M32: =IF(B32="Pre-seeded","Pre-seeded",IF(B32="Review 2026-09-16","Added from review",IF(C32="","New",IF(C32=D32,"","Changed")))) | N32: =TRIM(SUBSTITUTE(SUBSTITUTE(SUBSTITUTE(" "&TRIM(SUBSTITUTE(SUBSTITUTE(SUBSTITUTE(SUBSTITUTE(SUBSTITUTE(SUBSTITUTE(SUBSTITUTE(SUBSTITUTE(SUBSTITUTE(SUBSTITUTE(SUBSTITUTE(SUBSTITUTE(SUBSTITUTE(SUBSTITUTE(SUBSTITUTE(UPPER(TRIM(A32)),"[MEMBER]",""),"{MEMBER}",""),"[MEMBER}",""),"MEMBER]",""),"(A)",""),"""",""),"“",""),"”",""),".",""),":",""),",",""),"–"," "),"-"," "),"/"," "),"&"," AND "))&" "," THE "," ")," TOTAL "," ")," OPERATIONS "," ")) -> ALL OTHER | O32: =IF(COUNTIFS($N$2:$N$2000,N32,$D$2:$D$2000,"<>"&D32)>0,"CONFLICT","")
A33: All other countries | B33: final | C33: Other | D33: Other | E33: Residual | F33: =IF($D33="","",IFERROR(IF(INDEX(Hierarchy!$B$2:$B$1295,MATCH($D33,Hierarchy!$A$2:$A$1295,0))="","",INDEX(Hierarchy!$B$2:$B$1295,MATCH($D33,Hierarchy!$A$2:$A$1295,0))),"NODE NOT FOUND")) -> Bucket | G33: =IF($D33="","",IFERROR(IF(INDEX(Hierarchy!$D$2:$D$1295,MATCH($D33,Hierarchy!$A$2:$A$1295,0))="","",INDEX(Hierarchy!$D$2:$D$1295,MATCH($D33,Hierarchy!$A$2:$A$1295,0))),"NODE NOT FOUND")) -> Non-regional | H33: =IF($D33="","",IFERROR(IF(INDEX(Hierarchy!$E$2:$E$1295,MATCH($D33,Hierarchy!$A$2:$A$1295,0))="","",INDEX(Hierarchy!$E$2:$E$1295,MATCH($D33,Hierarchy!$A$2:$A$1295,0))),"NODE NOT FOUND")) | I33: =IF($D33="","",IFERROR(IF(INDEX(Hierarchy!$F$2:$F$1295,MATCH($D33,Hierarchy!$A$2:$A$1295,0))="","",INDEX(Hierarchy!$F$2:$F$1295,MATCH($D33,Hierarchy!$A$2:$A$1295,0))),"NODE NOT FOUND")) | J33: =IF($D33="","",IFERROR(IF(INDEX(Hierarchy!$G$2:$G$1295,MATCH($D33,Hierarchy!$A$2:$A$1295,0))="","",INDEX(Hierarchy!$G$2:$G$1295,MATCH($D33,Hierarchy!$A$2:$A$1295,0))),"NODE NOT FOUND")) | K33: =IF($D33="","",IFERROR(IF(INDEX(Hierarchy!$H$2:$H$1295,MATCH($D33,Hierarchy!$A$2:$A$1295,0))="","",INDEX(Hierarchy!$H$2:$H$1295,MATCH($D33,Hierarchy!$A$2:$A$1295,0))),"NODE NOT FOUND")) | L33: =IF($D33="","",IFERROR(IF(INDEX(Hierarchy!$I$2:$I$1295,MATCH($D33,Hierarchy!$A$2:$A$1295,0))="","",INDEX(Hierarchy!$I$2:$I$1295,MATCH($D33,Hierarchy!$A$2:$A$1295,0))),"NODE NOT FOUND")) | M33: =IF(B33="Pre-seeded","Pre-seeded",IF(B33="Review 2026-09-16","Added from review",IF(C33="","New",IF(C33=D33,"","Changed")))) | N33: =TRIM(SUBSTITUTE(SUBSTITUTE(SUBSTITUTE(" "&TRIM(SUBSTITUTE(SUBSTITUTE(SUBSTITUTE(SUBSTITUTE(SUBSTITUTE(SUBSTITUTE(SUBSTITUTE(SUBSTITUTE(SUBSTITUTE(SUBSTITUTE(SUBSTITUTE(SUBSTITUTE(SUBSTITUTE(SUBSTITUTE(SUBSTITUTE(UPPER(TRIM(A33)),"[MEMBER]",""),"{MEMBER}",""),"[MEMBER}",""),"MEMBER]",""),"(A)",""),"""",""),"“",""),"”",""),".",""),":",""),",",""),"–"," "),"-"," "),"/"," "),"&"," AND "))&" "," THE "," ")," TOTAL "," ")," OPERATIONS "," ")) -> ALL OTHER COUNTRIES | O33: =IF(COUNTIFS($N$2:$N$2000,N33,$D$2:$D$2000,"<>"&D33)>0,"CONFLICT","")
A34: All Other Foreign Countries | B34: final | C34: Foreign | D34: International | E34: Residual | F34: =IF($D34="","",IFERROR(IF(INDEX(Hierarchy!$B$2:$B$1295,MATCH($D34,Hierarchy!$A$2:$A$1295,0))="","",INDEX(Hierarchy!$B$2:$B$1295,MATCH($D34,Hierarchy!$A$2:$A$1295,0))),"NODE NOT FOUND")) -> Bucket | G34: =IF($D34="","",IFERROR(IF(INDEX(Hierarchy!$D$2:$D$1295,MATCH($D34,Hierarchy!$A$2:$A$1295,0))="","",INDEX(Hierarchy!$D$2:$D$1295,MATCH($D34,Hierarchy!$A$2:$A$1295,0))),"NODE NOT FOUND")) -> Non-regional | H34: =IF($D34="","",IFERROR(IF(INDEX(Hierarchy!$E$2:$E$1295,MATCH($D34,Hierarchy!$A$2:$A$1295,0))="","",INDEX(Hierarchy!$E$2:$E$1295,MATCH($D34,Hierarchy!$A$2:$A$1295,0))),"NODE NOT FOUND")) | I34: =IF($D34="","",IFERROR(IF(INDEX(Hierarchy!$F$2:$F$1295,MATCH($D34,Hierarchy!$A$2:$A$1295,0))="","",INDEX(Hierarchy!$F$2:$F$1295,MATCH($D34,Hierarchy!$A$2:$A$1295,0))),"NODE NOT FOUND")) | J34: =IF($D34="","",IFERROR(IF(INDEX(Hierarchy!$G$2:$G$1295,MATCH($D34,Hierarchy!$A$2:$A$1295,0))="","",INDEX(Hierarchy!$G$2:$G$1295,MATCH($D34,Hierarchy!$A$2:$A$1295,0))),"NODE NOT FOUND")) | K34: =IF($D34="","",IFERROR(IF(INDEX(Hierarchy!$H$2:$H$1295,MATCH($D34,Hierarchy!$A$2:$A$1295,0))="","",INDEX(Hierarchy!$H$2:$H$1295,MATCH($D34,Hierarchy!$A$2:$A$1295,0))),"NODE NOT FOUND")) | L34: =IF($D34="","",IFERROR(IF(INDEX(Hierarchy!$I$2:$I$1295,MATCH($D34,Hierarchy!$A$2:$A$1295,0))="","",INDEX(Hierarchy!$I$2:$I$1295,MATCH($D34,Hierarchy!$A$2:$A$1295,0))),"NODE NOT FOUND")) | M34: =IF(B34="Pre-seeded","Pre-seeded",IF(B34="Review 2026-09-16","Added from review",IF(C34="","New",IF(C34=D34,"","Changed")))) -> Changed | N34: =TRIM(SUBSTITUTE(SUBSTITUTE(SUBSTITUTE(" "&TRIM(SUBSTITUTE(SUBSTITUTE(SUBSTITUTE(SUBSTITUTE(SUBSTITUTE(SUBSTITUTE(SUBSTITUTE(SUBSTITUTE(SUBSTITUTE(SUBSTITUTE(SUBSTITUTE(SUBSTITUTE(SUBSTITUTE(SUBSTITUTE(SUBSTITUTE(UPPER(TRIM(A34)),"[MEMBER]",""),"{MEMBER}",""),"[MEMBER}",""),"MEMBER]",""),"(A)",""),"""",""),"“",""),"”",""),".",""),":",""),",",""),"–"," "),"-"," "),"/"," "),"&"," AND "))&" "," THE "," ")," TOTAL "," ")," OPERATIONS "," ")) -> ALL OTHER FOREIGN COUNTRIES | O34: =IF(COUNTIFS($N$2:$N$2000,N34,$D$2:$D$2000,"<>"&D34)>0,"CONFLICT","") | P34: Foreign → International
A35: All other international | B35: final | C35: International | D35: International | E35: Residual | F35: =IF($D35="","",IFERROR(IF(INDEX(Hierarchy!$B$2:$B$1295,MATCH($D35,Hierarchy!$A$2:$A$1295,0))="","",INDEX(Hierarchy!$B$2:$B$1295,MATCH($D35,Hierarchy!$A$2:$A$1295,0))),"NODE NOT FOUND")) -> Bucket | G35: =IF($D35="","",IFERROR(IF(INDEX(Hierarchy!$D$2:$D$1295,MATCH($D35,Hierarchy!$A$2:$A$1295,0))="","",INDEX(Hierarchy!$D$2:$D$1295,MATCH($D35,Hierarchy!$A$2:$A$1295,0))),"NODE NOT FOUND")) -> Non-regional | H35: =IF($D35="","",IFERROR(IF(INDEX(Hierarchy!$E$2:$E$1295,MATCH($D35,Hierarchy!$A$2:$A$1295,0))="","",INDEX(Hierarchy!$E$2:$E$1295,MATCH($D35,Hierarchy!$A$2:$A$1295,0))),"NODE NOT FOUND")) | I35: =IF($D35="","",IFERROR(IF(INDEX(Hierarchy!$F$2:$F$1295,MATCH($D35,Hierarchy!$A$2:$A$1295,0))="","",INDEX(Hierarchy!$F$2:$F$1295,MATCH($D35,Hierarchy!$A$2:$A$1295,0))),"NODE NOT FOUND")) | J35: =IF($D35="","",IFERROR(IF(INDEX(Hierarchy!$G$2:$G$1295,MATCH($D35,Hierarchy!$A$2:$A$1295,0))="","",INDEX(Hierarchy!$G$2:$G$1295,MATCH($D35,Hierarchy!$A$2:$A$1295,0))),"NODE NOT FOUND")) | K35: =IF($D35="","",IFERROR(IF(INDEX(Hierarchy!$H$2:$H$1295,MATCH($D35,Hierarchy!$A$2:$A$1295,0))="","",INDEX(Hierarchy!$H$2:$H$1295,MATCH($D35,Hierarchy!$A$2:$A$1295,0))),"NODE NOT FOUND")) | L35: =IF($D35="","",IFERROR(IF(INDEX(Hierarchy!$I$2:$I$1295,MATCH($D35,Hierarchy!$A$2:$A$1295,0))="","",INDEX(Hierarchy!$I$2:$I$1295,MATCH($D35,Hierarchy!$A$2:$A$1295,0))),"NODE NOT FOUND")) | M35: =IF(B35="Pre-seeded","Pre-seeded",IF(B35="Review 2026-09-16","Added from review",IF(C35="","New",IF(C35=D35,"","Changed")))) | N35: =TRIM(SUBSTITUTE(SUBSTITUTE(SUBSTITUTE(" "&TRIM(SUBSTITUTE(SUBSTITUTE(SUBSTITUTE(SUBSTITUTE(SUBSTITUTE(SUBSTITUTE(SUBSTITUTE(SUBSTITUTE(SUBSTITUTE(SUBSTITUTE(SUBSTITUTE(SUBSTITUTE(SUBSTITUTE(SUBSTITUTE(SUBSTITUTE(UPPER(TRIM(A35)),"[MEMBER]",""),"{MEMBER}",""),"[MEMBER}",""),"MEMBER]",""),"(A)",""),"""",""),"“",""),"”",""),".",""),":",""),",",""),"–"," "),"-"," "),"/"," "),"&"," AND "))&" "," THE "," ")," TOTAL "," ")," OPERATIONS "," ")) -> ALL OTHER INTERNATIONAL | O35: =IF(COUNTIFS($N$2:$N$2000,N35,$D$2:$D$2000,"<>"&D35)>0,"CONFLICT","")
A36: All other regions | B36: final | C36: Other | D36: Other | E36: Residual | F36: =IF($D36="","",IFERROR(IF(INDEX(Hierarchy!$B$2:$B$1295,MATCH($D36,Hierarchy!$A$2:$A$1295,0))="","",INDEX(Hierarchy!$B$2:$B$1295,MATCH($D36,Hierarchy!$A$2:$A$1295,0))),"NODE NOT FOUND")) -> Bucket | G36: =IF($D36="","",IFERROR(IF(INDEX(Hierarchy!$D$2:$D$1295,MATCH($D36,Hierarchy!$A$2:$A$1295,0))="","",INDEX(Hierarchy!$D$2:$D$1295,MATCH($D36,Hierarchy!$A$2:$A$1295,0))),"NODE NOT FOUND")) -> Non-regional | H36: =IF($D36="","",IFERROR(IF(INDEX(Hierarchy!$E$2:$E$1295,MATCH($D36,Hierarchy!$A$2:$A$1295,0))="","",INDEX(Hierarchy!$E$2:$E$1295,MATCH($D36,Hierarchy!$A$2:$A$1295,0))),"NODE NOT FOUND")) | I36: =IF($D36="","",IFERROR(IF(INDEX(Hierarchy!$F$2:$F$1295,MATCH($D36,Hierarchy!$A$2:$A$1295,0))="","",INDEX(Hierarchy!$F$2:$F$1295,MATCH($D36,Hierarchy!$A$2:$A$1295,0))),"NODE NOT FOUND")) | J36: =IF($D36="","",IFERROR(IF(INDEX(Hierarchy!$G$2:$G$1295,MATCH($D36,Hierarchy!$A$2:$A$1295,0))="","",INDEX(Hierarchy!$G$2:$G$1295,MATCH($D36,Hierarchy!$A$2:$A$1295,0))),"NODE NOT FOUND")) | K36: =IF($D36="","",IFERROR(IF(INDEX(Hierarchy!$H$2:$H$1295,MATCH($D36,Hierarchy!$A$2:$A$1295,0))="","",INDEX(Hierarchy!$H$2:$H$1295,MATCH($D36,Hierarchy!$A$2:$A$1295,0))),"NODE NOT FOUND")) | L36: =IF($D36="","",IFERROR(IF(INDEX(Hierarchy!$I$2:$I$1295,MATCH($D36,Hierarchy!$A$2:$A$1295,0))="","",INDEX(Hierarchy!$I$2:$I$1295,MATCH($D36,Hierarchy!$A$2:$A$1295,0))),"NODE NOT FOUND")) | M36: =IF(B36="Pre-seeded","Pre-seeded",IF(B36="Review 2026-09-16","Added from review",IF(C36="","New",IF(C36=D36,"","Changed")))) | N36: =TRIM(SUBSTITUTE(SUBSTITUTE(SUBSTITUTE(" "&TRIM(SUBSTITUTE(SUBSTITUTE(SUBSTITUTE(SUBSTITUTE(SUBSTITUTE(SUBSTITUTE(SUBSTITUTE(SUBSTITUTE(SUBSTITUTE(SUBSTITUTE(SUBSTITUTE(SUBSTITUTE(SUBSTITUTE(SUBSTITUTE(SUBSTITUTE(UPPER(TRIM(A36)),"[MEMBER]",""),"{MEMBER}",""),"[MEMBER}",""),"MEMBER]",""),"(A)",""),"""",""),"“",""),"”",""),".",""),":",""),",",""),"–"," "),"-"," "),"/"," "),"&"," AND "))&" "," THE "," ")," TOTAL "," ")," OPERATIONS "," ")) -> ALL OTHER REGIONS | O36: =IF(COUNTIFS($N$2:$N$2000,N36,$D$2:$D$2000,"<>"&D36)>0,"CONFLICT","")
A37: All others international | B37: final | C37: International | D37: International | E37: Residual | F37: =IF($D37="","",IFERROR(IF(INDEX(Hierarchy!$B$2:$B$1295,MATCH($D37,Hierarchy!$A$2:$A$1295,0))="","",INDEX(Hierarchy!$B$2:$B$1295,MATCH($D37,Hierarchy!$A$2:$A$1295,0))),"NODE NOT FOUND")) -> Bucket | G37: =IF($D37="","",IFERROR(IF(INDEX(Hierarchy!$D$2:$D$1295,MATCH($D37,Hierarchy!$A$2:$A$1295,0))="","",INDEX(Hierarchy!$D$2:$D$1295,MATCH($D37,Hierarchy!$A$2:$A$1295,0))),"NODE NOT FOUND")) -> Non-regional | H37: =IF($D37="","",IFERROR(IF(INDEX(Hierarchy!$E$2:$E$1295,MATCH($D37,Hierarchy!$A$2:$A$1295,0))="","",INDEX(Hierarchy!$E$2:$E$1295,MATCH($D37,Hierarchy!$A$2:$A$1295,0))),"NODE NOT FOUND")) | I37: =IF($D37="","",IFERROR(IF(INDEX(Hierarchy!$F$2:$F$1295,MATCH($D37,Hierarchy!$A$2:$A$1295,0))="","",INDEX(Hierarchy!$F$2:$F$1295,MATCH($D37,Hierarchy!$A$2:$A$1295,0))),"NODE NOT FOUND")) | J37: =IF($D37="","",IFERROR(IF(INDEX(Hierarchy!$G$2:$G$1295,MATCH($D37,Hierarchy!$A$2:$A$1295,0))="","",INDEX(Hierarchy!$G$2:$G$1295,MATCH($D37,Hierarchy!$A$2:$A$1295,0))),"NODE NOT FOUND")) | K37: =IF($D37="","",IFERROR(IF(INDEX(Hierarchy!$H$2:$H$1295,MATCH($D37,Hierarchy!$A$2:$A$1295,0))="","",INDEX(Hierarchy!$H$2:$H$1295,MATCH($D37,Hierarchy!$A$2:$A$1295,0))),"NODE NOT FOUND")) | L37: =IF($D37="","",IFERROR(IF(INDEX(Hierarchy!$I$2:$I$1295,MATCH($D37,Hierarchy!$A$2:$A$1295,0))="","",INDEX(Hierarchy!$I$2:$I$1295,MATCH($D37,Hierarchy!$A$2:$A$1295,0))),"NODE NOT FOUND")) | M37: =IF(B37="Pre-seeded","Pre-seeded",IF(B37="Review 2026-09-16","Added from review",IF(C37="","New",IF(C37=D37,"","Changed")))) | N37: =TRIM(SUBSTITUTE(SUBSTITUTE(SUBSTITUTE(" "&TRIM(SUBSTITUTE(SUBSTITUTE(SUBSTITUTE(SUBSTITUTE(SUBSTITUTE(SUBSTITUTE(SUBSTITUTE(SUBSTITUTE(SUBSTITUTE(SUBSTITUTE(SUBSTITUTE(SUBSTITUTE(SUBSTITUTE(SUBSTITUTE(SUBSTITUTE(UPPER(TRIM(A37)),"[MEMBER]",""),"{MEMBER}",""),"[MEMBER}",""),"MEMBER]",""),"(A)",""),"""",""),"“",""),"”",""),".",""),":",""),",",""),"–"," "),"-"," "),"/"," "),"&"," AND "))&" "," THE "," ")," TOTAL "," ")," OPERATIONS "," ")) -> ALL OTHERS INTERNATIONAL | O37: =IF(COUNTIFS($N$2:$N$2000,N37,$D$2:$D$2000,"<>"&D37)>0,"CONFLICT","")
A38: AllOtherGeographiesMember | B38: Excluded → mapped | C38: (excluded) | D38: Other | E38: Residual | F38: =IF($D38="","",IFERROR(IF(INDEX(Hierarchy!$B$2:$B$1295,MATCH($D38,Hierarchy!$A$2:$A$1295,0))="","",INDEX(Hierarchy!$B$2:$B$1295,MATCH($D38,Hierarchy!$A$2:$A$1295,0))),"NODE NOT FOUND")) -> Bucket | G38: =IF($D38="","",IFERROR(IF(INDEX(Hierarchy!$D$2:$D$1295,MATCH($D38,Hierarchy!$A$2:$A$1295,0))="","",INDEX(Hierarchy!$D$2:$D$1295,MATCH($D38,Hierarchy!$A$2:$A$1295,0))),"NODE NOT FOUND")) -> Non-regional | H38: =IF($D38="","",IFERROR(IF(INDEX(Hierarchy!$E$2:$E$1295,MATCH($D38,Hierarchy!$A$2:$A$1295,0))="","",INDEX(Hierarchy!$E$2:$E$1295,MATCH($D38,Hierarchy!$A$2:$A$1295,0))),"NODE NOT FOUND")) | I38: =IF($D38="","",IFERROR(IF(INDEX(Hierarchy!$F$2:$F$1295,MATCH($D38,Hierarchy!$A$2:$A$1295,0))="","",INDEX(Hierarchy!$F$2:$F$1295,MATCH($D38,Hierarchy!$A$2:$A$1295,0))),"NODE NOT FOUND")) | J38: =IF($D38="","",IFERROR(IF(INDEX(Hierarchy!$G$2:$G$1295,MATCH($D38,Hierarchy!$A$2:$A$1295,0))="","",INDEX(Hierarchy!$G$2:$G$1295,MATCH($D38,Hierarchy!$A$2:$A$1295,0))),"NODE NOT FOUND")) | K38: =IF($D38="","",IFERROR(IF(INDEX(Hierarchy!$H$2:$H$1295,MATCH($D38,Hierarchy!$A$2:$A$1295,0))="","",INDEX(Hierarchy!$H$2:$H$1295,MATCH($D38,Hierarchy!$A$2:$A$1295,0))),"NODE NOT FOUND")) | L38: =IF($D38="","",IFERROR(IF(INDEX(Hierarchy!$I$2:$I$1295,MATCH($D38,Hierarchy!$A$2:$A$1295,0))="","",INDEX(Hierarchy!$I$2:$I$1295,MATCH($D38,Hierarchy!$A$2:$A$1295,0))),"NODE NOT FOUND")) | M38: =IF(B38="Pre-seeded","Pre-seeded",IF(B38="Review 2026-09-16","Added from review",IF(C38="","New",IF(C38=D38,"","Changed")))) -> Changed | N38: =TRIM(SUBSTITUTE(SUBSTITUTE(SUBSTITUTE(" "&TRIM(SUBSTITUTE(SUBSTITUTE(SUBSTITUTE(SUBSTITUTE(SUBSTITUTE(SUBSTITUTE(SUBSTITUTE(SUBSTITUTE(SUBSTITUTE(SUBSTITUTE(SUBSTITUTE(SUBSTITUTE(SUBSTITUTE(SUBSTITUTE(SUBSTITUTE(UPPER(TRIM(A38)),"[MEMBER]",""),"{MEMBER}",""),"[MEMBER}",""),"MEMBER]",""),"(A)",""),"""",""),"“",""),"”",""),".",""),":",""),",",""),"–"," "),"-"," "),"/"," "),"&"," AND "))&" "," THE "," ")," TOTAL "," ")," OPERATIONS "," ")) -> ALLOTHERGEOGRAPHIESMEMBER | O38: =IF(COUNTIFS($N$2:$N$2000,N38,$D$2:$D$2000,"<>"&D38)>0,"CONFLICT","") | P38: XBRL name for 'All other geographies'; moved from Excluded
A39: Almea | B39: remove (decoded) | D39: Multi-region (Other) | E39: Combined | F39: =IF($D39="","",IFERROR(IF(INDEX(Hierarchy!$B$2:$B$1295,MATCH($D39,Hierarchy!$A$2:$A$1295,0))="","",INDEX(Hierarchy!$B$2:$B$1295,MATCH($D39,Hierarchy!$A$2:$A$1295,0))),"NODE NOT FOUND")) -> Multi-region | G39: =IF($D39="","",IFERROR(IF(INDEX(Hierarchy!$D$2:$D$1295,MATCH($D39,Hierarchy!$A$2:$A$1295,0))="","",INDEX(Hierarchy!$D$2:$D$1295,MATCH($D39,Hierarchy!$A$2:$A$1295,0))),"NODE NOT FOUND")) -> Multi-region | H39: =IF($D39="","",IFERROR(IF(INDEX(Hierarchy!$E$2:$E$1295,MATCH($D39,Hierarchy!$A$2:$A$1295,0))="","",INDEX(Hierarchy!$E$2:$E$1295,MATCH($D39,Hierarchy!$A$2:$A$1295,0))),"NODE NOT FOUND")) | I39: =IF($D39="","",IFERROR(IF(INDEX(Hierarchy!$F$2:$F$1295,MATCH($D39,Hierarchy!$A$2:$A$1295,0))="","",INDEX(Hierarchy!$F$2:$F$1295,MATCH($D39,Hierarchy!$A$2:$A$1295,0))),"NODE NOT FOUND")) | J39: =IF($D39="","",IFERROR(IF(INDEX(Hierarchy!$G$2:$G$1295,MATCH($D39,Hierarchy!$A$2:$A$1295,0))="","",INDEX(Hierarchy!$G$2:$G$1295,MATCH($D39,Hierarchy!$A$2:$A$1295,0))),"NODE NOT FOUND")) | K39: =IF($D39="","",IFERROR(IF(INDEX(Hierarchy!$H$2:$H$1295,MATCH($D39,Hierarchy!$A$2:$A$1295,0))="","",INDEX(Hierarchy!$H$2:$H$1295,MATCH($D39,Hierarchy!$A$2:$A$1295,0))),"NODE NOT FOUND")) | L39: =IF($D39="","",IFERROR(IF(INDEX(Hierarchy!$I$2:$I$1295,MATCH($D39,Hierarchy!$A$2:$A$1295,0))="","",INDEX(Hierarchy!$I$2:$I$1295,MATCH($D39,Hierarchy!$A$2:$A$1295,0))),"NODE NOT FOUND")) | M39: =IF(B39="Pre-seeded","Pre-seeded",IF(B39="Review 2026-09-16","Added from review",IF(C39="","New",IF(C39=D39,"","Changed")))) -> New | N39: =TRIM(SUBSTITUTE(SUBSTITUTE(SUBSTITUTE(" "&TRIM(SUBSTITUTE(SUBSTITUTE(SUBSTITUTE(SUBSTITUTE(SUBSTITUTE(SUBSTITUTE(SUBSTITUTE(SUBSTITUTE(SUBSTITUTE(SUBSTITUTE(SUBSTITUTE(SUBSTITUTE(SUBSTITUTE(SUBSTITUTE(SUBSTITUTE(UPPER(TRIM(A39)),"[MEMBER]",""),"{MEMBER}",""),"[MEMBER}",""),"MEMBER]",""),"(A)",""),"""",""),"“",""),"”",""),".",""),":",""),",",""),"–"," "),"-"," "),"/"," "),"&"," AND "))&" "," THE "," ")," TOTAL "," ")," OPERATIONS "," ")) -> ALMEA | O39: =IF(COUNTIFS($N$2:$N$2000,N39,$D$2:$D$2000,"<>"&D39)>0,"CONFLICT","") | P39: Likely Asia, Latin America, Middle East & Africa — confirm
A40: Amapá | B40: Pre-seeded | D40: Amapá | E40: Exact | F40: =IF($D40="","",IFERROR(IF(INDEX(Hierarchy!$B$2:$B$1295,MATCH($D40,Hierarchy!$A$2:$A$1295,0))="","",INDEX(Hierarchy!$B$2:$B$1295,MATCH($D40,Hierarchy!$A$2:$A$1295,0))),"NODE NOT FOUND")) -> State/Province | G40: =IF($D40="","",IFERROR(IF(INDEX(Hierarchy!$D$2:$D$1295,MATCH($D40,Hierarchy!$A$2:$A$1295,0))="","",INDEX(Hierarchy!$D$2:$D$1295,MATCH($D40,Hierarchy!$A$2:$A$1295,0))),"NODE NOT FOUND")) -> AMER | H40: =IF($D40="","",IFERROR(IF(INDEX(Hierarchy!$E$2:$E$1295,MATCH($D40,Hierarchy!$A$2:$A$1295,0))="","",INDEX(Hierarchy!$E$2:$E$1295,MATCH($D40,Hierarchy!$A$2:$A$1295,0))),"NODE NOT FOUND")) -> Latin America (LATAM) | I40: =IF($D40="","",IFERROR(IF(INDEX(Hierarchy!$F$2:$F$1295,MATCH($D40,Hierarchy!$A$2:$A$1295,0))="","",INDEX(Hierarchy!$F$2:$F$1295,MATCH($D40,Hierarchy!$A$2:$A$1295,0))),"NODE NOT FOUND")) -> Brazil | J40: =IF($D40="","",IFERROR(IF(INDEX(Hierarchy!$G$2:$G$1295,MATCH($D40,Hierarchy!$A$2:$A$1295,0))="","",INDEX(Hierarchy!$G$2:$G$1295,MATCH($D40,Hierarchy!$A$2:$A$1295,0))),"NODE NOT FOUND")) -> BRA | K40: =IF($D40="","",IFERROR(IF(INDEX(Hierarchy!$H$2:$H$1295,MATCH($D40,Hierarchy!$A$2:$A$1295,0))="","",INDEX(Hierarchy!$H$2:$H$1295,MATCH($D40,Hierarchy!$A$2:$A$1295,0))),"NODE NOT FOUND")) -> Amapá | L40: =IF($D40="","",IFERROR(IF(INDEX(Hierarchy!$I$2:$I$1295,MATCH($D40,Hierarchy!$A$2:$A$1295,0))="","",INDEX(Hierarchy!$I$2:$I$1295,MATCH($D40,Hierarchy!$A$2:$A$1295,0))),"NODE NOT FOUND")) | M40: =IF(B40="Pre-seeded","Pre-seeded",IF(B40="Review 2026-09-16","Added from review",IF(C40="","New",IF(C40=D40,"","Changed")))) -> Pre-seeded | N40: =TRIM(SUBSTITUTE(SUBSTITUTE(SUBSTITUTE(" "&TRIM(SUBSTITUTE(SUBSTITUTE(SUBSTITUTE(SUBSTITUTE(SUBSTITUTE(SUBSTITUTE(SUBSTITUTE(SUBSTITUTE(SUBSTITUTE(SUBSTITUTE(SUBSTITUTE(SUBSTITUTE(SUBSTITUTE(SUBSTITUTE(SUBSTITUTE(UPPER(TRIM(A40)),"[MEMBER]",""),"{MEMBER}",""),"[MEMBER}",""),"MEMBER]",""),"(A)",""),"""",""),"“",""),"”",""),".",""),":",""),",",""),"–"," "),"-"," "),"/"," "),"&"," AND "))&" "," THE "," ")," TOTAL "," ")," OPERATIONS "," ")) -> AMAPÁ | O40: =IF(COUNTIFS($N$2:$N$2000,N40,$D$2:$D$2000,"<>"&D40)>0,"CONFLICT","")
A41: Amazonas | B41: Pre-seeded | D41: Amazonas | E41: Exact | F41: =IF($D41="","",IFERROR(IF(INDEX(Hierarchy!$B$2:$B$1295,MATCH($D41,Hierarchy!$A$2:$A$1295,0))="","",INDEX(Hierarchy!$B$2:$B$1295,MATCH($D41,Hierarchy!$A$2:$A$1295,0))),"NODE NOT FOUND")) -> State/Province | G41: =IF($D41="","",IFERROR(IF(INDEX(Hierarchy!$D$2:$D$1295,MATCH($D41,Hierarchy!$A$2:$A$1295,0))="","",INDEX(Hierarchy!$D$2:$D$1295,MATCH($D41,Hierarchy!$A$2:$A$1295,0))),"NODE NOT FOUND")) -> AMER | H41: =IF($D41="","",IFERROR(IF(INDEX(Hierarchy!$E$2:$E$1295,MATCH($D41,Hierarchy!$A$2:$A$1295,0))="","",INDEX(Hierarchy!$E$2:$E$1295,MATCH($D41,Hierarchy!$A$2:$A$1295,0))),"NODE NOT FOUND")) -> Latin America (LATAM) | I41: =IF($D41="","",IFERROR(IF(INDEX(Hierarchy!$F$2:$F$1295,MATCH($D41,Hierarchy!$A$2:$A$1295,0))="","",INDEX(Hierarchy!$F$2:$F$1295,MATCH($D41,Hierarchy!$A$2:$A$1295,0))),"NODE NOT FOUND")) -> Brazil | J41: =IF($D41="","",IFERROR(IF(INDEX(Hierarchy!$G$2:$G$1295,MATCH($D41,Hierarchy!$A$2:$A$1295,0))="","",INDEX(Hierarchy!$G$2:$G$1295,MATCH($D41,Hierarchy!$A$2:$A$1295,0))),"NODE NOT FOUND")) -> BRA | K41: =IF($D41="","",IFERROR(IF(INDEX(Hierarchy!$H$2:$H$1295,MATCH($D41,Hierarchy!$A$2:$A$1295,0))="","",INDEX(Hierarchy!$H$2:$H$1295,MATCH($D41,Hierarchy!$A$2:$A$1295,0))),"NODE NOT FOUND")) -> Amazonas | L41: =IF($D41="","",IFERROR(IF(INDEX(Hierarchy!$I$2:$I$1295,MATCH($D41,Hierarchy!$A$2:$A$1295,0))="","",INDEX(Hierarchy!$I$2:$I$1295,MATCH($D41,Hierarchy!$A$2:$A$1295,0))),"NODE NOT FOUND")) | M41: =IF(B41="Pre-seeded","Pre-seeded",IF(B41="Review 2026-09-16","Added from review",IF(C41="","New",IF(C41=D41,"","Changed")))) -> Pre-seeded | N41: =TRIM(SUBSTITUTE(SUBSTITUTE(SUBSTITUTE(" "&TRIM(SUBSTITUTE(SUBSTITUTE(SUBSTITUTE(SUBSTITUTE(SUBSTITUTE(SUBSTITUTE(SUBSTITUTE(SUBSTITUTE(SUBSTITUTE(SUBSTITUTE(SUBSTITUTE(SUBSTITUTE(SUBSTITUTE(SUBSTITUTE(SUBSTITUTE(UPPER(TRIM(A41)),"[MEMBER]",""),"{MEMBER}",""),"[MEMBER}",""),"MEMBER]",""),"(A)",""),"""",""),"“",""),"”",""),".",""),":",""),",",""),"–"," "),"-"," "),"/"," "),"&"," AND "))&" "," THE "," ")," TOTAL "," ")," OPERATIONS "," ")) -> AMAZONAS | O41: =IF(COUNTIFS($N$2:$N$2000,N41,$D$2:$D$2000,"<>"&D41)>0,"CONFLICT","")
A42: Amazonas (Colombia) | B42: Pre-seeded | D42: Amazonas (Colombia) | E42: Exact | F42: =IF($D42="","",IFERROR(IF(INDEX(Hierarchy!$B$2:$B$1295,MATCH($D42,Hierarchy!$A$2:$A$1295,0))="","",INDEX(Hierarchy!$B$2:$B$1295,MATCH($D42,Hierarchy!$A$2:$A$1295,0))),"NODE NOT FOUND")) -> State/Province | G42: =IF($D42="","",IFERROR(IF(INDEX(Hierarchy!$D$2:$D$1295,MATCH($D42,Hierarchy!$A$2:$A$1295,0))="","",INDEX(Hierarchy!$D$2:$D$1295,MATCH($D42,Hierarchy!$A$2:$A$1295,0))),"NODE NOT FOUND")) -> AMER | H42: =IF($D42="","",IFERROR(IF(INDEX(Hierarchy!$E$2:$E$1295,MATCH($D42,Hierarchy!$A$2:$A$1295,0))="","",INDEX(Hierarchy!$E$2:$E$1295,MATCH($D42,Hierarchy!$A$2:$A$1295,0))),"NODE NOT FOUND")) -> Latin America (LATAM) | I42: =IF($D42="","",IFERROR(IF(INDEX(Hierarchy!$F$2:$F$1295,MATCH($D42,Hierarchy!$A$2:$A$1295,0))="","",INDEX(Hierarchy!$F$2:$F$1295,MATCH($D42,Hierarchy!$A$2:$A$1295,0))),"NODE NOT FOUND")) -> Colombia | J42: =IF($D42="","",IFERROR(IF(INDEX(Hierarchy!$G$2:$G$1295,MATCH($D42,Hierarchy!$A$2:$A$1295,0))="","",INDEX(Hierarchy!$G$2:$G$1295,MATCH($D42,Hierarchy!$A$2:$A$1295,0))),"NODE NOT FOUND")) -> COL | K42: =IF($D42="","",IFERROR(IF(INDEX(Hierarchy!$H$2:$H$1295,MATCH($D42,Hierarchy!$A$2:$A$1295,0))="","",INDEX(Hierarchy!$H$2:$H$1295,MATCH($D42,Hierarchy!$A$2:$A$1295,0))),"NODE NOT FOUND")) -> Amazonas (Colombia) | L42: =IF($D42="","",IFERROR(IF(INDEX(Hierarchy!$I$2:$I$1295,MATCH($D42,Hierarchy!$A$2:$A$1295,0))="","",INDEX(Hierarchy!$I$2:$I$1295,MATCH($D42,Hierarchy!$A$2:$A$1295,0))),"NODE NOT FOUND")) | M42: =IF(B42="Pre-seeded","Pre-seeded",IF(B42="Review 2026-09-16","Added from review",IF(C42="","New",IF(C42=D42,"","Changed")))) -> Pre-seeded | N42: =TRIM(SUBSTITUTE(SUBSTITUTE(SUBSTITUTE(" "&TRIM(SUBSTITUTE(SUBSTITUTE(SUBSTITUTE(SUBSTITUTE(SUBSTITUTE(SUBSTITUTE(SUBSTITUTE(SUBSTITUTE(SUBSTITUTE(SUBSTITUTE(SUBSTITUTE(SUBSTITUTE(SUBSTITUTE(SUBSTITUTE(SUBSTITUTE(UPPER(TRIM(A42)),"[MEMBER]",""),"{MEMBER}",""),"[MEMBER}",""),"MEMBER]",""),"(A)",""),"""",""),"“",""),"”",""),".",""),":",""),",",""),"–"," "),"-"," "),"/"," "),"&"," AND "))&" "," THE "," ")," TOTAL "," ")," OPERATIONS "," ")) -> AMAZONAS (COLOMBIA) | O42: =IF(COUNTIFS($N$2:$N$2000,N42,$D$2:$D$2000,"<>"&D42)>0,"CONFLICT","")
A43: Amea | B43: remove (decoded) | D43: Asia, Middle East and Africa (AMEA) | E43: Exact | F43: =IF($D43="","",IFERROR(IF(INDEX(Hierarchy!$B$2:$B$1295,MATCH($D43,Hierarchy!$A$2:$A$1295,0))="","",INDEX(Hierarchy!$B$2:$B$1295,MATCH($D43,Hierarchy!$A$2:$A$1295,0))),"NODE NOT FOUND")) -> Multi-region | G43: =IF($D43="","",IFERROR(IF(INDEX(Hierarchy!$D$2:$D$1295,MATCH($D43,Hierarchy!$A$2:$A$1295,0))="","",INDEX(Hierarchy!$D$2:$D$1295,MATCH($D43,Hierarchy!$A$2:$A$1295,0))),"NODE NOT FOUND")) -> Multi-region | H43: =IF($D43="","",IFERROR(IF(INDEX(Hierarchy!$E$2:$E$1295,MATCH($D43,Hierarchy!$A$2:$A$1295,0))="","",INDEX(Hierarchy!$E$2:$E$1295,MATCH($D43,Hierarchy!$A$2:$A$1295,0))),"NODE NOT FOUND")) | I43: =IF($D43="","",IFERROR(IF(INDEX(Hierarchy!$F$2:$F$1295,MATCH($D43,Hierarchy!$A$2:$A$1295,0))="","",INDEX(Hierarchy!$F$2:$F$1295,MATCH($D43,Hierarchy!$A$2:$A$1295,0))),"NODE NOT FOUND")) | J43: =IF($D43="","",IFERROR(IF(INDEX(Hierarchy!$G$2:$G$1295,MATCH($D43,Hierarchy!$A$2:$A$1295,0))="","",INDEX(Hierarchy!$G$2:$G$1295,MATCH($D43,Hierarchy!$A$2:$A$1295,0))),"NODE NOT FOUND")) | K43: =IF($D43="","",IFERROR(IF(INDEX(Hierarchy!$H$2:$H$1295,MATCH($D43,Hierarchy!$A$2:$A$1295,0))="","",INDEX(Hierarchy!$H$2:$H$1295,MATCH($D43,Hierarchy!$A$2:$A$1295,0))),"NODE NOT FOUND")) | L43: =IF($D43="","",IFERROR(IF(INDEX(Hierarchy!$I$2:$I$1295,MATCH($D43,Hierarchy!$A$2:$A$1295,0))="","",INDEX(Hierarchy!$I$2:$I$1295,MATCH($D43,Hierarchy!$A$2:$A$1295,0))),"NODE NOT FOUND")) | M43: =IF(B43="Pre-seeded","Pre-seeded",IF(B43="Review 2026-09-16","Added from review",IF(C43="","New",IF(C43=D43,"","Changed")))) -> New | N43: =TRIM(SUBSTITUTE(SUBSTITUTE(SUBSTITUTE(" "&TRIM(SUBSTITUTE(SUBSTITUTE(SUBSTITUTE(SUBSTITUTE(SUBSTITUTE(SUBSTITUTE(SUBSTITUTE(SUBSTITUTE(SUBSTITUTE(SUBSTITUTE(SUBSTITUTE(SUBSTITUTE(SUBSTITUTE(SUBSTITUTE(SUBSTITUTE(UPPER(TRIM(A43)),"[MEMBER]",""),"{MEMBER}",""),"[MEMBER}",""),"MEMBER]",""),"(A)",""),"""",""),"“",""),"”",""),".",""),":",""),",",""),"–"," "),"-"," "),"/"," "),"&"," AND "))&" "," THE "," ")," TOTAL "," ")," OPERATIONS "," ")) -> AMEA | O43: =IF(COUNTIFS($N$2:$N$2000,N43,$D$2:$D$2000,"<>"&D43)>0,"CONFLICT","")
A44: AMER | B44: Pre-seeded | D44: AMER (Americas) | E44: Exact | F44: =IF($D44="","",IFERROR(IF(INDEX(Hierarchy!$B$2:$B$1295,MATCH($D44,Hierarchy!$A$2:$A$1295,0))="","",INDEX(Hierarchy!$B$2:$B$1295,MATCH($D44,Hierarchy!$A$2:$A$1295,0))),"NODE NOT FOUND")) -> Region | G44: =IF($D44="","",IFERROR(IF(INDEX(Hierarchy!$D$2:$D$1295,MATCH($D44,Hierarchy!$A$2:$A$1295,0))="","",INDEX(Hierarchy!$D$2:$D$1295,MATCH($D44,Hierarchy!$A$2:$A$1295,0))),"NODE NOT FOUND")) -> AMER | H44: =IF($D44="","",IFERROR(IF(INDEX(Hierarchy!$E$2:$E$1295,MATCH($D44,Hierarchy!$A$2:$A$1295,0))="","",INDEX(Hierarchy!$E$2:$E$1295,MATCH($D44,Hierarchy!$A$2:$A$1295,0))),"NODE NOT FOUND")) | I44: =IF($D44="","",IFERROR(IF(INDEX(Hierarchy!$F$2:$F$1295,MATCH($D44,Hierarchy!$A$2:$A$1295,0))="","",INDEX(Hierarchy!$F$2:$F$1295,MATCH($D44,Hierarchy!$A$2:$A$1295,0))),"NODE NOT FOUND")) | J44: =IF($D44="","",IFERROR(IF(INDEX(Hierarchy!$G$2:$G$1295,MATCH($D44,Hierarchy!$A$2:$A$1295,0))="","",INDEX(Hierarchy!$G$2:$G$1295,MATCH($D44,Hierarchy!$A$2:$A$1295,0))),"NODE NOT FOUND")) | K44: =IF($D44="","",IFERROR(IF(INDEX(Hierarchy!$H$2:$H$1295,MATCH($D44,Hierarchy!$A$2:$A$1295,0))="","",INDEX(Hierarchy!$H$2:$H$1295,MATCH($D44,Hierarchy!$A$2:$A$1295,0))),"NODE NOT FOUND")) | L44: =IF($D44="","",IFERROR(IF(INDEX(Hierarchy!$I$2:$I$1295,MATCH($D44,Hierarchy!$A$2:$A$1295,0))="","",INDEX(Hierarchy!$I$2:$I$1295,MATCH($D44,Hierarchy!$A$2:$A$1295,0))),"NODE NOT FOUND")) | M44: =IF(B44="Pre-seeded","Pre-seeded",IF(B44="Review 2026-09-16","Added from review",IF(C44="","New",IF(C44=D44,"","Changed")))) -> Pre-seeded | N44: =TRIM(SUBSTITUTE(SUBSTITUTE(SUBSTITUTE(" "&TRIM(SUBSTITUTE(SUBSTITUTE(SUBSTITUTE(SUBSTITUTE(SUBSTITUTE(SUBSTITUTE(SUBSTITUTE(SUBSTITUTE(SUBSTITUTE(SUBSTITUTE(SUBSTITUTE(SUBSTITUTE(SUBSTITUTE(SUBSTITUTE(SUBSTITUTE(UPPER(TRIM(A44)),"[MEMBER]",""),"{MEMBER}",""),"[MEMBER}",""),"MEMBER]",""),"(A)",""),"""",""),"“",""),"”",""),".",""),":",""),",",""),"–"," "),"-"," "),"/"," "),"&"," AND "))&" "," THE "," ")," TOTAL "," ")," OPERATIONS "," ")) -> AMER | O44: =IF(COUNTIFS($N$2:$N$2000,N44,$D$2:$D$2000,"<>"&D44)>0,"CONFLICT","")
A45: AMER (Americas) | B45: Pre-seeded | D45: AMER (Americas) | E45: Exact | F45: =IF($D45="","",IFERROR(IF(INDEX(Hierarchy!$B$2:$B$1295,MATCH($D45,Hierarchy!$A$2:$A$1295,0))="","",INDEX(Hierarchy!$B$2:$B$1295,MATCH($D45,Hierarchy!$A$2:$A$1295,0))),"NODE NOT FOUND")) -> Region | G45: =IF($D45="","",IFERROR(IF(INDEX(Hierarchy!$D$2:$D$1295,MATCH($D45,Hierarchy!$A$2:$A$1295,0))="","",INDEX(Hierarchy!$D$2:$D$1295,MATCH($D45,Hierarchy!$A$2:$A$1295,0))),"NODE NOT FOUND")) -> AMER | H45: =IF($D45="","",IFERROR(IF(INDEX(Hierarchy!$E$2:$E$1295,MATCH($D45,Hierarchy!$A$2:$A$1295,0))="","",INDEX(Hierarchy!$E$2:$E$1295,MATCH($D45,Hierarchy!$A$2:$A$1295,0))),"NODE NOT FOUND")) | I45: =IF($D45="","",IFERROR(IF(INDEX(Hierarchy!$F$2:$F$1295,MATCH($D45,Hierarchy!$A$2:$A$1295,0))="","",INDEX(Hierarchy!$F$2:$F$1295,MATCH($D45,Hierarchy!$A$2:$A$1295,0))),"NODE NOT FOUND")) | J45: =IF($D45="","",IFERROR(IF(INDEX(Hierarchy!$G$2:$G$1295,MATCH($D45,Hierarchy!$A$2:$A$1295,0))="","",INDEX(Hierarchy!$G$2:$G$1295,MATCH($D45,Hierarchy!$A$2:$A$1295,0))),"NODE NOT FOUND")) | K45: =IF($D45="","",IFERROR(IF(INDEX(Hierarchy!$H$2:$H$1295,MATCH($D45,Hierarchy!$A$2:$A$1295,0))="","",INDEX(Hierarchy!$H$2:$H$1295,MATCH($D45,Hierarchy!$A$2:$A$1295,0))),"NODE NOT FOUND")) | L45: =IF($D45="","",IFERROR(IF(INDEX(Hierarchy!$I$2:$I$1295,MATCH($D45,Hierarchy!$A$2:$A$1295,0))="","",INDEX(Hierarchy!$I$2:$I$1295,MATCH($D45,Hierarchy!$A$2:$A$1295,0))),"NODE NOT FOUND")) | M45: =IF(B45="Pre-seeded","Pre-seeded",IF(B45="Review 2026-09-16","Added from review",IF(C45="","New",IF(C45=D45,"","Changed")))) -> Pre-seeded | N45: =TRIM(SUBSTITUTE(SUBSTITUTE(SUBSTITUTE(" "&TRIM(SUBSTITUTE(SUBSTITUTE(SUBSTITUTE(SUBSTITUTE(SUBSTITUTE(SUBSTITUTE(SUBSTITUTE(SUBSTITUTE(SUBSTITUTE(SUBSTITUTE(SUBSTITUTE(SUBSTITUTE(SUBSTITUTE(SUBSTITUTE(SUBSTITUTE(UPPER(TRIM(A45)),"[MEMBER]",""),"{MEMBER}",""),"[MEMBER}",""),"MEMBER]",""),"(A)",""),"""",""),"“",""),"”",""),".",""),":",""),",",""),"–"," "),"-"," "),"/"," "),"&"," AND "))&" "," THE "," ")," TOTAL "," ")," OPERATIONS "," ")) -> AMER (AMERICAS) | O45: =IF(COUNTIFS($N$2:$N$2000,N45,$D$2:$D$2000,"<>"&D45)>0,"CONFLICT","")
A46: America | B46: final | C46: Americas | D46: AMER (Americas) | E46: Exact | F46: =IF($D46="","",IFERROR(IF(INDEX(Hierarchy!$B$2:$B$1295,MATCH($D46,Hierarchy!$A$2:$A$1295,0))="","",INDEX(Hierarchy!$B$2:$B$1295,MATCH($D46,Hierarchy!$A$2:$A$1295,0))),"NODE NOT FOUND")) -> Region | G46: =IF($D46="","",IFERROR(IF(INDEX(Hierarchy!$D$2:$D$1295,MATCH($D46,Hierarchy!$A$2:$A$1295,0))="","",INDEX(Hierarchy!$D$2:$D$1295,MATCH($D46,Hierarchy!$A$2:$A$1295,0))),"NODE NOT FOUND")) -> AMER | H46: =IF($D46="","",IFERROR(IF(INDEX(Hierarchy!$E$2:$E$1295,MATCH($D46,Hierarchy!$A$2:$A$1295,0))="","",INDEX(Hierarchy!$E$2:$E$1295,MATCH($D46,Hierarchy!$A$2:$A$1295,0))),"NODE NOT FOUND")) | I46: =IF($D46="","",IFERROR(IF(INDEX(Hierarchy!$F$2:$F$1295,MATCH($D46,Hierarchy!$A$2:$A$1295,0))="","",INDEX(Hierarchy!$F$2:$F$1295,MATCH($D46,Hierarchy!$A$2:$A$1295,0))),"NODE NOT FOUND")) | J46: =IF($D46="","",IFERROR(IF(INDEX(Hierarchy!$G$2:$G$1295,MATCH($D46,Hierarchy!$A$2:$A$1295,0))="","",INDEX(Hierarchy!$G$2:$G$1295,MATCH($D46,Hierarchy!$A$2:$A$1295,0))),"NODE NOT FOUND")) | K46: =IF($D46="","",IFERROR(IF(INDEX(Hierarchy!$H$2:$H$1295,MATCH($D46,Hierarchy!$A$2:$A$1295,0))="","",INDEX(Hierarchy!$H$2:$H$1295,MATCH($D46,Hierarchy!$A$2:$A$1295,0))),"NODE NOT FOUND")) | L46: =IF($D46="","",IFERROR(IF(INDEX(Hierarchy!$I$2:$I$1295,MATCH($D46,Hierarchy!$A$2:$A$1295,0))="","",INDEX(Hierarchy!$I$2:$I$1295,MATCH($D46,Hierarchy!$A$2:$A$1295,0))),"NODE NOT FOUND")) | M46: =IF(B46="Pre-seeded","Pre-seeded",IF(B46="Review 2026-09-16","Added from review",IF(C46="","New",IF(C46=D46,"","Changed")))) -> Changed | N46: =TRIM(SUBSTITUTE(SUBSTITUTE(SUBSTITUTE(" "&TRIM(SUBSTITUTE(SUBSTITUTE(SUBSTITUTE(SUBSTITUTE(SUBSTITUTE(SUBSTITUTE(SUBSTITUTE(SUBSTITUTE(SUBSTITUTE(SUBSTITUTE(SUBSTITUTE(SUBSTITUTE(SUBSTITUTE(SUBSTITUTE(SUBSTITUTE(UPPER(TRIM(A46)),"[MEMBER]",""),"{MEMBER}",""),"[MEMBER}",""),"MEMBER]",""),"(A)",""),"""",""),"“",""),"”",""),".",""),":",""),",",""),"–"," "),"-"," "),"/"," "),"&"," AND "))&" "," THE "," ")," TOTAL "," ")," OPERATIONS "," ")) -> AMERICA | O46: =IF(COUNTIFS($N$2:$N$2000,N46,$D$2:$D$2000,"<>"&D46)>0,"CONFLICT","") | P46: Ambiguous — could mean US; confirm per filer
A47: American Samoa | B47: Pre-seeded | D47: American Samoa | E47: Exact | F47: =IF($D47="","",IFERROR(IF(INDEX(Hierarchy!$B$2:$B$1295,MATCH($D47,Hierarchy!$A$2:$A$1295,0))="","",INDEX(Hierarchy!$B$2:$B$1295,MATCH($D47,Hierarchy!$A$2:$A$1295,0))),"NODE NOT FOUND")) -> State/Province | G47: =IF($D47="","",IFERROR(IF(INDEX(Hierarchy!$D$2:$D$1295,MATCH($D47,Hierarchy!$A$2:$A$1295,0))="","",INDEX(Hierarchy!$D$2:$D$1295,MATCH($D47,Hierarchy!$A$2:$A$1295,0))),"NODE NOT FOUND")) -> AMER | H47: =IF($D47="","",IFERROR(IF(INDEX(Hierarchy!$E$2:$E$1295,MATCH($D47,Hierarchy!$A$2:$A$1295,0))="","",INDEX(Hierarchy!$E$2:$E$1295,MATCH($D47,Hierarchy!$A$2:$A$1295,0))),"NODE NOT FOUND")) -> North America (NORAM) | I47: =IF($D47="","",IFERROR(IF(INDEX(Hierarchy!$F$2:$F$1295,MATCH($D47,Hierarchy!$A$2:$A$1295,0))="","",INDEX(Hierarchy!$F$2:$F$1295,MATCH($D47,Hierarchy!$A$2:$A$1295,0))),"NODE NOT FOUND")) -> United States | J47: =IF($D47="","",IFERROR(IF(INDEX(Hierarchy!$G$2:$G$1295,MATCH($D47,Hierarchy!$A$2:$A$1295,0))="","",INDEX(Hierarchy!$G$2:$G$1295,MATCH($D47,Hierarchy!$A$2:$A$1295,0))),"NODE NOT FOUND")) -> USA | K47: =IF($D47="","",IFERROR(IF(INDEX(Hierarchy!$H$2:$H$1295,MATCH($D47,Hierarchy!$A$2:$A$1295,0))="","",INDEX(Hierarchy!$H$2:$H$1295,MATCH($D47,Hierarchy!$A$2:$A$1295,0))),"NODE NOT FOUND")) -> American Samoa | L47: =IF($D47="","",IFERROR(IF(INDEX(Hierarchy!$I$2:$I$1295,MATCH($D47,Hierarchy!$A$2:$A$1295,0))="","",INDEX(Hierarchy!$I$2:$I$1295,MATCH($D47,Hierarchy!$A$2:$A$1295,0))),"NODE NOT FOUND")) | M47: =IF(B47="Pre-seeded","Pre-seeded",IF(B47="Review 2026-09-16","Added from review",IF(C47="","New",IF(C47=D47,"","Changed")))) -> Pre-seeded | N47: =TRIM(SUBSTITUTE(SUBSTITUTE(SUBSTITUTE(" "&TRIM(SUBSTITUTE(SUBSTITUTE(SUBSTITUTE(SUBSTITUTE(SUBSTITUTE(SUBSTITUTE(SUBSTITUTE(SUBSTITUTE(SUBSTITUTE(SUBSTITUTE(SUBSTITUTE(SUBSTITUTE(SUBSTITUTE(SUBSTITUTE(SUBSTITUTE(UPPER(TRIM(A47)),"[MEMBER]",""),"{MEMBER}",""),"[MEMBER}",""),"MEMBER]",""),"(A)",""),"""",""),"“",""),"”",""),".",""),":",""),",",""),"–"," "),"-"," "),"/"," "),"&"," AND "))&" "," THE "," ")," TOTAL "," ")," OPERATIONS "," ")) -> AMERICAN SAMOA | O47: =IF(COUNTIFS($N$2:$N$2000,N47,$D$2:$D$2000,"<>"&D47)>0,"CONFLICT","")
A48: Americas | B48: Mapping | C48: Americas | D48: AMER (Americas) | E48: Exact | F48: =IF($D48="","",IFERROR(IF(INDEX(Hierarchy!$B$2:$B$1295,MATCH($D48,Hierarchy!$A$2:$A$1295,0))="","",INDEX(Hierarchy!$B$2:$B$1295,MATCH($D48,Hierarchy!$A$2:$A$1295,0))),"NODE NOT FOUND")) -> Region | G48: =IF($D48="","",IFERROR(IF(INDEX(Hierarchy!$D$2:$D$1295,MATCH($D48,Hierarchy!$A$2:$A$1295,0))="","",INDEX(Hierarchy!$D$2:$D$1295,MATCH($D48,Hierarchy!$A$2:$A$1295,0))),"NODE NOT FOUND")) -> AMER | H48: =IF($D48="","",IFERROR(IF(INDEX(Hierarchy!$E$2:$E$1295,MATCH($D48,Hierarchy!$A$2:$A$1295,0))="","",INDEX(Hierarchy!$E$2:$E$1295,MATCH($D48,Hierarchy!$A$2:$A$1295,0))),"NODE NOT FOUND")) | I48: =IF($D48="","",IFERROR(IF(INDEX(Hierarchy!$F$2:$F$1295,MATCH($D48,Hierarchy!$A$2:$A$1295,0))="","",INDEX(Hierarchy!$F$2:$F$1295,MATCH($D48,Hierarchy!$A$2:$A$1295,0))),"NODE NOT FOUND")) | J48: =IF($D48="","",IFERROR(IF(INDEX(Hierarchy!$G$2:$G$1295,MATCH($D48,Hierarchy!$A$2:$A$1295,0))="","",INDEX(Hierarchy!$G$2:$G$1295,MATCH($D48,Hierarchy!$A$2:$A$1295,0))),"NODE NOT FOUND")) | K48: =IF($D48="","",IFERROR(IF(INDEX(Hierarchy!$H$2:$H$1295,MATCH($D48,Hierarchy!$A$2:$A$1295,0))="","",INDEX(Hierarchy!$H$2:$H$1295,MATCH($D48,Hierarchy!$A$2:$A$1295,0))),"NODE NOT FOUND")) | L48: =IF($D48="","",IFERROR(IF(INDEX(Hierarchy!$I$2:$I$1295,MATCH($D48,Hierarchy!$A$2:$A$1295,0))="","",INDEX(Hierarchy!$I$2:$I$1295,MATCH($D48,Hierarchy!$A$2:$A$1295,0))),"NODE NOT FOUND")) | M48: =IF(B48="Pre-seeded","Pre-seeded",IF(B48="Review 2026-09-16","Added from review",IF(C48="","New",IF(C48=D48,"","Changed")))) -> Changed | N48: =TRIM(SUBSTITUTE(SUBSTITUTE(SUBSTITUTE(" "&TRIM(SUBSTITUTE(SUBSTITUTE(SUBSTITUTE(SUBSTITUTE(SUBSTITUTE(SUBSTITUTE(SUBSTITUTE(SUBSTITUTE(SUBSTITUTE(SUBSTITUTE(SUBSTITUTE(SUBSTITUTE(SUBSTITUTE(SUBSTITUTE(SUBSTITUTE(UPPER(TRIM(A48)),"[MEMBER]",""),"{MEMBER}",""),"[MEMBER}",""),"MEMBER]",""),"(A)",""),"""",""),"“",""),"”",""),".",""),":",""),",",""),"–"," "),"-"," "),"/"," "),"&"," AND "))&" "," THE "," ")," TOTAL "," ")," OPERATIONS "," ")) -> AMERICAS | O48: =IF(COUNTIFS($N$2:$N$2000,N48,$D$2:$D$2000,"<>"&D48)>0,"CONFLICT","")
A49: Americas (excluding United States) | B49: final | C49: Americas | D49: AMER (Americas) | E49: Partial | F49: =IF($D49="","",IFERROR(IF(INDEX(Hierarchy!$B$2:$B$1295,MATCH($D49,Hierarchy!$A$2:$A$1295,0))="","",INDEX(Hierarchy!$B$2:$B$1295,MATCH($D49,Hierarchy!$A$2:$A$1295,0))),"NODE NOT FOUND")) -> Region | G49: =IF($D49="","",IFERROR(IF(INDEX(Hierarchy!$D$2:$D$1295,MATCH($D49,Hierarchy!$A$2:$A$1295,0))="","",INDEX(Hierarchy!$D$2:$D$1295,MATCH($D49,Hierarchy!$A$2:$A$1295,0))),"NODE NOT FOUND")) -> AMER | H49: =IF($D49="","",IFERROR(IF(INDEX(Hierarchy!$E$2:$E$1295,MATCH($D49,Hierarchy!$A$2:$A$1295,0))="","",INDEX(Hierarchy!$E$2:$E$1295,MATCH($D49,Hierarchy!$A$2:$A$1295,0))),"NODE NOT FOUND")) | I49: =IF($D49="","",IFERROR(IF(INDEX(Hierarchy!$F$2:$F$1295,MATCH($D49,Hierarchy!$A$2:$A$1295,0))="","",INDEX(Hierarchy!$F$2:$F$1295,MATCH($D49,Hierarchy!$A$2:$A$1295,0))),"NODE NOT FOUND")) | J49: =IF($D49="","",IFERROR(IF(INDEX(Hierarchy!$G$2:$G$1295,MATCH($D49,Hierarchy!$A$2:$A$1295,0))="","",INDEX(Hierarchy!$G$2:$G$1295,MATCH($D49,Hierarchy!$A$2:$A$1295,0))),"NODE NOT FOUND")) | K49: =IF($D49="","",IFERROR(IF(INDEX(Hierarchy!$H$2:$H$1295,MATCH($D49,Hierarchy!$A$2:$A$1295,0))="","",INDEX(Hierarchy!$H$2:$H$1295,MATCH($D49,Hierarchy!$A$2:$A$1295,0))),"NODE NOT FOUND")) | L49: =IF($D49="","",IFERROR(IF(INDEX(Hierarchy!$I$2:$I$1295,MATCH($D49,Hierarchy!$A$2:$A$1295,0))="","",INDEX(Hierarchy!$I$2:$I$1295,MATCH($D49,Hierarchy!$A$2:$A$1295,0))),"NODE NOT FOUND")) | M49: =IF(B49="Pre-seeded","Pre-seeded",IF(B49="Review 2026-09-16","Added from review",IF(C49="","New",IF(C49=D49,"","Changed")))) -> Changed | N49: =TRIM(SUBSTITUTE(SUBSTITUTE(SUBSTITUTE(" "&TRIM(SUBSTITUTE(SUBSTITUTE(SUBSTITUTE(SUBSTITUTE(SUBSTITUTE(SUBSTITUTE(SUBSTITUTE(SUBSTITUTE(SUBSTITUTE(SUBSTITUTE(SUBSTITUTE(SUBSTITUTE(SUBSTITUTE(SUBSTITUTE(SUBSTITUTE(UPPER(TRIM(A49)),"[MEMBER]",""),"{MEMBER}",""),"[MEMBER}",""),"MEMBER]",""),"(A)",""),"""",""),"“",""),"”",""),".",""),":",""),",",""),"–"," "),"-"," "),"/"," "),"&"," AND "))&" "," THE "," ")," TOTAL "," ")," OPERATIONS "," ")) -> AMERICAS (EXCLUDING UNITED STATES) | O49: =IF(COUNTIFS($N$2:$N$2000,N49,$D$2:$D$2000,"<>"&D49)>0,"CONFLICT","") | P49: Excludes US
A50: Americas (non-U.S.) | B50: final | C50: Americas | D50: AMER (Americas) | E50: Partial | F50: =IF($D50="","",IFERROR(IF(INDEX(Hierarchy!$B$2:$B$1295,MATCH($D50,Hierarchy!$A$2:$A$1295,0))="","",INDEX(Hierarchy!$B$2:$B$1295,MATCH($D50,Hierarchy!$A$2:$A$1295,0))),"NODE NOT FOUND")) -> Region | G50: =IF($D50="","",IFERROR(IF(INDEX(Hierarchy!$D$2:$D$1295,MATCH($D50,Hierarchy!$A$2:$A$1295,0))="","",INDEX(Hierarchy!$D$2:$D$1295,MATCH($D50,Hierarchy!$A$2:$A$1295,0))),"NODE NOT FOUND")) -> AMER | H50: =IF($D50="","",IFERROR(IF(INDEX(Hierarchy!$E$2:$E$1295,MATCH($D50,Hierarchy!$A$2:$A$1295,0))="","",INDEX(Hierarchy!$E$2:$E$1295,MATCH($D50,Hierarchy!$A$2:$A$1295,0))),"NODE NOT FOUND")) | I50: =IF($D50="","",IFERROR(IF(INDEX(Hierarchy!$F$2:$F$1295,MATCH($D50,Hierarchy!$A$2:$A$1295,0))="","",INDEX(Hierarchy!$F$2:$F$1295,MATCH($D50,Hierarchy!$A$2:$A$1295,0))),"NODE NOT FOUND")) | J50: =IF($D50="","",IFERROR(IF(INDEX(Hierarchy!$G$2:$G$1295,MATCH($D50,Hierarchy!$A$2:$A$1295,0))="","",INDEX(Hierarchy!$G$2:$G$1295,MATCH($D50,Hierarchy!$A$2:$A$1295,0))),"NODE NOT FOUND")) | K50: =IF($D50="","",IFERROR(IF(INDEX(Hierarchy!$H$2:$H$1295,MATCH($D50,Hierarchy!$A$2:$A$1295,0))="","",INDEX(Hierarchy!$H$2:$H$1295,MATCH($D50,Hierarchy!$A$2:$A$1295,0))),"NODE NOT FOUND")) | L50: =IF($D50="","",IFERROR(IF(INDEX(Hierarchy!$I$2:$I$1295,MATCH($D50,Hierarchy!$A$2:$A$1295,0))="","",INDEX(Hierarchy!$I$2:$I$1295,MATCH($D50,Hierarchy!$A$2:$A$1295,0))),"NODE NOT FOUND")) | M50: =IF(B50="Pre-seeded","Pre-seeded",IF(B50="Review 2026-09-16","Added from review",IF(C50="","New",IF(C50=D50,"","Changed")))) -> Changed | N50: =TRIM(SUBSTITUTE(SUBSTITUTE(SUBSTITUTE(" "&TRIM(SUBSTITUTE(SUBSTITUTE(SUBSTITUTE(SUBSTITUTE(SUBSTITUTE(SUBSTITUTE(SUBSTITUTE(SUBSTITUTE(SUBSTITUTE(SUBSTITUTE(SUBSTITUTE(SUBSTITUTE(SUBSTITUTE(SUBSTITUTE(SUBSTITUTE(UPPER(TRIM(A50)),"[MEMBER]",""),"{MEMBER}",""),"[MEMBER}",""),"MEMBER]",""),"(A)",""),"""",""),"“",""),"”",""),".",""),":",""),",",""),"–"," "),"-"," "),"/"," "),"&"," AND "))&" "," THE "," ")," TOTAL "," ")," OPERATIONS "," ")) -> AMERICAS (NON US) | O50: =IF(COUNTIFS($N$2:$N$2000,N50,$D$2:$D$2000,"<>"&D50)>0,"CONFLICT","") | P50: Excludes US
A51: Americas - Other | B51: final | C51: Americas | D51: AMER (Americas) | E51: Residual | F51: =IF($D51="","",IFERROR(IF(INDEX(Hierarchy!$B$2:$B$1295,MATCH($D51,Hierarchy!$A$2:$A$1295,0))="","",INDEX(Hierarchy!$B$2:$B$1295,MATCH($D51,Hierarchy!$A$2:$A$1295,0))),"NODE NOT FOUND")) -> Region | G51: =IF($D51="","",IFERROR(IF(INDEX(Hierarchy!$D$2:$D$1295,MATCH($D51,Hierarchy!$A$2:$A$1295,0))="","",INDEX(Hierarchy!$D$2:$D$1295,MATCH($D51,Hierarchy!$A$2:$A$1295,0))),"NODE NOT FOUND")) -> AMER | H51: =IF($D51="","",IFERROR(IF(INDEX(Hierarchy!$E$2:$E$1295,MATCH($D51,Hierarchy!$A$2:$A$1295,0))="","",INDEX(Hierarchy!$E$2:$E$1295,MATCH($D51,Hierarchy!$A$2:$A$1295,0))),"NODE NOT FOUND")) | I51: =IF($D51="","",IFERROR(IF(INDEX(Hierarchy!$F$2:$F$1295,MATCH($D51,Hierarchy!$A$2:$A$1295,0))="","",INDEX(Hierarchy!$F$2:$F$1295,MATCH($D51,Hierarchy!$A$2:$A$1295,0))),"NODE NOT FOUND")) | J51: =IF($D51="","",IFERROR(IF(INDEX(Hierarchy!$G$2:$G$1295,MATCH($D51,Hierarchy!$A$2:$A$1295,0))="","",INDEX(Hierarchy!$G$2:$G$1295,MATCH($D51,Hierarchy!$A$2:$A$1295,0))),"NODE NOT FOUND")) | K51: =IF($D51="","",IFERROR(IF(INDEX(Hierarchy!$H$2:$H$1295,MATCH($D51,Hierarchy!$A$2:$A$1295,0))="","",INDEX(Hierarchy!$H$2:$H$1295,MATCH($D51,Hierarchy!$A$2:$A$1295,0))),"NODE NOT FOUND")) | L51: =IF($D51="","",IFERROR(IF(INDEX(Hierarchy!$I$2:$I$1295,MATCH($D51,Hierarchy!$A$2:$A$1295,0))="","",INDEX(Hierarchy!$I$2:$I$1295,MATCH($D51,Hierarchy!$A$2:$A$1295,0))),"NODE NOT FOUND")) | M51: =IF(B51="Pre-seeded","Pre-seeded",IF(B51="Review 2026-09-16","Added from review",IF(C51="","New",IF(C51=D51,"","Changed")))) -> Changed | N51: =TRIM(SUBSTITUTE(SUBSTITUTE(SUBSTITUTE(" "&TRIM(SUBSTITUTE(SUBSTITUTE(SUBSTITUTE(SUBSTITUTE(SUBSTITUTE(SUBSTITUTE(SUBSTITUTE(SUBSTITUTE(SUBSTITUTE(SUBSTITUTE(SUBSTITUTE(SUBSTITUTE(SUBSTITUTE(SUBSTITUTE(SUBSTITUTE(UPPER(TRIM(A51)),"[MEMBER]",""),"{MEMBER}",""),"[MEMBER}",""),"MEMBER]",""),"(A)",""),"""",""),"“",""),"”",""),".",""),":",""),",",""),"–"," "),"-"," "),"/"," "),"&"," AND "))&" "," THE "," ")," TOTAL "," ")," OPERATIONS "," ")) -> AMERICAS OTHER | O51: =IF(COUNTIFS($N$2:$N$2000,N51,$D$2:$D$2000,"<>"&D51)>0,"CONFLICT","")
A52: Americas - U.S. | B52: final | C52: Americas | D52: United States | E52: Exact | F52: =IF($D52="","",IFERROR(IF(INDEX(Hierarchy!$B$2:$B$1295,MATCH($D52,Hierarchy!$A$2:$A$1295,0))="","",INDEX(Hierarchy!$B$2:$B$1295,MATCH($D52,Hierarchy!$A$2:$A$1295,0))),"NODE NOT FOUND")) -> Country | G52: =IF($D52="","",IFERROR(IF(INDEX(Hierarchy!$D$2:$D$1295,MATCH($D52,Hierarchy!$A$2:$A$1295,0))="","",INDEX(Hierarchy!$D$2:$D$1295,MATCH($D52,Hierarchy!$A$2:$A$1295,0))),"NODE NOT FOUND")) -> AMER | H52: =IF($D52="","",IFERROR(IF(INDEX(Hierarchy!$E$2:$E$1295,MATCH($D52,Hierarchy!$A$2:$A$1295,0))="","",INDEX(Hierarchy!$E$2:$E$1295,MATCH($D52,Hierarchy!$A$2:$A$1295,0))),"NODE NOT FOUND")) -> North America (NORAM) | I52: =IF($D52="","",IFERROR(IF(INDEX(Hierarchy!$F$2:$F$1295,MATCH($D52,Hierarchy!$A$2:$A$1295,0))="","",INDEX(Hierarchy!$F$2:$F$1295,MATCH($D52,Hierarchy!$A$2:$A$1295,0))),"NODE NOT FOUND")) -> United States | J52: =IF($D52="","",IFERROR(IF(INDEX(Hierarchy!$G$2:$G$1295,MATCH($D52,Hierarchy!$A$2:$A$1295,0))="","",INDEX(Hierarchy!$G$2:$G$1295,MATCH($D52,Hierarchy!$A$2:$A$1295,0))),"NODE NOT FOUND")) -> USA | K52: =IF($D52="","",IFERROR(IF(INDEX(Hierarchy!$H$2:$H$1295,MATCH($D52,Hierarchy!$A$2:$A$1295,0))="","",INDEX(Hierarchy!$H$2:$H$1295,MATCH($D52,Hierarchy!$A$2:$A$1295,0))),"NODE NOT FOUND")) | L52: =IF($D52="","",IFERROR(IF(INDEX(Hierarchy!$I$2:$I$1295,MATCH($D52,Hierarchy!$A$2:$A$1295,0))="","",INDEX(Hierarchy!$I$2:$I$1295,MATCH($D52,Hierarchy!$A$2:$A$1295,0))),"NODE NOT FOUND")) | M52: =IF(B52="Pre-seeded","Pre-seeded",IF(B52="Review 2026-09-16","Added from review",IF(C52="","New",IF(C52=D52,"","Changed")))) -> Changed | N52: =TRIM(SUBSTITUTE(SUBSTITUTE(SUBSTITUTE(" "&TRIM(SUBSTITUTE(SUBSTITUTE(SUBSTITUTE(SUBSTITUTE(SUBSTITUTE(SUBSTITUTE(SUBSTITUTE(SUBSTITUTE(SUBSTITUTE(SUBSTITUTE(SUBSTITUTE(SUBSTITUTE(SUBSTITUTE(SUBSTITUTE(SUBSTITUTE(UPPER(TRIM(A52)),"[MEMBER]",""),"{MEMBER}",""),"[MEMBER}",""),"MEMBER]",""),"(A)",""),"""",""),"“",""),"”",""),".",""),":",""),",",""),"–"," "),"-"," "),"/"," "),"&"," AND "))&" "," THE "," ")," TOTAL "," ")," OPERATIONS "," ")) -> AMERICAS US | O52: =IF(COUNTIFS($N$2:$N$2000,N52,$D$2:$D$2000,"<>"&D52)>0,"CONFLICT","") | P52: Was Americas; label is the US line within Americas
A53: Americas - United States | B53: final | C53: United States | D53: United States | E53: Exact | F53: =IF($D53="","",IFERROR(IF(INDEX(Hierarchy!$B$2:$B$1295,MATCH($D53,Hierarchy!$A$2:$A$1295,0))="","",INDEX(Hierarchy!$B$2:$B$1295,MATCH($D53,Hierarchy!$A$2:$A$1295,0))),"NODE NOT FOUND")) -> Country | G53: =IF($D53="","",IFERROR(IF(INDEX(Hierarchy!$D$2:$D$1295,MATCH($D53,Hierarchy!$A$2:$A$1295,0))="","",INDEX(Hierarchy!$D$2:$D$1295,MATCH($D53,Hierarchy!$A$2:$A$1295,0))),"NODE NOT FOUND")) -> AMER | H53: =IF($D53="","",IFERROR(IF(INDEX(Hierarchy!$E$2:$E$1295,MATCH($D53,Hierarchy!$A$2:$A$1295,0))="","",INDEX(Hierarchy!$E$2:$E$1295,MATCH($D53,Hierarchy!$A$2:$A$1295,0))),"NODE NOT FOUND")) -> North America (NORAM) | I53: =IF($D53="","",IFERROR(IF(INDEX(Hierarchy!$F$2:$F$1295,MATCH($D53,Hierarchy!$A$2:$A$1295,0))="","",INDEX(Hierarchy!$F$2:$F$1295,MATCH($D53,Hierarchy!$A$2:$A$1295,0))),"NODE NOT FOUND")) -> United States | J53: =IF($D53="","",IFERROR(IF(INDEX(Hierarchy!$G$2:$G$1295,MATCH($D53,Hierarchy!$A$2:$A$1295,0))="","",INDEX(Hierarchy!$G$2:$G$1295,MATCH($D53,Hierarchy!$A$2:$A$1295,0))),"NODE NOT FOUND")) -> USA | K53: =IF($D53="","",IFERROR(IF(INDEX(Hierarchy!$H$2:$H$1295,MATCH($D53,Hierarchy!$A$2:$A$1295,0))="","",INDEX(Hierarchy!$H$2:$H$1295,MATCH($D53,Hierarchy!$A$2:$A$1295,0))),"NODE NOT FOUND")) | L53: =IF($D53="","",IFERROR(IF(INDEX(Hierarchy!$I$2:$I$1295,MATCH($D53,Hierarchy!$A$2:$A$1295,0))="","",INDEX(Hierarchy!$I$2:$I$1295,MATCH($D53,Hierarchy!$A$2:$A$1295,0))),"NODE NOT FOUND")) | M53: =IF(B53="Pre-seeded","Pre-seeded",IF(B53="Review 2026-09-16","Added from review",IF(C53="","New",IF(C53=D53,"","Changed")))) | N53: =TRIM(SUBSTITUTE(SUBSTITUTE(SUBSTITUTE(" "&TRIM(SUBSTITUTE(SUBSTITUTE(SUBSTITUTE(SUBSTITUTE(SUBSTITUTE(SUBSTITUTE(SUBSTITUTE(SUBSTITUTE(SUBSTITUTE(SUBSTITUTE(SUBSTITUTE(SUBSTITUTE(SUBSTITUTE(SUBSTITUTE(SUBSTITUTE(UPPER(TRIM(A53)),"[MEMBER]",""),"{MEMBER}",""),"[MEMBER}",""),"MEMBER]",""),"(A)",""),"""",""),"“",""),"”",""),".",""),":",""),",",""),"–"," "),"-"," "),"/"," "),"&"," AND "))&" "," THE "," ")," TOTAL "," ")," OPERATIONS "," ")) -> AMERICAS UNITED STATES | O53: =IF(COUNTIFS($N$2:$N$2000,N53,$D$2:$D$2000,"<>"&D53)>0,"CONFLICT","")
A54: Americas and APAC | B54: Pre-seeded | D54: Americas and APAC | E54: Exact | F54: =IF($D54="","",IFERROR(IF(INDEX(Hierarchy!$B$2:$B$1295,MATCH($D54,Hierarchy!$A$2:$A$1295,0))="","",INDEX(Hierarchy!$B$2:$B$1295,MATCH($D54,Hierarchy!$A$2:$A$1295,0))),"NODE NOT FOUND")) -> Multi-region | G54: =IF($D54="","",IFERROR(IF(INDEX(Hierarchy!$D$2:$D$1295,MATCH($D54,Hierarchy!$A$2:$A$1295,0))="","",INDEX(Hierarchy!$D$2:$D$1295,MATCH($D54,Hierarchy!$A$2:$A$1295,0))),"NODE NOT FOUND")) -> Multi-region | H54: =IF($D54="","",IFERROR(IF(INDEX(Hierarchy!$E$2:$E$1295,MATCH($D54,Hierarchy!$A$2:$A$1295,0))="","",INDEX(Hierarchy!$E$2:$E$1295,MATCH($D54,Hierarchy!$A$2:$A$1295,0))),"NODE NOT FOUND")) | I54: =IF($D54="","",IFERROR(IF(INDEX(Hierarchy!$F$2:$F$1295,MATCH($D54,Hierarchy!$A$2:$A$1295,0))="","",INDEX(Hierarchy!$F$2:$F$1295,MATCH($D54,Hierarchy!$A$2:$A$1295,0))),"NODE NOT FOUND")) | J54: =IF($D54="","",IFERROR(IF(INDEX(Hierarchy!$G$2:$G$1295,MATCH($D54,Hierarchy!$A$2:$A$1295,0))="","",INDEX(Hierarchy!$G$2:$G$1295,MATCH($D54,Hierarchy!$A$2:$A$1295,0))),"NODE NOT FOUND")) | K54: =IF($D54="","",IFERROR(IF(INDEX(Hierarchy!$H$2:$H$1295,MATCH($D54,Hierarchy!$A$2:$A$1295,0))="","",INDEX(Hierarchy!$H$2:$H$1295,MATCH($D54,Hierarchy!$A$2:$A$1295,0))),"NODE NOT FOUND")) | L54: =IF($D54="","",IFERROR(IF(INDEX(Hierarchy!$I$2:$I$1295,MATCH($D54,Hierarchy!$A$2:$A$1295,0))="","",INDEX(Hierarchy!$I$2:$I$1295,MATCH($D54,Hierarchy!$A$2:$A$1295,0))),"NODE NOT FOUND")) | M54: =IF(B54="Pre-seeded","Pre-seeded",IF(B54="Review 2026-09-16","Added from review",IF(C54="","New",IF(C54=D54,"","Changed")))) -> Pre-seeded | N54: =TRIM(SUBSTITUTE(SUBSTITUTE(SUBSTITUTE(" "&TRIM(SUBSTITUTE(SUBSTITUTE(SUBSTITUTE(SUBSTITUTE(SUBSTITUTE(SUBSTITUTE(SUBSTITUTE(SUBSTITUTE(SUBSTITUTE(SUBSTITUTE(SUBSTITUTE(SUBSTITUTE(SUBSTITUTE(SUBSTITUTE(SUBSTITUTE(UPPER(TRIM(A54)),"[MEMBER]",""),"{MEMBER}",""),"[MEMBER}",""),"MEMBER]",""),"(A)",""),"""",""),"“",""),"”",""),".",""),":",""),",",""),"–"," "),"-"," "),"/"," "),"&"," AND "))&" "," THE "," ")," TOTAL "," ")," OPERATIONS "," ")) -> AMERICAS AND APAC | O54: =IF(COUNTIFS($N$2:$N$2000,N54,$D$2:$D$2000,"<>"&D54)>0,"CONFLICT","")
A55: Americas and EMEA | B55: Pre-seeded | D55: Americas and EMEA | E55: Exact | F55: =IF($D55="","",IFERROR(IF(INDEX(Hierarchy!$B$2:$B$1295,MATCH($D55,Hierarchy!$A$2:$A$1295,0))="","",INDEX(Hierarchy!$B$2:$B$1295,MATCH($D55,Hierarchy!$A$2:$A$1295,0))),"NODE NOT FOUND")) -> Multi-region | G55: =IF($D55="","",IFERROR(IF(INDEX(Hierarchy!$D$2:$D$1295,MATCH($D55,Hierarchy!$A$2:$A$1295,0))="","",INDEX(Hierarchy!$D$2:$D$1295,MATCH($D55,Hierarchy!$A$2:$A$1295,0))),"NODE NOT FOUND")) -> Multi-region | H55: =IF($D55="","",IFERROR(IF(INDEX(Hierarchy!$E$2:$E$1295,MATCH($D55,Hierarchy!$A$2:$A$1295,0))="","",INDEX(Hierarchy!$E$2:$E$1295,MATCH($D55,Hierarchy!$A$2:$A$1295,0))),"NODE NOT FOUND")) | I55: =IF($D55="","",IFERROR(IF(INDEX(Hierarchy!$F$2:$F$1295,MATCH($D55,Hierarchy!$A$2:$A$1295,0))="","",INDEX(Hierarchy!$F$2:$F$1295,MATCH($D55,Hierarchy!$A$2:$A$1295,0))),"NODE NOT FOUND")) | J55: =IF($D55="","",IFERROR(IF(INDEX(Hierarchy!$G$2:$G$1295,MATCH($D55,Hierarchy!$A$2:$A$1295,0))="","",INDEX(Hierarchy!$G$2:$G$1295,MATCH($D55,Hierarchy!$A$2:$A$1295,0))),"NODE NOT FOUND")) | K55: =IF($D55="","",IFERROR(IF(INDEX(Hierarchy!$H$2:$H$1295,MATCH($D55,Hierarchy!$A$2:$A$1295,0))="","",INDEX(Hierarchy!$H$2:$H$1295,MATCH($D55,Hierarchy!$A$2:$A$1295,0))),"NODE NOT FOUND")) | L55: =IF($D55="","",IFERROR(IF(INDEX(Hierarchy!$I$2:$I$1295,MATCH($D55,Hierarchy!$A$2:$A$1295,0))="","",INDEX(Hierarchy!$I$2:$I$1295,MATCH($D55,Hierarchy!$A$2:$A$1295,0))),"NODE NOT FOUND")) | M55: =IF(B55="Pre-seeded","Pre-seeded",IF(B55="Review 2026-09-16","Added from review",IF(C55="","New",IF(C55=D55,"","Changed")))) -> Pre-seeded | N55: =TRIM(SUBSTITUTE(SUBSTITUTE(SUBSTITUTE(" "&TRIM(SUBSTITUTE(SUBSTITUTE(SUBSTITUTE(SUBSTITUTE(SUBSTITUTE(SUBSTITUTE(SUBSTITUTE(SUBSTITUTE(SUBSTITUTE(SUBSTITUTE(SUBSTITUTE(SUBSTITUTE(SUBSTITUTE(SUBSTITUTE(SUBSTITUTE(UPPER(TRIM(A55)),"[MEMBER]",""),"{MEMBER}",""),"[MEMBER}",""),"MEMBER]",""),"(A)",""),"""",""),"“",""),"”",""),".",""),":",""),",",""),"–"," "),"-"," "),"/"," "),"&"," AND "))&" "," THE "," ")," TOTAL "," ")," OPERATIONS "," ")) -> AMERICAS AND EMEA | O55: =IF(COUNTIFS($N$2:$N$2000,N55,$D$2:$D$2000,"<>"&D55)>0,"CONFLICT","")
A56: Americas and Europe | B56: Pre-seeded | D56: Multi-region (Other) | E56: Combined | F56: =IF($D56="","",IFERROR(IF(INDEX(Hierarchy!$B$2:$B$1295,MATCH($D56,Hierarchy!$A$2:$A$1295,0))="","",INDEX(Hierarchy!$B$2:$B$1295,MATCH($D56,Hierarchy!$A$2:$A$1295,0))),"NODE NOT FOUND")) -> Multi-region | G56: =IF($D56="","",IFERROR(IF(INDEX(Hierarchy!$D$2:$D$1295,MATCH($D56,Hierarchy!$A$2:$A$1295,0))="","",INDEX(Hierarchy!$D$2:$D$1295,MATCH($D56,Hierarchy!$A$2:$A$1295,0))),"NODE NOT FOUND")) -> Multi-region | H56: =IF($D56="","",IFERROR(IF(INDEX(Hierarchy!$E$2:$E$1295,MATCH($D56,Hierarchy!$A$2:$A$1295,0))="","",INDEX(Hierarchy!$E$2:$E$1295,MATCH($D56,Hierarchy!$A$2:$A$1295,0))),"NODE NOT FOUND")) | I56: =IF($D56="","",IFERROR(IF(INDEX(Hierarchy!$F$2:$F$1295,MATCH($D56,Hierarchy!$A$2:$A$1295,0))="","",INDEX(Hierarchy!$F$2:$F$1295,MATCH($D56,Hierarchy!$A$2:$A$1295,0))),"NODE NOT FOUND")) | J56: =IF($D56="","",IFERROR(IF(INDEX(Hierarchy!$G$2:$G$1295,MATCH($D56,Hierarchy!$A$2:$A$1295,0))="","",INDEX(Hierarchy!$G$2:$G$1295,MATCH($D56,Hierarchy!$A$2:$A$1295,0))),"NODE NOT FOUND")) | K56: =IF($D56="","",IFERROR(IF(INDEX(Hierarchy!$H$2:$H$1295,MATCH($D56,Hierarchy!$A$2:$A$1295,0))="","",INDEX(Hierarchy!$H$2:$H$1295,MATCH($D56,Hierarchy!$A$2:$A$1295,0))),"NODE NOT FOUND")) | L56: =IF($D56="","",IFERROR(IF(INDEX(Hierarchy!$I$2:$I$1295,MATCH($D56,Hierarchy!$A$2:$A$1295,0))="","",INDEX(Hierarchy!$I$2:$I$1295,MATCH($D56,Hierarchy!$A$2:$A$1295,0))),"NODE NOT FOUND")) | M56: =IF(B56="Pre-seeded","Pre-seeded",IF(B56="Review 2026-09-16","Added from review",IF(C56="","New",IF(C56=D56,"","Changed")))) -> Pre-seeded | N56: =TRIM(SUBSTITUTE(SUBSTITUTE(SUBSTITUTE(" "&TRIM(SUBSTITUTE(SUBSTITUTE(SUBSTITUTE(SUBSTITUTE(SUBSTITUTE(SUBSTITUTE(SUBSTITUTE(SUBSTITUTE(SUBSTITUTE(SUBSTITUTE(SUBSTITUTE(SUBSTITUTE(SUBSTITUTE(SUBSTITUTE(SUBSTITUTE(UPPER(TRIM(A56)),"[MEMBER]",""),"{MEMBER}",""),"[MEMBER}",""),"MEMBER]",""),"(A)",""),"""",""),"“",""),"”",""),".",""),":",""),",",""),"–"," "),"-"," "),"/"," "),"&"," AND "))&" "," THE "," ")," TOTAL "," ")," OPERATIONS "," ")) -> AMERICAS AND EUROPE | O56: =IF(COUNTIFS($N$2:$N$2000,N56,$D$2:$D$2000,"<>"&D56)>0,"CONFLICT","")
A57: Americas excluding U.S. | B57: final | C57: Americas | D57: AMER (Americas) | E57: Partial | F57: =IF($D57="","",IFERROR(IF(INDEX(Hierarchy!$B$2:$B$1295,MATCH($D57,Hierarchy!$A$2:$A$1295,0))="","",INDEX(Hierarchy!$B$2:$B$1295,MATCH($D57,Hierarchy!$A$2:$A$1295,0))),"NODE NOT FOUND")) -> Region | G57: =IF($D57="","",IFERROR(IF(INDEX(Hierarchy!$D$2:$D$1295,MATCH($D57,Hierarchy!$A$2:$A$1295,0))="","",INDEX(Hierarchy!$D$2:$D$1295,MATCH($D57,Hierarchy!$A$2:$A$1295,0))),"NODE NOT FOUND")) -> AMER | H57: =IF($D57="","",IFERROR(IF(INDEX(Hierarchy!$E$2:$E$1295,MATCH($D57,Hierarchy!$A$2:$A$1295,0))="","",INDEX(Hierarchy!$E$2:$E$1295,MATCH($D57,Hierarchy!$A$2:$A$1295,0))),"NODE NOT FOUND")) | I57: =IF($D57="","",IFERROR(IF(INDEX(Hierarchy!$F$2:$F$1295,MATCH($D57,Hierarchy!$A$2:$A$1295,0))="","",INDEX(Hierarchy!$F$2:$F$1295,MATCH($D57,Hierarchy!$A$2:$A$1295,0))),"NODE NOT FOUND")) | J57: =IF($D57="","",IFERROR(IF(INDEX(Hierarchy!$G$2:$G$1295,MATCH($D57,Hierarchy!$A$2:$A$1295,0))="","",INDEX(Hierarchy!$G$2:$G$1295,MATCH($D57,Hierarchy!$A$2:$A$1295,0))),"NODE NOT FOUND")) | K57: =IF($D57="","",IFERROR(IF(INDEX(Hierarchy!$H$2:$H$1295,MATCH($D57,Hierarchy!$A$2:$A$1295,0))="","",INDEX(Hierarchy!$H$2:$H$1295,MATCH($D57,Hierarchy!$A$2:$A$1295,0))),"NODE NOT FOUND")) | L57: =IF($D57="","",IFERROR(IF(INDEX(Hierarchy!$I$2:$I$1295,MATCH($D57,Hierarchy!$A$2:$A$1295,0))="","",INDEX(Hierarchy!$I$2:$I$1295,MATCH($D57,Hierarchy!$A$2:$A$1295,0))),"NODE NOT FOUND")) | M57: =IF(B57="Pre-seeded","Pre-seeded",IF(B57="Review 2026-09-16","Added from review",IF(C57="","New",IF(C57=D57,"","Changed")))) -> Changed | N57: =TRIM(SUBSTITUTE(SUBSTITUTE(SUBSTITUTE(" "&TRIM(SUBSTITUTE(SUBSTITUTE(SUBSTITUTE(SUBSTITUTE(SUBSTITUTE(SUBSTITUTE(SUBSTITUTE(SUBSTITUTE(SUBSTITUTE(SUBSTITUTE(SUBSTITUTE(SUBSTITUTE(SUBSTITUTE(SUBSTITUTE(SUBSTITUTE(UPPER(TRIM(A57)),"[MEMBER]",""),"{MEMBER}",""),"[MEMBER}",""),"MEMBER]",""),"(A)",""),"""",""),"“",""),"”",""),".",""),":",""),",",""),"–"," "),"-"," "),"/"," "),"&"," AND "))&" "," THE "," ")," TOTAL "," ")," OPERATIONS "," ")) -> AMERICAS EXCLUDING US | O57: =IF(COUNTIFS($N$2:$N$2000,N57,$D$2:$D$2000,"<>"&D57)>0,"CONFLICT","") | P57: Excludes US
A58: Anambra | B58: Pre-seeded | D58: Anambra | E58: Exact | F58: =IF($D58="","",IFERROR(IF(INDEX(Hierarchy!$B$2:$B$1295,MATCH($D58,Hierarchy!$A$2:$A$1295,0))="","",INDEX(Hierarchy!$B$2:$B$1295,MATCH($D58,Hierarchy!$A$2:$A$1295,0))),"NODE NOT FOUND")) -> State/Province | G58: =IF($D58="","",IFERROR(IF(INDEX(Hierarchy!$D$2:$D$1295,MATCH($D58,Hierarchy!$A$2:$A$1295,0))="","",INDEX(Hierarchy!$D$2:$D$1295,MATCH($D58,Hierarchy!$A$2:$A$1295,0))),"NODE NOT FOUND")) -> EMEA | H58: =IF($D58="","",IFERROR(IF(INDEX(Hierarchy!$E$2:$E$1295,MATCH($D58,Hierarchy!$A$2:$A$1295,0))="","",INDEX(Hierarchy!$E$2:$E$1295,MATCH($D58,Hierarchy!$A$2:$A$1295,0))),"NODE NOT FOUND")) -> Africa | I58: =IF($D58="","",IFERROR(IF(INDEX(Hierarchy!$F$2:$F$1295,MATCH($D58,Hierarchy!$A$2:$A$1295,0))="","",INDEX(Hierarchy!$F$2:$F$1295,MATCH($D58,Hierarchy!$A$2:$A$1295,0))),"NODE NOT FOUND")) -> Nigeria | J58: =IF($D58="","",IFERROR(IF(INDEX(Hierarchy!$G$2:$G$1295,MATCH($D58,Hierarchy!$A$2:$A$1295,0))="","",INDEX(Hierarchy!$G$2:$G$1295,MATCH($D58,Hierarchy!$A$2:$A$1295,0))),"NODE NOT FOUND")) -> NGA | K58: =IF($D58="","",IFERROR(IF(INDEX(Hierarchy!$H$2:$H$1295,MATCH($D58,Hierarchy!$A$2:$A$1295,0))="","",INDEX(Hierarchy!$H$2:$H$1295,MATCH($D58,Hierarchy!$A$2:$A$1295,0))),"NODE NOT FOUND")) -> Anambra | L58: =IF($D58="","",IFERROR(IF(INDEX(Hierarchy!$I$2:$I$1295,MATCH($D58,Hierarchy!$A$2:$A$1295,0))="","",INDEX(Hierarchy!$I$2:$I$1295,MATCH($D58,Hierarchy!$A$2:$A$1295,0))),"NODE NOT FOUND")) | M58: =IF(B58="Pre-seeded","Pre-seeded",IF(B58="Review 2026-09-16","Added from review",IF(C58="","New",IF(C58=D58,"","Changed")))) -> Pre-seeded | N58: =TRIM(SUBSTITUTE(SUBSTITUTE(SUBSTITUTE(" "&TRIM(SUBSTITUTE(SUBSTITUTE(SUBSTITUTE(SUBSTITUTE(SUBSTITUTE(SUBSTITUTE(SUBSTITUTE(SUBSTITUTE(SUBSTITUTE(SUBSTITUTE(SUBSTITUTE(SUBSTITUTE(SUBSTITUTE(SUBSTITUTE(SUBSTITUTE(UPPER(TRIM(A58)),"[MEMBER]",""),"{MEMBER}",""),"[MEMBER}",""),"MEMBER]",""),"(A)",""),"""",""),"“",""),"”",""),".",""),":",""),",",""),"–"," "),"-"," "),"/"," "),"&"," AND "))&" "," THE "," ")," TOTAL "," ")," OPERATIONS "," ")) -> ANAMBRA | O58: =IF(COUNTIFS($N$2:$N$2000,N58,$D$2:$D$2000,"<>"&D58)>0,"CONFLICT","")
A59: Andalucía | B59: Pre-seeded | D59: Andalusia | E59: Exact | F59: =IF($D59="","",IFERROR(IF(INDEX(Hierarchy!$B$2:$B$1295,MATCH($D59,Hierarchy!$A$2:$A$1295,0))="","",INDEX(Hierarchy!$B$2:$B$1295,MATCH($D59,Hierarchy!$A$2:$A$1295,0))),"NODE NOT FOUND")) -> State/Province | G59: =IF($D59="","",IFERROR(IF(INDEX(Hierarchy!$D$2:$D$1295,MATCH($D59,Hierarchy!$A$2:$A$1295,0))="","",INDEX(Hierarchy!$D$2:$D$1295,MATCH($D59,Hierarchy!$A$2:$A$1295,0))),"NODE NOT FOUND")) -> EMEA | H59: =IF($D59="","",IFERROR(IF(INDEX(Hierarchy!$E$2:$E$1295,MATCH($D59,Hierarchy!$A$2:$A$1295,0))="","",INDEX(Hierarchy!$E$2:$E$1295,MATCH($D59,Hierarchy!$A$2:$A$1295,0))),"NODE NOT FOUND")) -> Europe | I59: =IF($D59="","",IFERROR(IF(INDEX(Hierarchy!$F$2:$F$1295,MATCH($D59,Hierarchy!$A$2:$A$1295,0))="","",INDEX(Hierarchy!$F$2:$F$1295,MATCH($D59,Hierarchy!$A$2:$A$1295,0))),"NODE NOT FOUND")) -> Spain | J59: =IF($D59="","",IFERROR(IF(INDEX(Hierarchy!$G$2:$G$1295,MATCH($D59,Hierarchy!$A$2:$A$1295,0))="","",INDEX(Hierarchy!$G$2:$G$1295,MATCH($D59,Hierarchy!$A$2:$A$1295,0))),"NODE NOT FOUND")) -> ESP | K59: =IF($D59="","",IFERROR(IF(INDEX(Hierarchy!$H$2:$H$1295,MATCH($D59,Hierarchy!$A$2:$A$1295,0))="","",INDEX(Hierarchy!$H$2:$H$1295,MATCH($D59,Hierarchy!$A$2:$A$1295,0))),"NODE NOT FOUND")) -> Andalusia | L59: =IF($D59="","",IFERROR(IF(INDEX(Hierarchy!$I$2:$I$1295,MATCH($D59,Hierarchy!$A$2:$A$1295,0))="","",INDEX(Hierarchy!$I$2:$I$1295,MATCH($D59,Hierarchy!$A$2:$A$1295,0))),"NODE NOT FOUND")) | M59: =IF(B59="Pre-seeded","Pre-seeded",IF(B59="Review 2026-09-16","Added from review",IF(C59="","New",IF(C59=D59,"","Changed")))) -> Pre-seeded | N59: =TRIM(SUBSTITUTE(SUBSTITUTE(SUBSTITUTE(" "&TRIM(SUBSTITUTE(SUBSTITUTE(SUBSTITUTE(SUBSTITUTE(SUBSTITUTE(SUBSTITUTE(SUBSTITUTE(SUBSTITUTE(SUBSTITUTE(SUBSTITUTE(SUBSTITUTE(SUBSTITUTE(SUBSTITUTE(SUBSTITUTE(SUBSTITUTE(UPPER(TRIM(A59)),"[MEMBER]",""),"{MEMBER}",""),"[MEMBER}",""),"MEMBER]",""),"(A)",""),"""",""),"“",""),"”",""),".",""),":",""),",",""),"–"," "),"-"," "),"/"," "),"&"," AND "))&" "," THE "," ")," TOTAL "," ")," OPERATIONS "," ")) -> ANDALUCÍA | O59: =IF(COUNTIFS($N$2:$N$2000,N59,$D$2:$D$2000,"<>"&D59)>0,"CONFLICT","")
A60: Andalusia | B60: Pre-seeded | D60: Andalusia | E60: Exact | F60: =IF($D60="","",IFERROR(IF(INDEX(Hierarchy!$B$2:$B$1295,MATCH($D60,Hierarchy!$A$2:$A$1295,0))="","",INDEX(Hierarchy!$B$2:$B$1295,MATCH($D60,Hierarchy!$A$2:$A$1295,0))),"NODE NOT FOUND")) -> State/Province | G60: =IF($D60="","",IFERROR(IF(INDEX(Hierarchy!$D$2:$D$1295,MATCH($D60,Hierarchy!$A$2:$A$1295,0))="","",INDEX(Hierarchy!$D$2:$D$1295,MATCH($D60,Hierarchy!$A$2:$A$1295,0))),"NODE NOT FOUND")) -> EMEA | H60: =IF($D60="","",IFERROR(IF(INDEX(Hierarchy!$E$2:$E$1295,MATCH($D60,Hierarchy!$A$2:$A$1295,0))="","",INDEX(Hierarchy!$E$2:$E$1295,MATCH($D60,Hierarchy!$A$2:$A$1295,0))),"NODE NOT FOUND")) -> Europe | I60: =IF($D60="","",IFERROR(IF(INDEX(Hierarchy!$F$2:$F$1295,MATCH($D60,Hierarchy!$A$2:$A$1295,0))="","",INDEX(Hierarchy!$F$2:$F$1295,MATCH($D60,Hierarchy!$A$2:$A$1295,0))),"NODE NOT FOUND")) -> Spain | J60: =IF($D60="","",IFERROR(IF(INDEX(Hierarchy!$G$2:$G$1295,MATCH($D60,Hierarchy!$A$2:$A$1295,0))="","",INDEX(Hierarchy!$G$2:$G$1295,MATCH($D60,Hierarchy!$A$2:$A$1295,0))),"NODE NOT FOUND")) -> ESP | K60: =IF($D60="","",IFERROR(IF(INDEX(Hierarchy!$H$2:$H$1295,MATCH($D60,Hierarchy!$A$2:$A$1295,0))="","",INDEX(Hierarchy!$H$2:$H$1295,MATCH($D60,Hierarchy!$A$2:$A$1295,0))),"NODE NOT FOUND")) -> Andalusia | L60: =IF($D60="","",IFERROR(IF(INDEX(Hierarchy!$I$2:$I$1295,MATCH($D60,Hierarchy!$A$2:$A$1295,0))="","",INDEX(Hierarchy!$I$2:$I$1295,MATCH($D60,Hierarchy!$A$2:$A$1295,0))),"NODE NOT FOUND")) | M60: =IF(B60="Pre-seeded","Pre-seeded",IF(B60="Review 2026-09-16","Added from review",IF(C60="","New",IF(C60=D60,"","Changed")))) -> Pre-seeded | N60: =TRIM(SUBSTITUTE(SUBSTITUTE(SUBSTITUTE(" "&TRIM(SUBSTITUTE(SUBSTITUTE(SUBSTITUTE(SUBSTITUTE(SUBSTITUTE(SUBSTITUTE(SUBSTITUTE(SUBSTITUTE(SUBSTITUTE(SUBSTITUTE(SUBSTITUTE(SUBSTITUTE(SUBSTITUTE(SUBSTITUTE(SUBSTITUTE(UPPER(TRIM(A60)),"[MEMBER]",""),"{MEMBER}",""),"[MEMBER}",""),"MEMBER]",""),"(A)",""),"""",""),"“",""),"”",""),".",""),":",""),",",""),"–"," "),"-"," "),"/"," "),"&"," AND "))&" "," THE "," ")," TOTAL "," ")," OPERATIONS "," ")) -> ANDALUSIA | O60: =IF(COUNTIFS($N$2:$N$2000,N60,$D$2:$D$2000,"<>"&D60)>0,"CONFLICT","")
A61: Andaman and Nicobar Islands | B61: Pre-seeded | D61: Andaman and Nicobar Islands | E61: Exact | F61: =IF($D61="","",IFERROR(IF(INDEX(Hierarchy!$B$2:$B$1295,MATCH($D61,Hierarchy!$A$2:$A$1295,0))="","",INDEX(Hierarchy!$B$2:$B$1295,MATCH($D61,Hierarchy!$A$2:$A$1295,0))),"NODE NOT FOUND")) -> State/Province | G61: =IF($D61="","",IFERROR(IF(INDEX(Hierarchy!$D$2:$D$1295,MATCH($D61,Hierarchy!$A$2:$A$1295,0))="","",INDEX(Hierarchy!$D$2:$D$1295,MATCH($D61,Hierarchy!$A$2:$A$1295,0))),"NODE NOT FOUND")) -> APAC | H61: =IF($D61="","",IFERROR(IF(INDEX(Hierarchy!$E$2:$E$1295,MATCH($D61,Hierarchy!$A$2:$A$1295,0))="","",INDEX(Hierarchy!$E$2:$E$1295,MATCH($D61,Hierarchy!$A$2:$A$1295,0))),"NODE NOT FOUND")) -> South Asia | I61: =IF($D61="","",IFERROR(IF(INDEX(Hierarchy!$F$2:$F$1295,MATCH($D61,Hierarchy!$A$2:$A$1295,0))="","",INDEX(Hierarchy!$F$2:$F$1295,MATCH($D61,Hierarchy!$A$2:$A$1295,0))),"NODE NOT FOUND")) -> India | J61: =IF($D61="","",IFERROR(IF(INDEX(Hierarchy!$G$2:$G$1295,MATCH($D61,Hierarchy!$A$2:$A$1295,0))="","",INDEX(Hierarchy!$G$2:$G$1295,MATCH($D61,Hierarchy!$A$2:$A$1295,0))),"NODE NOT FOUND")) -> IND | K61: =IF($D61="","",IFERROR(IF(INDEX(Hierarchy!$H$2:$H$1295,MATCH($D61,Hierarchy!$A$2:$A$1295,0))="","",INDEX(Hierarchy!$H$2:$H$1295,MATCH($D61,Hierarchy!$A$2:$A$1295,0))),"NODE NOT FOUND")) -> Andaman and Nicobar Islands | L61: =IF($D61="","",IFERROR(IF(INDEX(Hierarchy!$I$2:$I$1295,MATCH($D61,Hierarchy!$A$2:$A$1295,0))="","",INDEX(Hierarchy!$I$2:$I$1295,MATCH($D61,Hierarchy!$A$2:$A$1295,0))),"NODE NOT FOUND")) | M61: =IF(B61="Pre-seeded","Pre-seeded",IF(B61="Review 2026-09-16","Added from review",IF(C61="","New",IF(C61=D61,"","Changed")))) -> Pre-seeded | N61: =TRIM(SUBSTITUTE(SUBSTITUTE(SUBSTITUTE(" "&TRIM(SUBSTITUTE(SUBSTITUTE(SUBSTITUTE(SUBSTITUTE(SUBSTITUTE(SUBSTITUTE(SUBSTITUTE(SUBSTITUTE(SUBSTITUTE(SUBSTITUTE(SUBSTITUTE(SUBSTITUTE(SUBSTITUTE(SUBSTITUTE(SUBSTITUTE(UPPER(TRIM(A61)),"[MEMBER]",""),"{MEMBER}",""),"[MEMBER}",""),"MEMBER]",""),"(A)",""),"""",""),"“",""),"”",""),".",""),":",""),",",""),"–"," "),"-"," "),"/"," "),"&"," AND "))&" "," THE "," ")," TOTAL "," ")," OPERATIONS "," ")) -> ANDAMAN AND NICOBAR ISLANDS | O61: =IF(COUNTIFS($N$2:$N$2000,N61,$D$2:$D$2000,"<>"&D61)>0,"CONFLICT","")
A62: Andean | B62: Pre-seeded | D62: Andean Region | E62: Exact | F62: =IF($D62="","",IFERROR(IF(INDEX(Hierarchy!$B$2:$B$1295,MATCH($D62,Hierarchy!$A$2:$A$1295,0))="","",INDEX(Hierarchy!$B$2:$B$1295,MATCH($D62,Hierarchy!$A$2:$A$1295,0))),"NODE NOT FOUND")) -> Sub-region component | G62: =IF($D62="","",IFERROR(IF(INDEX(Hierarchy!$D$2:$D$1295,MATCH($D62,Hierarchy!$A$2:$A$1295,0))="","",INDEX(Hierarchy!$D$2:$D$1295,MATCH($D62,Hierarchy!$A$2:$A$1295,0))),"NODE NOT FOUND")) -> AMER | H62: =IF($D62="","",IFERROR(IF(INDEX(Hierarchy!$E$2:$E$1295,MATCH($D62,Hierarchy!$A$2:$A$1295,0))="","",INDEX(Hierarchy!$E$2:$E$1295,MATCH($D62,Hierarchy!$A$2:$A$1295,0))),"NODE NOT FOUND")) -> Latin America (LATAM) | I62: =IF($D62="","",IFERROR(IF(INDEX(Hierarchy!$F$2:$F$1295,MATCH($D62,Hierarchy!$A$2:$A$1295,0))="","",INDEX(Hierarchy!$F$2:$F$1295,MATCH($D62,Hierarchy!$A$2:$A$1295,0))),"NODE NOT FOUND")) | J62: =IF($D62="","",IFERROR(IF(INDEX(Hierarchy!$G$2:$G$1295,MATCH($D62,Hierarchy!$A$2:$A$1295,0))="","",INDEX(Hierarchy!$G$2:$G$1295,MATCH($D62,Hierarchy!$A$2:$A$1295,0))),"NODE NOT FOUND")) | K62: =IF($D62="","",IFERROR(IF(INDEX(Hierarchy!$H$2:$H$1295,MATCH($D62,Hierarchy!$A$2:$A$1295,0))="","",INDEX(Hierarchy!$H$2:$H$1295,MATCH($D62,Hierarchy!$A$2:$A$1295,0))),"NODE NOT FOUND")) | L62: =IF($D62="","",IFERROR(IF(INDEX(Hierarchy!$I$2:$I$1295,MATCH($D62,Hierarchy!$A$2:$A$1295,0))="","",INDEX(Hierarchy!$I$2:$I$1295,MATCH($D62,Hierarchy!$A$2:$A$1295,0))),"NODE NOT FOUND")) | M62: =IF(B62="Pre-seeded","Pre-seeded",IF(B62="Review 2026-09-16","Added from review",IF(C62="","New",IF(C62=D62,"","Changed")))) -> Pre-seeded | N62: =TRIM(SUBSTITUTE(SUBSTITUTE(SUBSTITUTE(" "&TRIM(SUBSTITUTE(SUBSTITUTE(SUBSTITUTE(SUBSTITUTE(SUBSTITUTE(SUBSTITUTE(SUBSTITUTE(SUBSTITUTE(SUBSTITUTE(SUBSTITUTE(SUBSTITUTE(SUBSTITUTE(SUBSTITUTE(SUBSTITUTE(SUBSTITUTE(UPPER(TRIM(A62)),"[MEMBER]",""),"{MEMBER}",""),"[MEMBER}",""),"MEMBER]",""),"(A)",""),"""",""),"“",""),"”",""),".",""),":",""),",",""),"–"," "),"-"," "),"/"," "),"&"," AND "))&" "," THE "," ")," TOTAL "," ")," OPERATIONS "," ")) -> ANDEAN | O62: =IF(COUNTIFS($N$2:$N$2000,N62,$D$2:$D$2000,"<>"&D62)>0,"CONFLICT","")
A63: Andean Region | B63: Pre-seeded | D63: Andean Region | E63: Exact | F63: =IF($D63="","",IFERROR(IF(INDEX(Hierarchy!$B$2:$B$1295,MATCH($D63,Hierarchy!$A$2:$A$1295,0))="","",INDEX(Hierarchy!$B$2:$B$1295,MATCH($D63,Hierarchy!$A$2:$A$1295,0))),"NODE NOT FOUND")) -> Sub-region component | G63: =IF($D63="","",IFERROR(IF(INDEX(Hierarchy!$D$2:$D$1295,MATCH($D63,Hierarchy!$A$2:$A$1295,0))="","",INDEX(Hierarchy!$D$2:$D$1295,MATCH($D63,Hierarchy!$A$2:$A$1295,0))),"NODE NOT FOUND")) -> AMER | H63: =IF($D63="","",IFERROR(IF(INDEX(Hierarchy!$E$2:$E$1295,MATCH($D63,Hierarchy!$A$2:$A$1295,0))="","",INDEX(Hierarchy!$E$2:$E$1295,MATCH($D63,Hierarchy!$A$2:$A$1295,0))),"NODE NOT FOUND")) -> Latin America (LATAM) | I63: =IF($D63="","",IFERROR(IF(INDEX(Hierarchy!$F$2:$F$1295,MATCH($D63,Hierarchy!$A$2:$A$1295,0))="","",INDEX(Hierarchy!$F$2:$F$1295,MATCH($D63,Hierarchy!$A$2:$A$1295,0))),"NODE NOT FOUND")) | J63: =IF($D63="","",IFERROR(IF(INDEX(Hierarchy!$G$2:$G$1295,MATCH($D63,Hierarchy!$A$2:$A$1295,0))="","",INDEX(Hierarchy!$G$2:$G$1295,MATCH($D63,Hierarchy!$A$2:$A$1295,0))),"NODE NOT FOUND")) | K63: =IF($D63="","",IFERROR(IF(INDEX(Hierarchy!$H$2:$H$1295,MATCH($D63,Hierarchy!$A$2:$A$1295,0))="","",INDEX(Hierarchy!$H$2:$H$1295,MATCH($D63,Hierarchy!$A$2:$A$1295,0))),"NODE NOT FOUND")) | L63: =IF($D63="","",IFERROR(IF(INDEX(Hierarchy!$I$2:$I$1295,MATCH($D63,Hierarchy!$A$2:$A$1295,0))="","",INDEX(Hierarchy!$I$2:$I$1295,MATCH($D63,Hierarchy!$A$2:$A$1295,0))),"NODE NOT FOUND")) | M63: =IF(B63="Pre-seeded","Pre-seeded",IF(B63="Review 2026-09-16","Added from review",IF(C63="","New",IF(C63=D63,"","Changed")))) -> Pre-seeded | N63: =TRIM(SUBSTITUTE(SUBSTITUTE(SUBSTITUTE(" "&TRIM(SUBSTITUTE(SUBSTITUTE(SUBSTITUTE(SUBSTITUTE(SUBSTITUTE(SUBSTITUTE(SUBSTITUTE(SUBSTITUTE(SUBSTITUTE(SUBSTITUTE(SUBSTITUTE(SUBSTITUTE(SUBSTITUTE(SUBSTITUTE(SUBSTITUTE(UPPER(TRIM(A63)),"[MEMBER]",""),"{MEMBER}",""),"[MEMBER}",""),"MEMBER]",""),"(A)",""),"""",""),"“",""),"”",""),".",""),":",""),",",""),"–"," "),"-"," "),"/"," "),"&"," AND "))&" "," THE "," ")," TOTAL "," ")," OPERATIONS "," ")) -> ANDEAN REGION | O63: =IF(COUNTIFS($N$2:$N$2000,N63,$D$2:$D$2000,"<>"&D63)>0,"CONFLICT","")
A64: Andhra Pradesh | B64: Pre-seeded | D64: Andhra Pradesh | E64: Exact | F64: =IF($D64="","",IFERROR(IF(INDEX(Hierarchy!$B$2:$B$1295,MATCH($D64,Hierarchy!$A$2:$A$1295,0))="","",INDEX(Hierarchy!$B$2:$B$1295,MATCH($D64,Hierarchy!$A$2:$A$1295,0))),"NODE NOT FOUND")) -> State/Province | G64: =IF($D64="","",IFERROR(IF(INDEX(Hierarchy!$D$2:$D$1295,MATCH($D64,Hierarchy!$A$2:$A$1295,0))="","",INDEX(Hierarchy!$D$2:$D$1295,MATCH($D64,Hierarchy!$A$2:$A$1295,0))),"NODE NOT FOUND")) -> APAC | H64: =IF($D64="","",IFERROR(IF(INDEX(Hierarchy!$E$2:$E$1295,MATCH($D64,Hierarchy!$A$2:$A$1295,0))="","",INDEX(Hierarchy!$E$2:$E$1295,MATCH($D64,Hierarchy!$A$2:$A$1295,0))),"NODE NOT FOUND")) -> South Asia | I64: =IF($D64="","",IFERROR(IF(INDEX(Hierarchy!$F$2:$F$1295,MATCH($D64,Hierarchy!$A$2:$A$1295,0))="","",INDEX(Hierarchy!$F$2:$F$1295,MATCH($D64,Hierarchy!$A$2:$A$1295,0))),"NODE NOT FOUND")) -> India | J64: =IF($D64="","",IFERROR(IF(INDEX(Hierarchy!$G$2:$G$1295,MATCH($D64,Hierarchy!$A$2:$A$1295,0))="","",INDEX(Hierarchy!$G$2:$G$1295,MATCH($D64,Hierarchy!$A$2:$A$1295,0))),"NODE NOT FOUND")) -> IND | K64: =IF($D64="","",IFERROR(IF(INDEX(Hierarchy!$H$2:$H$1295,MATCH($D64,Hierarchy!$A$2:$A$1295,0))="","",INDEX(Hierarchy!$H$2:$H$1295,MATCH($D64,Hierarchy!$A$2:$A$1295,0))),"NODE NOT FOUND")) -> Andhra Pradesh | L64: =IF($D64="","",IFERROR(IF(INDEX(Hierarchy!$I$2:$I$1295,MATCH($D64,Hierarchy!$A$2:$A$1295,0))="","",INDEX(Hierarchy!$I$2:$I$1295,MATCH($D64,Hierarchy!$A$2:$A$1295,0))),"NODE NOT FOUND")) | M64: =IF(B64="Pre-seeded","Pre-seeded",IF(B64="Review 2026-09-16","Added from review",IF(C64="","New",IF(C64=D64,"","Changed")))) -> Pre-seeded | N64: =TRIM(SUBSTITUTE(SUBSTITUTE(SUBSTITUTE(" "&TRIM(SUBSTITUTE(SUBSTITUTE(SUBSTITUTE(SUBSTITUTE(SUBSTITUTE(SUBSTITUTE(SUBSTITUTE(SUBSTITUTE(SUBSTITUTE(SUBSTITUTE(SUBSTITUTE(SUBSTITUTE(SUBSTITUTE(SUBSTITUTE(SUBSTITUTE(UPPER(TRIM(A64)),"[MEMBER]",""),"{MEMBER}",""),"[MEMBER}",""),"MEMBER]",""),"(A)",""),"""",""),"“",""),"”",""),".",""),":",""),",",""),"–"," "),"-"," "),"/"," "),"&"," AND "))&" "," THE "," ")," TOTAL "," ")," OPERATIONS "," ")) -> ANDHRA PRADESH | O64: =IF(COUNTIFS($N$2:$N$2000,N64,$D$2:$D$2000,"<>"&D64)>0,"CONFLICT","")
A65: Andorra | B65: Pre-seeded | D65: Andorra | E65: Exact | F65: =IF($D65="","",IFERROR(IF(INDEX(Hierarchy!$B$2:$B$1295,MATCH($D65,Hierarchy!$A$2:$A$1295,0))="","",INDEX(Hierarchy!$B$2:$B$1295,MATCH($D65,Hierarchy!$A$2:$A$1295,0))),"NODE NOT FOUND")) -> Country | G65: =IF($D65="","",IFERROR(IF(INDEX(Hierarchy!$D$2:$D$1295,MATCH($D65,Hierarchy!$A$2:$A$1295,0))="","",INDEX(Hierarchy!$D$2:$D$1295,MATCH($D65,Hierarchy!$A$2:$A$1295,0))),"NODE NOT FOUND")) -> EMEA | H65: =IF($D65="","",IFERROR(IF(INDEX(Hierarchy!$E$2:$E$1295,MATCH($D65,Hierarchy!$A$2:$A$1295,0))="","",INDEX(Hierarchy!$E$2:$E$1295,MATCH($D65,Hierarchy!$A$2:$A$1295,0))),"NODE NOT FOUND")) -> Europe | I65: =IF($D65="","",IFERROR(IF(INDEX(Hierarchy!$F$2:$F$1295,MATCH($D65,Hierarchy!$A$2:$A$1295,0))="","",INDEX(Hierarchy!$F$2:$F$1295,MATCH($D65,Hierarchy!$A$2:$A$1295,0))),"NODE NOT FOUND")) -> Andorra | J65: =IF($D65="","",IFERROR(IF(INDEX(Hierarchy!$G$2:$G$1295,MATCH($D65,Hierarchy!$A$2:$A$1295,0))="","",INDEX(Hierarchy!$G$2:$G$1295,MATCH($D65,Hierarchy!$A$2:$A$1295,0))),"NODE NOT FOUND")) -> AND | K65: =IF($D65="","",IFERROR(IF(INDEX(Hierarchy!$H$2:$H$1295,MATCH($D65,Hierarchy!$A$2:$A$1295,0))="","",INDEX(Hierarchy!$H$2:$H$1295,MATCH($D65,Hierarchy!$A$2:$A$1295,0))),"NODE NOT FOUND")) | L65: =IF($D65="","",IFERROR(IF(INDEX(Hierarchy!$I$2:$I$1295,MATCH($D65,Hierarchy!$A$2:$A$1295,0))="","",INDEX(Hierarchy!$I$2:$I$1295,MATCH($D65,Hierarchy!$A$2:$A$1295,0))),"NODE NOT FOUND")) | M65: =IF(B65="Pre-seeded","Pre-seeded",IF(B65="Review 2026-09-16","Added from review",IF(C65="","New",IF(C65=D65,"","Changed")))) -> Pre-seeded | N65: =TRIM(SUBSTITUTE(SUBSTITUTE(SUBSTITUTE(" "&TRIM(SUBSTITUTE(SUBSTITUTE(SUBSTITUTE(SUBSTITUTE(SUBSTITUTE(SUBSTITUTE(SUBSTITUTE(SUBSTITUTE(SUBSTITUTE(SUBSTITUTE(SUBSTITUTE(SUBSTITUTE(SUBSTITUTE(SUBSTITUTE(SUBSTITUTE(UPPER(TRIM(A65)),"[MEMBER]",""),"{MEMBER}",""),"[MEMBER}",""),"MEMBER]",""),"(A)",""),"""",""),"“",""),"”",""),".",""),":",""),",",""),"–"," "),"-"," "),"/"," "),"&"," AND "))&" "," THE "," ")," TOTAL "," ")," OPERATIONS "," ")) -> ANDORRA | O65: =IF(COUNTIFS($N$2:$N$2000,N65,$D$2:$D$2000,"<>"&D65)>0,"CONFLICT","")
A66: Angola | B66: Mapping | C66: Angola | D66: Angola | E66: Exact | F66: =IF($D66="","",IFERROR(IF(INDEX(Hierarchy!$B$2:$B$1295,MATCH($D66,Hierarchy!$A$2:$A$1295,0))="","",INDEX(Hierarchy!$B$2:$B$1295,MATCH($D66,Hierarchy!$A$2:$A$1295,0))),"NODE NOT FOUND")) -> Country | G66: =IF($D66="","",IFERROR(IF(INDEX(Hierarchy!$D$2:$D$1295,MATCH($D66,Hierarchy!$A$2:$A$1295,0))="","",INDEX(Hierarchy!$D$2:$D$1295,MATCH($D66,Hierarchy!$A$2:$A$1295,0))),"NODE NOT FOUND")) -> EMEA | H66: =IF($D66="","",IFERROR(IF(INDEX(Hierarchy!$E$2:$E$1295,MATCH($D66,Hierarchy!$A$2:$A$1295,0))="","",INDEX(Hierarchy!$E$2:$E$1295,MATCH($D66,Hierarchy!$A$2:$A$1295,0))),"NODE NOT FOUND")) -> Africa | I66: =IF($D66="","",IFERROR(IF(INDEX(Hierarchy!$F$2:$F$1295,MATCH($D66,Hierarchy!$A$2:$A$1295,0))="","",INDEX(Hierarchy!$F$2:$F$1295,MATCH($D66,Hierarchy!$A$2:$A$1295,0))),"NODE NOT FOUND")) -> Angola | J66: =IF($D66="","",IFERROR(IF(INDEX(Hierarchy!$G$2:$G$1295,MATCH($D66,Hierarchy!$A$2:$A$1295,0))="","",INDEX(Hierarchy!$G$2:$G$1295,MATCH($D66,Hierarchy!$A$2:$A$1295,0))),"NODE NOT FOUND")) -> AGO | K66: =IF($D66="","",IFERROR(IF(INDEX(Hierarchy!$H$2:$H$1295,MATCH($D66,Hierarchy!$A$2:$A$1295,0))="","",INDEX(Hierarchy!$H$2:$H$1295,MATCH($D66,Hierarchy!$A$2:$A$1295,0))),"NODE NOT FOUND")) | L66: =IF($D66="","",IFERROR(IF(INDEX(Hierarchy!$I$2:$I$1295,MATCH($D66,Hierarchy!$A$2:$A$1295,0))="","",INDEX(Hierarchy!$I$2:$I$1295,MATCH($D66,Hierarchy!$A$2:$A$1295,0))),"NODE NOT FOUND")) | M66: =IF(B66="Pre-seeded","Pre-seeded",IF(B66="Review 2026-09-16","Added from review",IF(C66="","New",IF(C66=D66,"","Changed")))) | N66: =TRIM(SUBSTITUTE(SUBSTITUTE(SUBSTITUTE(" "&TRIM(SUBSTITUTE(SUBSTITUTE(SUBSTITUTE(SUBSTITUTE(SUBSTITUTE(SUBSTITUTE(SUBSTITUTE(SUBSTITUTE(SUBSTITUTE(SUBSTITUTE(SUBSTITUTE(SUBSTITUTE(SUBSTITUTE(SUBSTITUTE(SUBSTITUTE(UPPER(TRIM(A66)),"[MEMBER]",""),"{MEMBER}",""),"[MEMBER}",""),"MEMBER]",""),"(A)",""),"""",""),"“",""),"”",""),".",""),":",""),",",""),"–"," "),"-"," "),"/"," "),"&"," AND "))&" "," THE "," ")," TOTAL "," ")," OPERATIONS "," ")) -> ANGOLA | O66: =IF(COUNTIFS($N$2:$N$2000,N66,$D$2:$D$2000,"<>"&D66)>0,"CONFLICT","")
A67: Anguilla | B67: Pre-seeded | D67: Anguilla | E67: Exact | F67: =IF($D67="","",IFERROR(IF(INDEX(Hierarchy!$B$2:$B$1295,MATCH($D67,Hierarchy!$A$2:$A$1295,0))="","",INDEX(Hierarchy!$B$2:$B$1295,MATCH($D67,Hierarchy!$A$2:$A$1295,0))),"NODE NOT FOUND")) -> Country | G67: =IF($D67="","",IFERROR(IF(INDEX(Hierarchy!$D$2:$D$1295,MATCH($D67,Hierarchy!$A$2:$A$1295,0))="","",INDEX(Hierarchy!$D$2:$D$1295,MATCH($D67,Hierarchy!$A$2:$A$1295,0))),"NODE NOT FOUND")) -> AMER | H67: =IF($D67="","",IFERROR(IF(INDEX(Hierarchy!$E$2:$E$1295,MATCH($D67,Hierarchy!$A$2:$A$1295,0))="","",INDEX(Hierarchy!$E$2:$E$1295,MATCH($D67,Hierarchy!$A$2:$A$1295,0))),"NODE NOT FOUND")) -> Latin America (LATAM) | I67: =IF($D67="","",IFERROR(IF(INDEX(Hierarchy!$F$2:$F$1295,MATCH($D67,Hierarchy!$A$2:$A$1295,0))="","",INDEX(Hierarchy!$F$2:$F$1295,MATCH($D67,Hierarchy!$A$2:$A$1295,0))),"NODE NOT FOUND")) -> Anguilla | J67: =IF($D67="","",IFERROR(IF(INDEX(Hierarchy!$G$2:$G$1295,MATCH($D67,Hierarchy!$A$2:$A$1295,0))="","",INDEX(Hierarchy!$G$2:$G$1295,MATCH($D67,Hierarchy!$A$2:$A$1295,0))),"NODE NOT FOUND")) -> AIA | K67: =IF($D67="","",IFERROR(IF(INDEX(Hierarchy!$H$2:$H$1295,MATCH($D67,Hierarchy!$A$2:$A$1295,0))="","",INDEX(Hierarchy!$H$2:$H$1295,MATCH($D67,Hierarchy!$A$2:$A$1295,0))),"NODE NOT FOUND")) | L67: =IF($D67="","",IFERROR(IF(INDEX(Hierarchy!$I$2:$I$1295,MATCH($D67,Hierarchy!$A$2:$A$1295,0))="","",INDEX(Hierarchy!$I$2:$I$1295,MATCH($D67,Hierarchy!$A$2:$A$1295,0))),"NODE NOT FOUND")) | M67: =IF(B67="Pre-seeded","Pre-seeded",IF(B67="Review 2026-09-16","Added from review",IF(C67="","New",IF(C67=D67,"","Changed")))) -> Pre-seeded | N67: =TRIM(SUBSTITUTE(SUBSTITUTE(SUBSTITUTE(" "&TRIM(SUBSTITUTE(SUBSTITUTE(SUBSTITUTE(SUBSTITUTE(SUBSTITUTE(SUBSTITUTE(SUBSTITUTE(SUBSTITUTE(SUBSTITUTE(SUBSTITUTE(SUBSTITUTE(SUBSTITUTE(SUBSTITUTE(SUBSTITUTE(SUBSTITUTE(UPPER(TRIM(A67)),"[MEMBER]",""),"{MEMBER}",""),"[MEMBER}",""),"MEMBER]",""),"(A)",""),"""",""),"“",""),"”",""),".",""),":",""),",",""),"–"," "),"-"," "),"/"," "),"&"," AND "))&" "," THE "," ")," TOTAL "," ")," OPERATIONS "," ")) -> ANGUILLA | O67: =IF(COUNTIFS($N$2:$N$2000,N67,$D$2:$D$2000,"<>"&D67)>0,"CONFLICT","")
A68: Anhui | B68: Pre-seeded | D68: Anhui | E68: Exact | F68: =IF($D68="","",IFERROR(IF(INDEX(Hierarchy!$B$2:$B$1295,MATCH($D68,Hierarchy!$A$2:$A$1295,0))="","",INDEX(Hierarchy!$B$2:$B$1295,MATCH($D68,Hierarchy!$A$2:$A$1295,0))),"NODE NOT FOUND")) -> State/Province | G68: =IF($D68="","",IFERROR(IF(INDEX(Hierarchy!$D$2:$D$1295,MATCH($D68,Hierarchy!$A$2:$A$1295,0))="","",INDEX(Hierarchy!$D$2:$D$1295,MATCH($D68,Hierarchy!$A$2:$A$1295,0))),"NODE NOT FOUND")) -> APAC | H68: =IF($D68="","",IFERROR(IF(INDEX(Hierarchy!$E$2:$E$1295,MATCH($D68,Hierarchy!$A$2:$A$1295,0))="","",INDEX(Hierarchy!$E$2:$E$1295,MATCH($D68,Hierarchy!$A$2:$A$1295,0))),"NODE NOT FOUND")) -> East Asia | I68: =IF($D68="","",IFERROR(IF(INDEX(Hierarchy!$F$2:$F$1295,MATCH($D68,Hierarchy!$A$2:$A$1295,0))="","",INDEX(Hierarchy!$F$2:$F$1295,MATCH($D68,Hierarchy!$A$2:$A$1295,0))),"NODE NOT FOUND")) -> China | J68: =IF($D68="","",IFERROR(IF(INDEX(Hierarchy!$G$2:$G$1295,MATCH($D68,Hierarchy!$A$2:$A$1295,0))="","",INDEX(Hierarchy!$G$2:$G$1295,MATCH($D68,Hierarchy!$A$2:$A$1295,0))),"NODE NOT FOUND")) -> CHN | K68: =IF($D68="","",IFERROR(IF(INDEX(Hierarchy!$H$2:$H$1295,MATCH($D68,Hierarchy!$A$2:$A$1295,0))="","",INDEX(Hierarchy!$H$2:$H$1295,MATCH($D68,Hierarchy!$A$2:$A$1295,0))),"NODE NOT FOUND")) -> Anhui | L68: =IF($D68="","",IFERROR(IF(INDEX(Hierarchy!$I$2:$I$1295,MATCH($D68,Hierarchy!$A$2:$A$1295,0))="","",INDEX(Hierarchy!$I$2:$I$1295,MATCH($D68,Hierarchy!$A$2:$A$1295,0))),"NODE NOT FOUND")) | M68: =IF(B68="Pre-seeded","Pre-seeded",IF(B68="Review 2026-09-16","Added from review",IF(C68="","New",IF(C68=D68,"","Changed")))) -> Pre-seeded | N68: =TRIM(SUBSTITUTE(SUBSTITUTE(SUBSTITUTE(" "&TRIM(SUBSTITUTE(SUBSTITUTE(SUBSTITUTE(SUBSTITUTE(SUBSTITUTE(SUBSTITUTE(SUBSTITUTE(SUBSTITUTE(SUBSTITUTE(SUBSTITUTE(SUBSTITUTE(SUBSTITUTE(SUBSTITUTE(SUBSTITUTE(SUBSTITUTE(UPPER(TRIM(A68)),"[MEMBER]",""),"{MEMBER}",""),"[MEMBER}",""),"MEMBER]",""),"(A)",""),"""",""),"“",""),"”",""),".",""),":",""),",",""),"–"," "),"-"," "),"/"," "),"&"," AND "))&" "," THE "," ")," TOTAL "," ")," OPERATIONS "," ")) -> ANHUI | O68: =IF(COUNTIFS($N$2:$N$2000,N68,$D$2:$D$2000,"<>"&D68)>0,"CONFLICT","")
A69: Antigua and Barbuda | B69: Pre-seeded | D69: Antigua and Barbuda | E69: Exact | F69: =IF($D69="","",IFERROR(IF(INDEX(Hierarchy!$B$2:$B$1295,MATCH($D69,Hierarchy!$A$2:$A$1295,0))="","",INDEX(Hierarchy!$B$2:$B$1295,MATCH($D69,Hierarchy!$A$2:$A$1295,0))),"NODE NOT FOUND")) -> Country | G69: =IF($D69="","",IFERROR(IF(INDEX(Hierarchy!$D$2:$D$1295,MATCH($D69,Hierarchy!$A$2:$A$1295,0))="","",INDEX(Hierarchy!$D$2:$D$1295,MATCH($D69,Hierarchy!$A$2:$A$1295,0))),"NODE NOT FOUND")) -> AMER | H69: =IF($D69="","",IFERROR(IF(INDEX(Hierarchy!$E$2:$E$1295,MATCH($D69,Hierarchy!$A$2:$A$1295,0))="","",INDEX(Hierarchy!$E$2:$E$1295,MATCH($D69,Hierarchy!$A$2:$A$1295,0))),"NODE NOT FOUND")) -> Latin America (LATAM) | I69: =IF($D69="","",IFERROR(IF(INDEX(Hierarchy!$F$2:$F$1295,MATCH($D69,Hierarchy!$A$2:$A$1295,0))="","",INDEX(Hierarchy!$F$2:$F$1295,MATCH($D69,Hierarchy!$A$2:$A$1295,0))),"NODE NOT FOUND")) -> Antigua and Barbuda | J69: =IF($D69="","",IFERROR(IF(INDEX(Hierarchy!$G$2:$G$1295,MATCH($D69,Hierarchy!$A$2:$A$1295,0))="","",INDEX(Hierarchy!$G$2:$G$1295,MATCH($D69,Hierarchy!$A$2:$A$1295,0))),"NODE NOT FOUND")) -> ATG | K69: =IF($D69="","",IFERROR(IF(INDEX(Hierarchy!$H$2:$H$1295,MATCH($D69,Hierarchy!$A$2:$A$1295,0))="","",INDEX(Hierarchy!$H$2:$H$1295,MATCH($D69,Hierarchy!$A$2:$A$1295,0))),"NODE NOT FOUND")) | L69: =IF($D69="","",IFERROR(IF(INDEX(Hierarchy!$I$2:$I$1295,MATCH($D69,Hierarchy!$A$2:$A$1295,0))="","",INDEX(Hierarchy!$I$2:$I$1295,MATCH($D69,Hierarchy!$A$2:$A$1295,0))),"NODE NOT FOUND")) | M69: =IF(B69="Pre-seeded","Pre-seeded",IF(B69="Review 2026-09-16","Added from review",IF(C69="","New",IF(C69=D69,"","Changed")))) -> Pre-seeded | N69: =TRIM(SUBSTITUTE(SUBSTITUTE(SUBSTITUTE(" "&TRIM(SUBSTITUTE(SUBSTITUTE(SUBSTITUTE(SUBSTITUTE(SUBSTITUTE(SUBSTITUTE(SUBSTITUTE(SUBSTITUTE(SUBSTITUTE(SUBSTITUTE(SUBSTITUTE(SUBSTITUTE(SUBSTITUTE(SUBSTITUTE(SUBSTITUTE(UPPER(TRIM(A69)),"[MEMBER]",""),"{MEMBER}",""),"[MEMBER}",""),"MEMBER]",""),"(A)",""),"""",""),"“",""),"”",""),".",""),":",""),",",""),"–"," "),"-"," "),"/"," "),"&"," AND "))&" "," THE "," ")," TOTAL "," ")," OPERATIONS "," ")) -> ANTIGUA AND BARBUDA | O69: =IF(COUNTIFS($N$2:$N$2000,N69,$D$2:$D$2000,"<>"&D69)>0,"CONFLICT","")
A70: Antioquia | B70: Pre-seeded | D70: Antioquia | E70: Exact | F70: =IF($D70="","",IFERROR(IF(INDEX(Hierarchy!$B$2:$B$1295,MATCH($D70,Hierarchy!$A$2:$A$1295,0))="","",INDEX(Hierarchy!$B$2:$B$1295,MATCH($D70,Hierarchy!$A$2:$A$1295,0))),"NODE NOT FOUND")) -> State/Province | G70: =IF($D70="","",IFERROR(IF(INDEX(Hierarchy!$D$2:$D$1295,MATCH($D70,Hierarchy!$A$2:$A$1295,0))="","",INDEX(Hierarchy!$D$2:$D$1295,MATCH($D70,Hierarchy!$A$2:$A$1295,0))),"NODE NOT FOUND")) -> AMER | H70: =IF($D70="","",IFERROR(IF(INDEX(Hierarchy!$E$2:$E$1295,MATCH($D70,Hierarchy!$A$2:$A$1295,0))="","",INDEX(Hierarchy!$E$2:$E$1295,MATCH($D70,Hierarchy!$A$2:$A$1295,0))),"NODE NOT FOUND")) -> Latin America (LATAM) | I70: =IF($D70="","",IFERROR(IF(INDEX(Hierarchy!$F$2:$F$1295,MATCH($D70,Hierarchy!$A$2:$A$1295,0))="","",INDEX(Hierarchy!$F$2:$F$1295,MATCH($D70,Hierarchy!$A$2:$A$1295,0))),"NODE NOT FOUND")) -> Colombia | J70: =IF($D70="","",IFERROR(IF(INDEX(Hierarchy!$G$2:$G$1295,MATCH($D70,Hierarchy!$A$2:$A$1295,0))="","",INDEX(Hierarchy!$G$2:$G$1295,MATCH($D70,Hierarchy!$A$2:$A$1295,0))),"NODE NOT FOUND")) -> COL | K70: =IF($D70="","",IFERROR(IF(INDEX(Hierarchy!$H$2:$H$1295,MATCH($D70,Hierarchy!$A$2:$A$1295,0))="","",INDEX(Hierarchy!$H$2:$H$1295,MATCH($D70,Hierarchy!$A$2:$A$1295,0))),"NODE NOT FOUND")) -> Antioquia | L70: =IF($D70="","",IFERROR(IF(INDEX(Hierarchy!$I$2:$I$1295,MATCH($D70,Hierarchy!$A$2:$A$1295,0))="","",INDEX(Hierarchy!$I$2:$I$1295,MATCH($D70,Hierarchy!$A$2:$A$1295,0))),"NODE NOT FOUND")) | M70: =IF(B70="Pre-seeded","Pre-seeded",IF(B70="Review 2026-09-16","Added from review",IF(C70="","New",IF(C70=D70,"","Changed")))) -> Pre-seeded | N70: =TRIM(SUBSTITUTE(SUBSTITUTE(SUBSTITUTE(" "&TRIM(SUBSTITUTE(SUBSTITUTE(SUBSTITUTE(SUBSTITUTE(SUBSTITUTE(SUBSTITUTE(SUBSTITUTE(SUBSTITUTE(SUBSTITUTE(SUBSTITUTE(SUBSTITUTE(SUBSTITUTE(SUBSTITUTE(SUBSTITUTE(SUBSTITUTE(UPPER(TRIM(A70)),"[MEMBER]",""),"{MEMBER}",""),"[MEMBER}",""),"MEMBER]",""),"(A)",""),"""",""),"“",""),"”",""),".",""),":",""),",",""),"–"," "),"-"," "),"/"," "),"&"," AND "))&" "," THE "," ")," TOTAL "," ")," OPERATIONS "," ")) -> ANTIOQUIA | O70: =IF(COUNTIFS($N$2:$N$2000,N70,$D$2:$D$2000,"<>"&D70)>0,"CONFLICT","")
A71: Antofagasta | B71: Pre-seeded | D71: Antofagasta | E71: Exact | F71: =IF($D71="","",IFERROR(IF(INDEX(Hierarchy!$B$2:$B$1295,MATCH($D71,Hierarchy!$A$2:$A$1295,0))="","",INDEX(Hierarchy!$B$2:$B$1295,MATCH($D71,Hierarchy!$A$2:$A$1295,0))),"NODE NOT FOUND")) -> State/Province | G71: =IF($D71="","",IFERROR(IF(INDEX(Hierarchy!$D$2:$D$1295,MATCH($D71,Hierarchy!$A$2:$A$1295,0))="","",INDEX(Hierarchy!$D$2:$D$1295,MATCH($D71,Hierarchy!$A$2:$A$1295,0))),"NODE NOT FOUND")) -> AMER | H71: =IF($D71="","",IFERROR(IF(INDEX(Hierarchy!$E$2:$E$1295,MATCH($D71,Hierarchy!$A$2:$A$1295,0))="","",INDEX(Hierarchy!$E$2:$E$1295,MATCH($D71,Hierarchy!$A$2:$A$1295,0))),"NODE NOT FOUND")) -> Latin America (LATAM) | I71: =IF($D71="","",IFERROR(IF(INDEX(Hierarchy!$F$2:$F$1295,MATCH($D71,Hierarchy!$A$2:$A$1295,0))="","",INDEX(Hierarchy!$F$2:$F$1295,MATCH($D71,Hierarchy!$A$2:$A$1295,0))),"NODE NOT FOUND")) -> Chile | J71: =IF($D71="","",IFERROR(IF(INDEX(Hierarchy!$G$2:$G$1295,MATCH($D71,Hierarchy!$A$2:$A$1295,0))="","",INDEX(Hierarchy!$G$2:$G$1295,MATCH($D71,Hierarchy!$A$2:$A$1295,0))),"NODE NOT FOUND")) -> CHL | K71: =IF($D71="","",IFERROR(IF(INDEX(Hierarchy!$H$2:$H$1295,MATCH($D71,Hierarchy!$A$2:$A$1295,0))="","",INDEX(Hierarchy!$H$2:$H$1295,MATCH($D71,Hierarchy!$A$2:$A$1295,0))),"NODE NOT FOUND")) -> Antofagasta | L71: =IF($D71="","",IFERROR(IF(INDEX(Hierarchy!$I$2:$I$1295,MATCH($D71,Hierarchy!$A$2:$A$1295,0))="","",INDEX(Hierarchy!$I$2:$I$1295,MATCH($D71,Hierarchy!$A$2:$A$1295,0))),"NODE NOT FOUND")) | M71: =IF(B71="Pre-seeded","Pre-seeded",IF(B71="Review 2026-09-16","Added from review",IF(C71="","New",IF(C71=D71,"","Changed")))) -> Pre-seeded | N71: =TRIM(SUBSTITUTE(SUBSTITUTE(SUBSTITUTE(" "&TRIM(SUBSTITUTE(SUBSTITUTE(SUBSTITUTE(SUBSTITUTE(SUBSTITUTE(SUBSTITUTE(SUBSTITUTE(SUBSTITUTE(SUBSTITUTE(SUBSTITUTE(SUBSTITUTE(SUBSTITUTE(SUBSTITUTE(SUBSTITUTE(SUBSTITUTE(UPPER(TRIM(A71)),"[MEMBER]",""),"{MEMBER}",""),"[MEMBER}",""),"MEMBER]",""),"(A)",""),"""",""),"“",""),"”",""),".",""),":",""),",",""),"–"," "),"-"," "),"/"," "),"&"," AND "))&" "," THE "," ")," TOTAL "," ")," OPERATIONS "," ")) -> ANTOFAGASTA | O71: =IF(COUNTIFS($N$2:$N$2000,N71,$D$2:$D$2000,"<>"&D71)>0,"CONFLICT","")
A72: ANZ | B72: Pre-seeded | D72: Oceania (ANZ) | E72: Exact | F72: =IF($D72="","",IFERROR(IF(INDEX(Hierarchy!$B$2:$B$1295,MATCH($D72,Hierarchy!$A$2:$A$1295,0))="","",INDEX(Hierarchy!$B$2:$B$1295,MATCH($D72,Hierarchy!$A$2:$A$1295,0))),"NODE NOT FOUND")) -> Sub-region | G72: =IF($D72="","",IFERROR(IF(INDEX(Hierarchy!$D$2:$D$1295,MATCH($D72,Hierarchy!$A$2:$A$1295,0))="","",INDEX(Hierarchy!$D$2:$D$1295,MATCH($D72,Hierarchy!$A$2:$A$1295,0))),"NODE NOT FOUND")) -> APAC | H72: =IF($D72="","",IFERROR(IF(INDEX(Hierarchy!$E$2:$E$1295,MATCH($D72,Hierarchy!$A$2:$A$1295,0))="","",INDEX(Hierarchy!$E$2:$E$1295,MATCH($D72,Hierarchy!$A$2:$A$1295,0))),"NODE NOT FOUND")) -> Oceania (ANZ) | I72: =IF($D72="","",IFERROR(IF(INDEX(Hierarchy!$F$2:$F$1295,MATCH($D72,Hierarchy!$A$2:$A$1295,0))="","",INDEX(Hierarchy!$F$2:$F$1295,MATCH($D72,Hierarchy!$A$2:$A$1295,0))),"NODE NOT FOUND")) | J72: =IF($D72="","",IFERROR(IF(INDEX(Hierarchy!$G$2:$G$1295,MATCH($D72,Hierarchy!$A$2:$A$1295,0))="","",INDEX(Hierarchy!$G$2:$G$1295,MATCH($D72,Hierarchy!$A$2:$A$1295,0))),"NODE NOT FOUND")) | K72: =IF($D72="","",IFERROR(IF(INDEX(Hierarchy!$H$2:$H$1295,MATCH($D72,Hierarchy!$A$2:$A$1295,0))="","",INDEX(Hierarchy!$H$2:$H$1295,MATCH($D72,Hierarchy!$A$2:$A$1295,0))),"NODE NOT FOUND")) | L72: =IF($D72="","",IFERROR(IF(INDEX(Hierarchy!$I$2:$I$1295,MATCH($D72,Hierarchy!$A$2:$A$1295,0))="","",INDEX(Hierarchy!$I$2:$I$1295,MATCH($D72,Hierarchy!$A$2:$A$1295,0))),"NODE NOT FOUND")) | M72: =IF(B72="Pre-seeded","Pre-seeded",IF(B72="Review 2026-09-16","Added from review",IF(C72="","New",IF(C72=D72,"","Changed")))) -> Pre-seeded | N72: =TRIM(SUBSTITUTE(SUBSTITUTE(SUBSTITUTE(" "&TRIM(SUBSTITUTE(SUBSTITUTE(SUBSTITUTE(SUBSTITUTE(SUBSTITUTE(SUBSTITUTE(SUBSTITUTE(SUBSTITUTE(SUBSTITUTE(SUBSTITUTE(SUBSTITUTE(SUBSTITUTE(SUBSTITUTE(SUBSTITUTE(SUBSTITUTE(UPPER(TRIM(A72)),"[MEMBER]",""),"{MEMBER}",""),"[MEMBER}",""),"MEMBER]",""),"(A)",""),"""",""),"“",""),"”",""),".",""),":",""),",",""),"–"," "),"-"," "),"/"," "),"&"," AND "))&" "," THE "," ")," TOTAL "," ")," OPERATIONS "," ")) -> ANZ | O72: =IF(COUNTIFS($N$2:$N$2000,N72,$D$2:$D$2000,"<>"&D72)>0,"CONFLICT","")
A73: Aomori | B73: Pre-seeded | D73: Aomori | E73: Exact | F73: =IF($D73="","",IFERROR(IF(INDEX(Hierarchy!$B$2:$B$1295,MATCH($D73,Hierarchy!$A$2:$A$1295,0))="","",INDEX(Hierarchy!$B$2:$B$1295,MATCH($D73,Hierarchy!$A$2:$A$1295,0))),"NODE NOT FOUND")) -> State/Province | G73: =IF($D73="","",IFERROR(IF(INDEX(Hierarchy!$D$2:$D$1295,MATCH($D73,Hierarchy!$A$2:$A$1295,0))="","",INDEX(Hierarchy!$D$2:$D$1295,MATCH($D73,Hierarchy!$A$2:$A$1295,0))),"NODE NOT FOUND")) -> APAC | H73: =IF($D73="","",IFERROR(IF(INDEX(Hierarchy!$E$2:$E$1295,MATCH($D73,Hierarchy!$A$2:$A$1295,0))="","",INDEX(Hierarchy!$E$2:$E$1295,MATCH($D73,Hierarchy!$A$2:$A$1295,0))),"NODE NOT FOUND")) -> East Asia | I73: =IF($D73="","",IFERROR(IF(INDEX(Hierarchy!$F$2:$F$1295,MATCH($D73,Hierarchy!$A$2:$A$1295,0))="","",INDEX(Hierarchy!$F$2:$F$1295,MATCH($D73,Hierarchy!$A$2:$A$1295,0))),"NODE NOT FOUND")) -> Japan | J73: =IF($D73="","",IFERROR(IF(INDEX(Hierarchy!$G$2:$G$1295,MATCH($D73,Hierarchy!$A$2:$A$1295,0))="","",INDEX(Hierarchy!$G$2:$G$1295,MATCH($D73,Hierarchy!$A$2:$A$1295,0))),"NODE NOT FOUND")) -> JPN | K73: =IF($D73="","",IFERROR(IF(INDEX(Hierarchy!$H$2:$H$1295,MATCH($D73,Hierarchy!$A$2:$A$1295,0))="","",INDEX(Hierarchy!$H$2:$H$1295,MATCH($D73,Hierarchy!$A$2:$A$1295,0))),"NODE NOT FOUND")) -> Aomori | L73: =IF($D73="","",IFERROR(IF(INDEX(Hierarchy!$I$2:$I$1295,MATCH($D73,Hierarchy!$A$2:$A$1295,0))="","",INDEX(Hierarchy!$I$2:$I$1295,MATCH($D73,Hierarchy!$A$2:$A$1295,0))),"NODE NOT FOUND")) | M73: =IF(B73="Pre-seeded","Pre-seeded",IF(B73="Review 2026-09-16","Added from review",IF(C73="","New",IF(C73=D73,"","Changed")))) -> Pre-seeded | N73: =TRIM(SUBSTITUTE(SUBSTITUTE(SUBSTITUTE(" "&TRIM(SUBSTITUTE(SUBSTITUTE(SUBSTITUTE(SUBSTITUTE(SUBSTITUTE(SUBSTITUTE(SUBSTITUTE(SUBSTITUTE(SUBSTITUTE(SUBSTITUTE(SUBSTITUTE(SUBSTITUTE(SUBSTITUTE(SUBSTITUTE(SUBSTITUTE(UPPER(TRIM(A73)),"[MEMBER]",""),"{MEMBER}",""),"[MEMBER}",""),"MEMBER]",""),"(A)",""),"""",""),"“",""),"”",""),".",""),":",""),",",""),"–"," "),"-"," "),"/"," "),"&"," AND "))&" "," THE "," ")," TOTAL "," ")," OPERATIONS "," ")) -> AOMORI | O73: =IF(COUNTIFS($N$2:$N$2000,N73,$D$2:$D$2000,"<>"&D73)>0,"CONFLICT","")
A74: Aosta Valley | B74: Pre-seeded | D74: Aosta Valley | E74: Exact | F74: =IF($D74="","",IFERROR(IF(INDEX(Hierarchy!$B$2:$B$1295,MATCH($D74,Hierarchy!$A$2:$A$1295,0))="","",INDEX(Hierarchy!$B$2:$B$1295,MATCH($D74,Hierarchy!$A$2:$A$1295,0))),"NODE NOT FOUND")) -> State/Province | G74: =IF($D74="","",IFERROR(IF(INDEX(Hierarchy!$D$2:$D$1295,MATCH($D74,Hierarchy!$A$2:$A$1295,0))="","",INDEX(Hierarchy!$D$2:$D$1295,MATCH($D74,Hierarchy!$A$2:$A$1295,0))),"NODE NOT FOUND")) -> EMEA | H74: =IF($D74="","",IFERROR(IF(INDEX(Hierarchy!$E$2:$E$1295,MATCH($D74,Hierarchy!$A$2:$A$1295,0))="","",INDEX(Hierarchy!$E$2:$E$1295,MATCH($D74,Hierarchy!$A$2:$A$1295,0))),"NODE NOT FOUND")) -> Europe | I74: =IF($D74="","",IFERROR(IF(INDEX(Hierarchy!$F$2:$F$1295,MATCH($D74,Hierarchy!$A$2:$A$1295,0))="","",INDEX(Hierarchy!$F$2:$F$1295,MATCH($D74,Hierarchy!$A$2:$A$1295,0))),"NODE NOT FOUND")) -> Italy | J74: =IF($D74="","",IFERROR(IF(INDEX(Hierarchy!$G$2:$G$1295,MATCH($D74,Hierarchy!$A$2:$A$1295,0))="","",INDEX(Hierarchy!$G$2:$G$1295,MATCH($D74,Hierarchy!$A$2:$A$1295,0))),"NODE NOT FOUND")) -> ITA | K74: =IF($D74="","",IFERROR(IF(INDEX(Hierarchy!$H$2:$H$1295,MATCH($D74,Hierarchy!$A$2:$A$1295,0))="","",INDEX(Hierarchy!$H$2:$H$1295,MATCH($D74,Hierarchy!$A$2:$A$1295,0))),"NODE NOT FOUND")) -> Aosta Valley | L74: =IF($D74="","",IFERROR(IF(INDEX(Hierarchy!$I$2:$I$1295,MATCH($D74,Hierarchy!$A$2:$A$1295,0))="","",INDEX(Hierarchy!$I$2:$I$1295,MATCH($D74,Hierarchy!$A$2:$A$1295,0))),"NODE NOT FOUND")) | M74: =IF(B74="Pre-seeded","Pre-seeded",IF(B74="Review 2026-09-16","Added from review",IF(C74="","New",IF(C74=D74,"","Changed")))) -> Pre-seeded | N74: =TRIM(SUBSTITUTE(SUBSTITUTE(SUBSTITUTE(" "&TRIM(SUBSTITUTE(SUBSTITUTE(SUBSTITUTE(SUBSTITUTE(SUBSTITUTE(SUBSTITUTE(SUBSTITUTE(SUBSTITUTE(SUBSTITUTE(SUBSTITUTE(SUBSTITUTE(SUBSTITUTE(SUBSTITUTE(SUBSTITUTE(SUBSTITUTE(UPPER(TRIM(A74)),"[MEMBER]",""),"{MEMBER}",""),"[MEMBER}",""),"MEMBER]",""),"(A)",""),"""",""),"“",""),"”",""),".",""),":",""),",",""),"–"," "),"-"," "),"/"," "),"&"," AND "))&" "," THE "," ")," TOTAL "," ")," OPERATIONS "," ")) -> AOSTA VALLEY | O74: =IF(COUNTIFS($N$2:$N$2000,N74,$D$2:$D$2000,"<>"&D74)>0,"CONFLICT","")
A75: APAC | B75: Mapping | C75: Asia Pacific (APAC) | D75: APAC (Asia-Pacific) | E75: Exact | F75: =IF($D75="","",IFERROR(IF(INDEX(Hierarchy!$B$2:$B$1295,MATCH($D75,Hierarchy!$A$2:$A$1295,0))="","",INDEX(Hierarchy!$B$2:$B$1295,MATCH($D75,Hierarchy!$A$2:$A$1295,0))),"NODE NOT FOUND")) -> Region | G75: =IF($D75="","",IFERROR(IF(INDEX(Hierarchy!$D$2:$D$1295,MATCH($D75,Hierarchy!$A$2:$A$1295,0))="","",INDEX(Hierarchy!$D$2:$D$1295,MATCH($D75,Hierarchy!$A$2:$A$1295,0))),"NODE NOT FOUND")) -> APAC | H75: =IF($D75="","",IFERROR(IF(INDEX(Hierarchy!$E$2:$E$1295,MATCH($D75,Hierarchy!$A$2:$A$1295,0))="","",INDEX(Hierarchy!$E$2:$E$1295,MATCH($D75,Hierarchy!$A$2:$A$1295,0))),"NODE NOT FOUND")) | I75: =IF($D75="","",IFERROR(IF(INDEX(Hierarchy!$F$2:$F$1295,MATCH($D75,Hierarchy!$A$2:$A$1295,0))="","",INDEX(Hierarchy!$F$2:$F$1295,MATCH($D75,Hierarchy!$A$2:$A$1295,0))),"NODE NOT FOUND")) | J75: =IF($D75="","",IFERROR(IF(INDEX(Hierarchy!$G$2:$G$1295,MATCH($D75,Hierarchy!$A$2:$A$1295,0))="","",INDEX(Hierarchy!$G$2:$G$1295,MATCH($D75,Hierarchy!$A$2:$A$1295,0))),"NODE NOT FOUND")) | K75: =IF($D75="","",IFERROR(IF(INDEX(Hierarchy!$H$2:$H$1295,MATCH($D75,Hierarchy!$A$2:$A$1295,0))="","",INDEX(Hierarchy!$H$2:$H$1295,MATCH($D75,Hierarchy!$A$2:$A$1295,0))),"NODE NOT FOUND")) | L75: =IF($D75="","",IFERROR(IF(INDEX(Hierarchy!$I$2:$I$1295,MATCH($D75,Hierarchy!$A$2:$A$1295,0))="","",INDEX(Hierarchy!$I$2:$I$1295,MATCH($D75,Hierarchy!$A$2:$A$1295,0))),"NODE NOT FOUND")) | M75: =IF(B75="Pre-seeded","Pre-seeded",IF(B75="Review 2026-09-16","Added from review",IF(C75="","New",IF(C75=D75,"","Changed")))) -> Changed | N75: =TRIM(SUBSTITUTE(SUBSTITUTE(SUBSTITUTE(" "&TRIM(SUBSTITUTE(SUBSTITUTE(SUBSTITUTE(SUBSTITUTE(SUBSTITUTE(SUBSTITUTE(SUBSTITUTE(SUBSTITUTE(SUBSTITUTE(SUBSTITUTE(SUBSTITUTE(SUBSTITUTE(SUBSTITUTE(SUBSTITUTE(SUBSTITUTE(UPPER(TRIM(A75)),"[MEMBER]",""),"{MEMBER}",""),"[MEMBER}",""),"MEMBER]",""),"(A)",""),"""",""),"“",""),"”",""),".",""),":",""),",",""),"–"," "),"-"," "),"/"," "),"&"," AND "))&" "," THE "," ")," TOTAL "," ")," OPERATIONS "," ")) -> APAC | O75: =IF(COUNTIFS($N$2:$N$2000,N75,$D$2:$D$2000,"<>"&D75)>0,"CONFLICT","")
A76: APAC (Asia-Pacific) | B76: Pre-seeded | D76: APAC (Asia-Pacific) | E76: Exact | F76: =IF($D76="","",IFERROR(IF(INDEX(Hierarchy!$B$2:$B$1295,MATCH($D76,Hierarchy!$A$2:$A$1295,0))="","",INDEX(Hierarchy!$B$2:$B$1295,MATCH($D76,Hierarchy!$A$2:$A$1295,0))),"NODE NOT FOUND")) -> Region | G76: =IF($D76="","",IFERROR(IF(INDEX(Hierarchy!$D$2:$D$1295,MATCH($D76,Hierarchy!$A$2:$A$1295,0))="","",INDEX(Hierarchy!$D$2:$D$1295,MATCH($D76,Hierarchy!$A$2:$A$1295,0))),"NODE NOT FOUND")) -> APAC | H76: =IF($D76="","",IFERROR(IF(INDEX(Hierarchy!$E$2:$E$1295,MATCH($D76,Hierarchy!$A$2:$A$1295,0))="","",INDEX(Hierarchy!$E$2:$E$1295,MATCH($D76,Hierarchy!$A$2:$A$1295,0))),"NODE NOT FOUND")) | I76: =IF($D76="","",IFERROR(IF(INDEX(Hierarchy!$F$2:$F$1295,MATCH($D76,Hierarchy!$A$2:$A$1295,0))="","",INDEX(Hierarchy!$F$2:$F$1295,MATCH($D76,Hierarchy!$A$2:$A$1295,0))),"NODE NOT FOUND")) | J76: =IF($D76="","",IFERROR(IF(INDEX(Hierarchy!$G$2:$G$1295,MATCH($D76,Hierarchy!$A$2:$A$1295,0))="","",INDEX(Hierarchy!$G$2:$G$1295,MATCH($D76,Hierarchy!$A$2:$A$1295,0))),"NODE NOT FOUND")) | K76: =IF($D76="","",IFERROR(IF(INDEX(Hierarchy!$H$2:$H$1295,MATCH($D76,Hierarchy!$A$2:$A$1295,0))="","",INDEX(Hierarchy!$H$2:$H$1295,MATCH($D76,Hierarchy!$A$2:$A$1295,0))),"NODE NOT FOUND")) | L76: =IF($D76="","",IFERROR(IF(INDEX(Hierarchy!$I$2:$I$1295,MATCH($D76,Hierarchy!$A$2:$A$1295,0))="","",INDEX(Hierarchy!$I$2:$I$1295,MATCH($D76,Hierarchy!$A$2:$A$1295,0))),"NODE NOT FOUND")) | M76: =IF(B76="Pre-seeded","Pre-seeded",IF(B76="Review 2026-09-16","Added from review",IF(C76="","New",IF(C76=D76,"","Changed")))) -> Pre-seeded | N76: =TRIM(SUBSTITUTE(SUBSTITUTE(SUBSTITUTE(" "&TRIM(SUBSTITUTE(SUBSTITUTE(SUBSTITUTE(SUBSTITUTE(SUBSTITUTE(SUBSTITUTE(SUBSTITUTE(SUBSTITUTE(SUBSTITUTE(SUBSTITUTE(SUBSTITUTE(SUBSTITUTE(SUBSTITUTE(SUBSTITUTE(SUBSTITUTE(UPPER(TRIM(A76)),"[MEMBER]",""),"{MEMBER}",""),"[MEMBER}",""),"MEMBER]",""),"(A)",""),"""",""),"“",""),"”",""),".",""),":",""),",",""),"–"," "),"-"," "),"/"," "),"&"," AND "))&" "," THE "," ")," TOTAL "," ")," OPERATIONS "," ")) -> APAC (ASIA PACIFIC) | O76: =IF(COUNTIFS($N$2:$N$2000,N76,$D$2:$D$2000,"<>"&D76)>0,"CONFLICT","")
A77: APAC and Latin America | B77: Pre-seeded | D77: APAC and Latin America | E77: Exact | F77: =IF($D77="","",IFERROR(IF(INDEX(Hierarchy!$B$2:$B$1295,MATCH($D77,Hierarchy!$A$2:$A$1295,0))="","",INDEX(Hierarchy!$B$2:$B$1295,MATCH($D77,Hierarchy!$A$2:$A$1295,0))),"NODE NOT FOUND")) -> Multi-region | G77: =IF($D77="","",IFERROR(IF(INDEX(Hierarchy!$D$2:$D$1295,MATCH($D77,Hierarchy!$A$2:$A$1295,0))="","",INDEX(Hierarchy!$D$2:$D$1295,MATCH($D77,Hierarchy!$A$2:$A$1295,0))),"NODE NOT FOUND")) -> Multi-region | H77: =IF($D77="","",IFERROR(IF(INDEX(Hierarchy!$E$2:$E$1295,MATCH($D77,Hierarchy!$A$2:$A$1295,0))="","",INDEX(Hierarchy!$E$2:$E$1295,MATCH($D77,Hierarchy!$A$2:$A$1295,0))),"NODE NOT FOUND")) | I77: =IF($D77="","",IFERROR(IF(INDEX(Hierarchy!$F$2:$F$1295,MATCH($D77,Hierarchy!$A$2:$A$1295,0))="","",INDEX(Hierarchy!$F$2:$F$1295,MATCH($D77,Hierarchy!$A$2:$A$1295,0))),"NODE NOT FOUND")) | J77: =IF($D77="","",IFERROR(IF(INDEX(Hierarchy!$G$2:$G$1295,MATCH($D77,Hierarchy!$A$2:$A$1295,0))="","",INDEX(Hierarchy!$G$2:$G$1295,MATCH($D77,Hierarchy!$A$2:$A$1295,0))),"NODE NOT FOUND")) | K77: =IF($D77="","",IFERROR(IF(INDEX(Hierarchy!$H$2:$H$1295,MATCH($D77,Hierarchy!$A$2:$A$1295,0))="","",INDEX(Hierarchy!$H$2:$H$1295,MATCH($D77,Hierarchy!$A$2:$A$1295,0))),"NODE NOT FOUND")) | L77: =IF($D77="","",IFERROR(IF(INDEX(Hierarchy!$I$2:$I$1295,MATCH($D77,Hierarchy!$A$2:$A$1295,0))="","",INDEX(Hierarchy!$I$2:$I$1295,MATCH($D77,Hierarchy!$A$2:$A$1295,0))),"NODE NOT FOUND")) | M77: =IF(B77="Pre-seeded","Pre-seeded",IF(B77="Review 2026-09-16","Added from review",IF(C77="","New",IF(C77=D77,"","Changed")))) -> Pre-seeded | N77: =TRIM(SUBSTITUTE(SUBSTITUTE(SUBSTITUTE(" "&TRIM(SUBSTITUTE(SUBSTITUTE(SUBSTITUTE(SUBSTITUTE(SUBSTITUTE(SUBSTITUTE(SUBSTITUTE(SUBSTITUTE(SUBSTITUTE(SUBSTITUTE(SUBSTITUTE(SUBSTITUTE(SUBSTITUTE(SUBSTITUTE(SUBSTITUTE(UPPER(TRIM(A77)),"[MEMBER]",""),"{MEMBER}",""),"[MEMBER}",""),"MEMBER]",""),"(A)",""),"""",""),"“",""),"”",""),".",""),":",""),",",""),"–"," "),"-"," "),"/"," "),"&"," AND "))&" "," THE "," ")," TOTAL "," ")," OPERATIONS "," ")) -> APAC AND LATIN AMERICA | O77: =IF(COUNTIFS($N$2:$N$2000,N77,$D$2:$D$2000,"<>"&D77)>0,"CONFLICT","")
A78: APAC Geographic Region | B78: Mapping | C78: Asia Pacific (APAC) | D78: APAC (Asia-Pacific) | E78: Exact | F78: =IF($D78="","",IFERROR(IF(INDEX(Hierarchy!$B$2:$B$1295,MATCH($D78,Hierarchy!$A$2:$A$1295,0))="","",INDEX(Hierarchy!$B$2:$B$1295,MATCH($D78,Hierarchy!$A$2:$A$1295,0))),"NODE NOT FOUND")) -> Region | G78: =IF($D78="","",IFERROR(IF(INDEX(Hierarchy!$D$2:$D$1295,MATCH($D78,Hierarchy!$A$2:$A$1295,0))="","",INDEX(Hierarchy!$D$2:$D$1295,MATCH($D78,Hierarchy!$A$2:$A$1295,0))),"NODE NOT FOUND")) -> APAC | H78: =IF($D78="","",IFERROR(IF(INDEX(Hierarchy!$E$2:$E$1295,MATCH($D78,Hierarchy!$A$2:$A$1295,0))="","",INDEX(Hierarchy!$E$2:$E$1295,MATCH($D78,Hierarchy!$A$2:$A$1295,0))),"NODE NOT FOUND")) | I78: =IF($D78="","",IFERROR(IF(INDEX(Hierarchy!$F$2:$F$1295,MATCH($D78,Hierarchy!$A$2:$A$1295,0))="","",INDEX(Hierarchy!$F$2:$F$1295,MATCH($D78,Hierarchy!$A$2:$A$1295,0))),"NODE NOT FOUND")) | J78: =IF($D78="","",IFERROR(IF(INDEX(Hierarchy!$G$2:$G$1295,MATCH($D78,Hierarchy!$A$2:$A$1295,0))="","",INDEX(Hierarchy!$G$2:$G$1295,MATCH($D78,Hierarchy!$A$2:$A$1295,0))),"NODE NOT FOUND")) | K78: =IF($D78="","",IFERROR(IF(INDEX(Hierarchy!$H$2:$H$1295,MATCH($D78,Hierarchy!$A$2:$A$1295,0))="","",INDEX(Hierarchy!$H$2:$H$1295,MATCH($D78,Hierarchy!$A$2:$A$1295,0))),"NODE NOT FOUND")) | L78: =IF($D78="","",IFERROR(IF(INDEX(Hierarchy!$I$2:$I$1295,MATCH($D78,Hierarchy!$A$2:$A$1295,0))="","",INDEX(Hierarchy!$I$2:$I$1295,MATCH($D78,Hierarchy!$A$2:$A$1295,0))),"NODE NOT FOUND")) | M78: =IF(B78="Pre-seeded","Pre-seeded",IF(B78="Review 2026-09-16","Added from review",IF(C78="","New",IF(C78=D78,"","Changed")))) -> Changed | N78: =TRIM(SUBSTITUTE(SUBSTITUTE(SUBSTITUTE(" "&TRIM(SUBSTITUTE(SUBSTITUTE(SUBSTITUTE(SUBSTITUTE(SUBSTITUTE(SUBSTITUTE(SUBSTITUTE(SUBSTITUTE(SUBSTITUTE(SUBSTITUTE(SUBSTITUTE(SUBSTITUTE(SUBSTITUTE(SUBSTITUTE(SUBSTITUTE(UPPER(TRIM(A78)),"[MEMBER]",""),"{MEMBER}",""),"[MEMBER}",""),"MEMBER]",""),"(A)",""),"""",""),"“",""),"”",""),".",""),":",""),",",""),"–"," "),"-"," "),"/"," "),"&"," AND "))&" "," THE "," ")," TOTAL "," ")," OPERATIONS "," ")) -> APAC GEOGRAPHIC REGION | O78: =IF(COUNTIFS($N$2:$N$2000,N78,$D$2:$D$2000,"<>"&D78)>0,"CONFLICT","")
A79: APAC, Middle East and Africa (APMEA) | B79: Pre-seeded | D79: APAC, Middle East and Africa (APMEA) | E79: Exact | F79: =IF($D79="","",IFERROR(IF(INDEX(Hierarchy!$B$2:$B$1295,MATCH($D79,Hierarchy!$A$2:$A$1295,0))="","",INDEX(Hierarchy!$B$2:$B$1295,MATCH($D79,Hierarchy!$A$2:$A$1295,0))),"NODE NOT FOUND")) -> Multi-region | G79: =IF($D79="","",IFERROR(IF(INDEX(Hierarchy!$D$2:$D$1295,MATCH($D79,Hierarchy!$A$2:$A$1295,0))="","",INDEX(Hierarchy!$D$2:$D$1295,MATCH($D79,Hierarchy!$A$2:$A$1295,0))),"NODE NOT FOUND")) -> Multi-region | H79: =IF($D79="","",IFERROR(IF(INDEX(Hierarchy!$E$2:$E$1295,MATCH($D79,Hierarchy!$A$2:$A$1295,0))="","",INDEX(Hierarchy!$E$2:$E$1295,MATCH($D79,Hierarchy!$A$2:$A$1295,0))),"NODE NOT FOUND")) | I79: =IF($D79="","",IFERROR(IF(INDEX(Hierarchy!$F$2:$F$1295,MATCH($D79,Hierarchy!$A$2:$A$1295,0))="","",INDEX(Hierarchy!$F$2:$F$1295,MATCH($D79,Hierarchy!$A$2:$A$1295,0))),"NODE NOT FOUND")) | J79: =IF($D79="","",IFERROR(IF(INDEX(Hierarchy!$G$2:$G$1295,MATCH($D79,Hierarchy!$A$2:$A$1295,0))="","",INDEX(Hierarchy!$G$2:$G$1295,MATCH($D79,Hierarchy!$A$2:$A$1295,0))),"NODE NOT FOUND")) | K79: =IF($D79="","",IFERROR(IF(INDEX(Hierarchy!$H$2:$H$1295,MATCH($D79,Hierarchy!$A$2:$A$1295,0))="","",INDEX(Hierarchy!$H$2:$H$1295,MATCH($D79,Hierarchy!$A$2:$A$1295,0))),"NODE NOT FOUND")) | L79: =IF($D79="","",IFERROR(IF(INDEX(Hierarchy!$I$2:$I$1295,MATCH($D79,Hierarchy!$A$2:$A$1295,0))="","",INDEX(Hierarchy!$I$2:$I$1295,MATCH($D79,Hierarchy!$A$2:$A$1295,0))),"NODE NOT FOUND")) | M79: =IF(B79="Pre-seeded","Pre-seeded",IF(B79="Review 2026-09-16","Added from review",IF(C79="","New",IF(C79=D79,"","Changed")))) -> Pre-seeded | N79: =TRIM(SUBSTITUTE(SUBSTITUTE(SUBSTITUTE(" "&TRIM(SUBSTITUTE(SUBSTITUTE(SUBSTITUTE(SUBSTITUTE(SUBSTITUTE(SUBSTITUTE(SUBSTITUTE(SUBSTITUTE(SUBSTITUTE(SUBSTITUTE(SUBSTITUTE(SUBSTITUTE(SUBSTITUTE(SUBSTITUTE(SUBSTITUTE(UPPER(TRIM(A79)),"[MEMBER]",""),"{MEMBER}",""),"[MEMBER}",""),"MEMBER]",""),"(A)",""),"""",""),"“",""),"”",""),".",""),":",""),",",""),"–"," "),"-"," "),"/"," "),"&"," AND "))&" "," THE "," ")," TOTAL "," ")," OPERATIONS "," ")) -> APAC MIDDLE EAST AND AFRICA (APMEA) | O79: =IF(COUNTIFS($N$2:$N$2000,N79,$D$2:$D$2000,"<>"&D79)>0,"CONFLICT","")
